Workbook
Name \e: #REF!
Name __________JM1: #REF!
Name __________JM1_1: #REF!
Name __________JM1_10: #REF!
Name __________JM1_6: #REF!
Name __________JM1_8: #REF!
Name __________JM1_9: #REF!
Name __________JM2: #REF!
Name __________JM2_1: #REF!
Name __________JM2_10: #REF!
Name __________JM2_6: #REF!
Name __________JM2_8: #REF!
Name __________JM2_9: #REF!
Name __________JM3: #REF!
Name __________JM3_1: #REF!
Name __________JM3_10: #REF!
Name __________JM3_6: #REF!
Name __________JM3_8: #REF!
Name __________JM3_9: #REF!
Name __________JM4: #REF!
Name __________JM4_1: #REF!
Name __________JM4_10: #REF!
Name __________JM4_6: #REF!
Name __________JM4_8: #REF!
Name __________JM4_9: #REF!
Name __________JM5: #REF!
Name __________JM5_1: #REF!
Name __________JM5_10: #REF!
Name __________JM5_6: #REF!
Name __________JM5_8: #REF!
Name __________JM5_9: #REF!
Name __________JM6: #REF!
Name __________JM6_1: #REF!
Name __________JM6_10: #REF!
Name __________JM6_6: #REF!
Name __________JM6_8: #REF!
Name __________JM6_9: #REF!
Name __________PM1: #REF!
Name __________PM1_1: #REF!
Name __________PM1_10: #REF!
Name __________PM1_6: #REF!
Name __________PM1_8: #REF!
Name __________PM1_9: #REF!
Name __________PM2: #REF!
Name __________PM2_1: #REF!
Name __________PM2_10: #REF!
Name __________PM2_6: #REF!
Name __________PM2_8: #REF!
Name __________PM2_9: #REF!
Name __________PM3: #REF!
Name __________PM3_1: #REF!
Name __________PM3_10: #REF!
Name __________PM3_6: #REF!
Name __________PM3_8: #REF!
Name __________PM3_9: #REF!
Name __________PM4: #REF!
Name __________PM4_1: #REF!
Name __________PM4_10: #REF!
Name __________PM4_6: #REF!
Name __________PM4_8: #REF!

Sheet CONFIG
B1: INFORMAR MEDIÇÃO | I1: vigência
B2: 4
N3: =N7/N6 -> 0.22988506 | O3: ="PRAZO DE VIGÊNCIA - 0"&DAY(O6)&"/"&MONTH(O6)&"/"&YEAR(O6) -> PRAZO DE VIGÊNCIA - 04/12/2028
N4: =1-N3 -> 0.77011494 | O4: ="VIGÊNCIA DECORRIDA - "&N7&" DIAS" -> VIGÊNCIA DECORRIDA - 280 DIAS
O5: ="VIGÊNCIA RESTANTE - "&N6-N7&" DIAS" -> VIGÊNCIA RESTANTE - 938 DIAS
I6: PRAZO DE VIGÊNCIA | L6: ='RESUM.'!I24 -> 45873 | N6: =O6-L6 -> 1218 | O6: ='RESUM.'!AC24 -> 47091
B7: EAP ORÇAMENTO | I7: VIGÊNCIA DECORRIDA | N7: =O7-L6 -> 280 | O7: =TODAY() -> 46153
A8: 1 | B8: SERVIÇOS PRELIMINARES | C8: =VLOOKUP(A8,'EAP DE MEDIÇÃO'!$B$12:$DM$268,116,0) -> 0.99046778 | D8: =VLOOKUP(A8,'EAP DE MEDIÇÃO'!B12:DM268,114,0) -> 678310.22
A9: 2 | B9: ADMINISTRAÇÃO DA OBRA | C9: =VLOOKUP(A9,'EAP DE MEDIÇÃO'!$B$12:$DM$268,116,0) -> 0.082108315 | D9: =VLOOKUP(A9,'EAP DE MEDIÇÃO'!B13:DM269,114,0) -> 191575.6
A10: 3 | B10: FUNDAÇÕES E ESTRUTURAS | C10: =VLOOKUP(A10,'EAP DE MEDIÇÃO'!$B$12:$DM$268,116,0) -> 0.24320415 | D10: =VLOOKUP(A10,'EAP DE MEDIÇÃO'!B14:DM270,114,0) -> 1475681.9 | I10: execução
A11: 4 | B11: ARQUITETURA E ELEMENTOS DE URBANISMO | C11: =VLOOKUP(A11,'EAP DE MEDIÇÃO'!$B$12:$DM$268,116,0) -> 0 | D11: =VLOOKUP(A11,'EAP DE MEDIÇÃO'!B15:DM271,114,0) -> 0 | N11: =N15/N14 -> 0.13868613 | O11: ="PRAZO DE EXECUÇÃO - "&DAY(O14)&"/"&MONTH(O14)&"/"&YEAR(O14) -> PRAZO DE EXECUÇÃO - 10/12/2028
A12: 5 | B12: INSTALAÇÕES HIDROSSANITARIAS | C12: =VLOOKUP(A12,'EAP DE MEDIÇÃO'!$B$12:$DM$268,116,0) -> 0 | D12: =VLOOKUP(A12,'EAP DE MEDIÇÃO'!B16:DM272,114,0) -> 0 | N12: =1-N11 -> 0.86131387 | O12: ="EXECUÇÃO DECORRIDA - "&N15&" DIAS" -> EXECUÇÃO DECORRIDA - 152 DIAS
A13: 6 | B13: INSTALAÇOES ELETRICAS E ELETRONICAS | C13: =VLOOKUP(A13,'EAP DE MEDIÇÃO'!$B$12:$DM$268,116,0) -> 0 | D13: =VLOOKUP(A13,'EAP DE MEDIÇÃO'!B17:DM273,114,0) -> 0 | O13: ="EXECUÇÃO RESTANTE - "&N14-N15&" DIAS" -> EXECUÇÃO RESTANTE - 944 DIAS
A14: 7 | B14: EQUIPAMENTOS - INSTALAÇÕES MECÂNICAS E UTILIDADES | C14: =VLOOKUP(A14,'EAP DE MEDIÇÃO'!$B$12:$DM$268,116,0) -> 0 | D14: =VLOOKUP(A14,'EAP DE MEDIÇÃO'!B18:DM274,114,0) -> 0 | I14: PRAZO DE EXECUÇÃO | L14: ='RESUM.'!I28 -> 46001 | N14: =O14-L14 -> 1096 | O14: ='RESUM.'!J29 -> 47097
A15: 8 | B15: PREVENÇÃO DE COMBATE A INCENDIO | C15: =VLOOKUP(A15,'EAP DE MEDIÇÃO'!$B$12:$DM$268,116,0) -> 0 | D15: =VLOOKUP(A15,'EAP DE MEDIÇÃO'!B19:DM275,114,0) -> 0 | I15: EXECUÇÃO DECORRIDA | N15: =O15-L14 -> 152 | O15: =TODAY() -> 46153
A16: 9 | B16: SERVIÇOS COMPLEMENTARES | C16: =VLOOKUP(A16,'EAP DE MEDIÇÃO'!$B$12:$DM$268,116,0) -> 0 | D16: =VLOOKUP(A16,'EAP DE MEDIÇÃO'!B20:DM276,114,0) -> 0
A17: 10 | B17: USINA FOTOVOLTAICA | C17: =VLOOKUP(A17,'EAP DE MEDIÇÃO'!$B$12:$DM$268,116,0) -> 0 | D17: =VLOOKUP(A17,'EAP DE MEDIÇÃO'!B21:DM277,114,0) -> 0
B19: 1 | I19: avanço físico da obra
B20: 2
B21: 3 | I21: AVANÇ. REAL. | K21: AVANÇ. PLAN.
B22: 4 | I22: =VLOOKUP(B2,'RESUM.'!$D$52:$R$87,14,0) -> 0.046795872 | K22: =HLOOKUP(B2,'CRONOGRAMA DE METAS'!$G$8:$DJ$272,265,0) -> 0.033904196
B23: 5 | I23: =1-K22 -> 0.9660958 | K23: =1-I22 -> 0.95320413
B24: 6
B25: 7
B26: 8 | I26: idp
B27: 9 | J27: IDP | M27: =IF((VLOOKUP(CONFIG!B2,'RESUM.'!$D$52:$AD$87,24,0))/(HLOOKUP(B2,'CRONOGRAMA DE METAS'!$G$8:$DJ$273,264,0))<=2,(VLOOKUP(CONFIG!B2,'RESUM.'!$D$52:$AD$87,24,0))/(HLOOKUP(B2,'CRONOGRAMA DE METAS'!$G$8:$DJ$273,264,0)),"2,00") -> 1
B28: 10 | P28: =IF(M27<0.95,"OBRA ATRASADA",IF(AND(M27>=0.95,M27<=1.05),"OBRA NO PRAZO","OBRA ADIANTADA")) -> OBRA NO PRAZO
B29: 11 | I29: % | J29: SETA | M29: OCULTA
B30: 12 | I30: =(M27/2)-(0.5/100) -> 0.495 | J30: 0.01 | M30: =2-I30-J30 -> 1.495
B31: 13
B32: 14
B33: 15 | I33: tendência de término
B34: 16 | I34: duração da obra (d) | L34: =('RESUM.'!$J$29-'RESUM.'!$I$28)-'RESUM.'!U28 -> 1096 | P34: =IF('RESUM.'!R29="CONCLUÍDA","OBRA CONCLUÍDA","TENDÊNCIA DE DURAÇÃO DA OBRA - "&L35&" DIAS") -> TENDÊNCIA DE DURAÇÃO DA OBRA - 1096 DIAS
B35: 17 | I35: nova duração (d) | L35: =ROUNDDOWN(L34/M27,0) -> 1096 | N35: duração / idp | P35: =IF('RESUM.'!R29="CONCLUÍDA","-","TENDÊNCIA DE TÉRMINO DA OBRA - "&DAY(L37)&"/"&MONTH(L37)&"/"&YEAR(L37)) -> TENDÊNCIA DE TÉRMINO DA OBRA - 10/12/2028
B36: 18 | I36: nova duração (MêS) | L36: =ROUND(L35/30,2) -> 36.53
B37: 19 | I37: nova data de término | L37: ='RESUM.'!I28+'RESUM.'!U28+L35 -> 47097
B38: 20
B39: 21
B40: 22
B41: 23
B42: 24
B43: 25
B44: 26 | I44: CRONOGRAMA ATUAL DO CONTRATO
B45: 27
B46: 28 | N46: 1 | O46: 2 | P46: 3 | Q46: 4 | R46: 5 | S46: 6 | T46: 7 | U46: 8 | V46: 9 | W46: 10 | X46: 11 | Y46: 12 | Z46: 13 | AA46: 14 | AB46: 15 | AC46: 16 | AD46: 17 | AE46: 18 | AF46: 19 | AG46: 20 | AH46: 21 | AI46: 22 | AJ46: 23 | AK46: 24 | AL46: 25 | AM46: 26 | AN46: 27 | AO46: 28 | AP46: 29 | AQ46: 30 | AR46: 31 | AS46: 32 | AT46: 33 | AU46: 34 | AV46: 35 | AW46: 36
B47: 29
B48: 30 | I48: VALOR PLANEJADO (PROP.) | N48: =HLOOKUP(N46,'CRONOGRAMA DE METAS'!$G$8:$DJ$273,263,0) -> 0 | O48: =HLOOKUP(O46,'CRONOGRAMA DE METAS'!$G$8:$DJ$273,263,0) -> 0 | P48: =HLOOKUP(P46,'CRONOGRAMA DE METAS'!$G$8:$DJ$273,263,0) -> 368273.27 | Q48: =HLOOKUP(Q46,'CRONOGRAMA DE METAS'!$G$8:$DJ$273,263,0) -> 968532.67 | R48: =HLOOKUP(R46,'CRONOGRAMA DE METAS'!$G$8:$DJ$273,263,0) -> 1008761.8 | S48: =HLOOKUP(S46,'CRONOGRAMA DE METAS'!$G$8:$DJ$273,263,0) -> 241632.87 | T48: =HLOOKUP(T46,'CRONOGRAMA DE METAS'!$G$8:$DJ$273,263,0) -> 222386.7 | U48: =HLOOKUP(U46,'CRONOGRAMA DE METAS'!$G$8:$DJ$273,263,0) -> 60588.7 | ... AW48: =HLOOKUP(AW46,'CRONOGRAMA DE METAS'!$G$8:$DJ$273,263,0) -> 1488541.7
B49: 31 | I49: VALOR PLANEJADO ACUM. | N49: =HLOOKUP(N46,'CRONOGRAMA DE METAS'!$G$8:$DJ$273,264,0) -> 0 | O49: =HLOOKUP(O46,'CRONOGRAMA DE METAS'!$G$8:$DJ$273,264,0) -> 0 | P49: =HLOOKUP(P46,'CRONOGRAMA DE METAS'!$G$8:$DJ$273,264,0) -> 368273.27 | Q49: =HLOOKUP(Q46,'CRONOGRAMA DE METAS'!$G$8:$DJ$273,264,0) -> 1336805.9 | R49: =HLOOKUP(R46,'CRONOGRAMA DE METAS'!$G$8:$DJ$273,264,0) -> 2345567.7 | S49: =HLOOKUP(S46,'CRONOGRAMA DE METAS'!$G$8:$DJ$273,264,0) -> 2587200.6 | T49: =HLOOKUP(T46,'CRONOGRAMA DE METAS'!$G$8:$DJ$273,264,0) -> 2809587.3 | U49: =HLOOKUP(U46,'CRONOGRAMA DE METAS'!$G$8:$DJ$273,264,0) -> 2870176 | ... AW49: =HLOOKUP(AW46,'CRONOGRAMA DE METAS'!$G$8:$DJ$273,264,0) -> 28566749
B50: 32 | I50: VALOR MEDIDO | N50: =IF((VLOOKUP(N46,'RESUM.'!$D$52:$AD$87,16,0))<1,"",VLOOKUP(N46,'RESUM.'!$D$52:$AD$87,16,0)) | O50: =IF((VLOOKUP(O46,'RESUM.'!$D$52:$AD$87,16,0))<1,"",VLOOKUP(O46,'RESUM.'!$D$52:$AD$87,16,0)) | P50: =IF((VLOOKUP(P46,'RESUM.'!$D$52:$AD$87,16,0))<1,"",VLOOKUP(P46,'RESUM.'!$D$52:$AD$87,16,0)) -> 368273.27 | Q50: =IF((VLOOKUP(Q46,'RESUM.'!$D$52:$AD$87,16,0))<1,"",VLOOKUP(Q46,'RESUM.'!$D$52:$AD$87,16,0)) -> 968532.67 | R50: =IF((VLOOKUP(R46,'RESUM.'!$D$52:$AD$87,16,0))<1,"",VLOOKUP(R46,'RESUM.'!$D$52:$AD$87,16,0)) -> 1008761.8 | S50: =IF((VLOOKUP(S46,'RESUM.'!$D$52:$AD$87,16,0))<1,"",VLOOKUP(S46,'RESUM.'!$D$52:$AD$87,16,0)) -> #REF! | T50: =IF((VLOOKUP(T46,'RESUM.'!$D$52:$AD$87,16,0))<1,"",VLOOKUP(T46,'RESUM.'!$D$52:$AD$87,16,0)) -> #REF! | U50: =IF((VLOOKUP(U46,'RESUM.'!$D$52:$AD$87,16,0))<1,"",VLOOKUP(U46,'RESUM.'!$D$52:$AD$87,16,0)) -> #REF! | ... AW50: =IF((VLOOKUP(AW46,'RESUM.'!$D$52:$AD$87,16,0))<1,"",VLOOKUP(AW46,'RESUM.'!$D$52:$AD$87,16,0)) -> #REF!
B51: 33 | I51: VALOR MEDIDO ACUM. | N51: =IF(N50="","",VLOOKUP(N46,'RESUM.'!$D$52:$AD$87,24,0)) | P51: =IF((VLOOKUP(P46,'RESUM.'!$D$52:$AD$87,26,0))<1,"",VLOOKUP(P46,'RESUM.'!$D$52:$AD$87,24,0)) -> 368273.27 | Q51: =IF((VLOOKUP(Q46,'RESUM.'!$D$52:$AD$87,26,0))<1,"",VLOOKUP(Q46,'RESUM.'!$D$52:$AD$87,24,0)) -> 1336805.9
B52: 34 | I52: % FÍSICO PLANEJADO
B53: 35 | I53: % FÍSICO PLANEJADO ACUM.
B54: 36 | I54: % FÍSICO MEDIDO
I55: % FÍSICO MEDIDO ACUM.

Sheet CAPA MEDIÇÃO
A17: =CONFIG!B2 -> 4
A18: =VLOOKUP(CONFIG!B2,'RESUM.'!$D$52:$AD$90,5,0) -> 46082 | E18: A | F18: =VLOOKUP(CONFIG!B2,'RESUM.'!$D$52:$AD$90,8,0) -> 46112
A22: ='RESUM.'!H9 -> CONSTRUÇÃO DA NOVA SEDE DA JUSTIÇA FEDERAL EM JUAZEIRO DO NORTE/CE
T25: 1
A28: ='RESUM.'!D11 -> Nº DO CONTRATO: | F28: ='RESUM.'!H11 -> 25/2025 | T28: 1
T29: 1

Sheet CARTA DE ENTREGA
L2: =DAY('CAPA MEDIÇÃO'!F18)&"/"&MONTH('CAPA MEDIÇÃO'!F18)&"/"&YEAR('CAPA MEDIÇÃO'!F18) -> 31/3/2026
A6: À Justiça federal de primeira instância no estado do ceará
A8: Ref.: | B8: ='RESUM.'!H11&" - "&'RESUM.'!H9 -> 25/2025 - CONSTRUÇÃO DA NOVA SEDE DA JUSTIÇA FEDERAL EM JUAZEIRO DO NORTE/CE
A10: Empresa: | B10: ='RESUM.'!H13&" - "&'RESUM.'!Y13 -> CONSÓRCIO JUAZEIRO DO NORTE - 62.009.288/0001-12
A12: Assunto: | B12: ='CAPA MEDIÇÃO'!A17 -> 4
A14: Senhor(a) Coordenador(a),
A16: ="Encaminhamos em anexo a medição de nº "&B12&" do contrato em referência, relativa ao período de "&DAY('CAPA MEDIÇÃO'!A18)&"/"&MONTH('CAPA MEDIÇÃO'!A18)&"/"&YEAR('CAPA MEDIÇÃO'!A18)&" a "&DAY('CAPA MEDIÇÃO'!F18)&"/"&MONTH('CAPA MEDIÇÃO'!F18)&"/"&YEAR('CAPA MEDIÇÃO'!F18)&", no valor de "&TEXT(HLOOKUP(B12,CONFIG!$N$46:$AW$50,5,0),"R$ #.##0,00")&"." -> Encaminhamos em anexo a medição de nº 4 do contrato em referência, relativa ao período de 1/3/2026 a 31/3/2026, no valor de R$ 968.532,67.
T25: 1
H26: =DATEVALUE(L2) -> 46112
A28: Atenciosamente, | T28: 1
T29: 1
A32: =B10 -> CONSÓRCIO JUAZEIRO DO NORTE - 62.009.288/0001-12

Sheet RESUM.
D4: JUSTIÇA FEDERAL DE PRIMEIRA INSTÂNCIA NO ESTADO DO CEARÁ
D6: RELATÓRIO DE CONTROLE DO CONTRATO
D8: INFORMAÇÕES DO CONTRATO
D9: OBJETO: | H9: CONSTRUÇÃO DA NOVA SEDE DA JUSTIÇA FEDERAL EM JUAZEIRO DO NORTE/CE
D10: ENDEREÇO: | H10: RUAS JOSÉ GERALDO DA CRUZ (L) COM A RUA PRESIDENTE MÉDICI (O), NA RUA MANOEL PIRES (N) COM A RUA FREI DAMIÃO (S), BAIRRO LAGOA SECA NO MUNICÍPIO DE JUAZEIRO DO NORTE-CE
D11: Nº DO CONTRATO: | H11: 25/2025 | N11: CONCORRÊNCIA PÚBLICA: | R11: 90001/2025 | X11: CNO DA OBRA: | AB11: 90.025.93927/72
D12: SECRETARIA GESTORA:
D13: EMPRESA CONTRATADA: | H13: CONSÓRCIO JUAZEIRO DO NORTE | V13: CNPJ.: | Y13: 62.009.288/0001-12
D14: RECURSO: | P14: ÓRGÃO CONCEDENTE: | Y14: Nº CONVÊNIO: | AB14: PT
D15: GESTOR DO CONTRATO: | M15: FISCAL DO CONTRATO: | T15: FISCAL DA OBRA: | AB15: ENG. CIVIL
AB16: ENG. ELETRICISTA
M17: FISCAL RESERVA: | T17: FISCAL RESERVA: | AB17: ENG. CIVIL
D19: VALOR DO CONTRATO
D20: VALOR INICIAL DO CONTRATO: | H20: 28566749 | K20: VALOR DE REPASSE: | S20: =P20/H20 -> 0 | U20: VALOR DE CONTRAPARTIDA: | AC20: =Z20/H20 -> 0
D21: VALOR ATUAL DO CONTRATO: | H21: =H20+SUM(Y37:AA47) -> 28566749 | K21: VALOR DE REPASSE: | S21: =P21/H21 -> 0 | U21: VALOR DE CONTRAPARTIDA: | AC21: =Z21/H21 -> 0
D23: PRAZO DE VIGÊNCIA DO CONTRATO
D24: DATA DA ASSINATURA DO CONTRATO: | I24: 45873 | K24: PERÍODO DE VIGÊNCIA DO CONTRATO: | O24: 40 | P24: MESES | Q24: PERÍODO DE VIGÊNCIA ADITIVADO AO CONTRATO: | U24: 0 | V24: MESES | W24: DATA DO TÉRMINO DA VIGÊNGIA DO CONTRATO: | AC24: =EDATE(I24,O24+U24) -> 47091
D25: SITUAÇÃO DO CONTRATO: | M25: VIGENTE | S25: PRAZO RESTANTE DE VIGÊNCIA DO CONTRATO (DIAS): | AC25: =CONFIG!N6-CONFIG!N7 -> 938
D27: PRAZO DE EXECUÇÃO DO CONTRATO
D28: DATA DA ORDEM DE SERVIÇO: | I28: 46001 | K28: PRAZO DE EXECUÇÃO : | O28: 36 | P28: MESES | Q28: TOTAL DE DIAS PARALISADOS: | U28: =SUM(U33:W33) -> 0 | V28: PERÍODO DE EXECUÇÃO ADITIVADO AO CONTRATO: | AD28: MESES
D29: DATA DO TÉRMINO DA EXECUÇÃO DA OBRA: | J29: =EDATE(I28,O28+AC28)+U28 -> 47097 | M29: SITUAÇÃO DA OBRA: | R29: NÃO INICIADA | U29: PRAZO RESTANTE DE EXECUÇÃO DO CONTRATO (DIAS): | AC29: =CONFIG!N14-CONFIG!N15 -> 944
D31: PARALISAÇÕES
D32: PARALISAÇÕES | G32: DATA DO INÍCIO DA PARALISAÇÃO DA OBRA | N32: DATA DO REINÍCIO DA OBRA | U32: DIAS DE PARALISAÇÃO | X32: MOTIVO
U33: =N33-G33 -> 0
D35: ADITIVOS
D36: DATA | F36: Nº | G36: OBJETO | M36: INÍCIO DO ADITIVO DE PRAZO | P36: TÉRMINO DO ADITIVO DE PRAZO | S36: VALORES ACRÉSCIDOS | V36: VALORES REDUZIDOS | Y36: VALOR DO ADITIVO | AB36: % ADITIVADO
K38: MESES | Y38: =S38-V38 -> 0 | AB38: =ROUND(Y38/$H$20,4) -> 0
K39: MESES | Y39: =S39-V39 -> 0 | AB39: =ROUND(Y39/$H$20,4) -> 0
K40: MESES | Y40: =S40-V40 -> 0 | AB40: =ROUND(Y40/$H$20,4) -> 0
K41: MESES | Y41: =S41-V41 -> 0 | AB41: =ROUND(Y41/$H$20,4) -> 0
Y42: =S42-V42 -> 0 | AB42: =ROUND(Y42/$H$20,4) -> 0
K43: MESES | Y43: =S43-V43 -> 0 | AB43: =ROUND(Y43/$H$20,4) -> 0
K44: MESES | Y44: =S44-V44 -> 0 | AB44: =ROUND(Y44/$H$20,4) -> 0
Y45: =S45-V45 -> 0 | AB45: =ROUND(Y45/$H$20,4) -> 0
Y47: =S47-V47 -> 0 | AB47: =ROUND(Y47/$H$20,4) -> 0
D49: MEDIÇÕES
D50: MEDIÇÃO | F50: DATA DE EMISSÃO | H50: PERÍODO | M50: % EXEC. ATUAL | O50: % EXEC. ANTER. | Q50: % EXEC. ACUM. | S50: VALOR MEDIDO | Y50: VALOR ACUMUL. DA MEDIÇÃO ANTERIOR | AA50: VALOR DA MEDIÇÃO ATUAL ACUMULADO | AC50: VALOR DO SALDO CONTRATUAL
D52: 1 | H52: =HLOOKUP(D52,'CRONOGRAMA DE METAS'!$G$8:$DJ$10,2,0) -> 46001 | J52: a | K52: =HLOOKUP(D52,'CRONOGRAMA DE METAS'!$G$8:$DJ$10,3,0) -> 46022 | M52: =S52/$H$21 -> 0 | O52: =Y52/$H$21 -> 0 | Q52: =AA52/$H$21 -> 0 | S52: =HLOOKUP(D52,'EAP DE MEDIÇÃO'!$G$8:$DJ$272,264,0) -> 0 | Y52: 0 | AA52: =S52+Y52 -> 0 | AC52: =$H$21-AA52 -> 28566749
D53: 2 | H53: =HLOOKUP(D53,'CRONOGRAMA DE METAS'!$G$8:$DJ$10,2,0) -> 46023 | J53: a | K53: =HLOOKUP(D53,'CRONOGRAMA DE METAS'!$G$8:$DJ$10,3,0) -> 46053 | M53: =S53/$H$21 -> 0 | O53: =Y53/$H$21 -> 0 | Q53: =AA53/$H$21 -> 0 | S53: =HLOOKUP(D53,'EAP DE MEDIÇÃO'!$G$8:$DJ$272,264,0) -> 0 | Y53: =AA52 -> 0 | AA53: =S53+Y53 -> 0 | AC53: =$H$21-AA53 -> 28566749
D54: 3 | H54: =HLOOKUP(D54,'CRONOGRAMA DE METAS'!$G$8:$DJ$10,2,0) -> 46054 | J54: a | K54: =HLOOKUP(D54,'CRONOGRAMA DE METAS'!$G$8:$DJ$10,3,0) -> 46081 | M54: =S54/$H$21 -> 0.012891676 | O54: =Y54/$H$21 -> 0 | Q54: =AA54/$H$21 -> 0.012891676 | S54: =HLOOKUP(D54,'EAP DE MEDIÇÃO'!$G$8:$DJ$272,263,0) -> 368273.27 | Y54: =AA53 -> 0 | AA54: =S54+Y54 -> 368273.27 | AC54: =$H$21-AA54 -> 28198476
D55: 4 | H55: =HLOOKUP(D55,'CRONOGRAMA DE METAS'!$G$8:$DJ$10,2,0) -> 46082 | J55: a | K55: =HLOOKUP(D55,'CRONOGRAMA DE METAS'!$G$8:$DJ$10,3,0) -> 46112 | M55: =S55/$H$21 -> 0.033904196 | O55: =Y55/$H$21 -> 0.012891676 | Q55: =AA55/$H$21 -> 0.046795872 | S55: =HLOOKUP(D55,'EAP DE MEDIÇÃO'!$G$8:$DJ$272,263,0) -> 968532.67 | Y55: =AA54 -> 368273.27 | AA55: =S55+Y55 -> 1336805.9 | AC55: =$H$21-AA55 -> 27229943
D56: 5 | H56: =HLOOKUP(D56,'CRONOGRAMA DE METAS'!$G$8:$DJ$10,2,0) -> 46113 | J56: a | K56: =HLOOKUP(D56,'CRONOGRAMA DE METAS'!$G$8:$DJ$10,3,0) -> 46142 | M56: =S56/$H$21 -> 0.035312446 | O56: =Y56/$H$21 -> 0.046795872 | Q56: =AA56/$H$21 -> 0.082108317 | S56: =HLOOKUP(D56,'EAP DE MEDIÇÃO'!$G$8:$DJ$272,263,0) -> 1008761.8 | Y56: =AA55 -> 1336805.9 | AA56: =S56+Y56 -> 2345567.7 | AC56: =$H$21-AA56 -> 26221182
D57: 6 | H57: =HLOOKUP(D57,'CRONOGRAMA DE METAS'!$G$8:$DJ$10,2,0) -> 46143 | J57: a | K57: =HLOOKUP(D57,'CRONOGRAMA DE METAS'!$G$8:$DJ$10,3,0) -> 46173 | M57: =S57/$H$21 -> #REF! | O57: =Y57/$H$21 -> 0.082108317 | Q57: =AA57/$H$21 -> #REF! | S57: =HLOOKUP(D57,#REF!,697,0) -> #REF! | Y57: =AA56 -> 2345567.7 | AA57: =S57+Y57 -> #REF! | AC57: =$H$21-AA57 -> #REF!
D58: 7 | H58: =HLOOKUP(D58,'CRONOGRAMA DE METAS'!$G$8:$DJ$10,2,0) -> 46174 | J58: a | K58: =HLOOKUP(D58,'CRONOGRAMA DE METAS'!$G$8:$DJ$10,3,0) -> 46203 | M58: =S58/$H$21 -> #REF! | O58: =Y58/$H$21 -> #REF! | Q58: =AA58/$H$21 -> #REF! | S58: =HLOOKUP(D58,#REF!,697,0) -> #REF! | Y58: =AA57 -> #REF! | AA58: =S58+Y58 -> #REF! | AC58: =$H$21-AA58 -> #REF!
D59: 8 | H59: =HLOOKUP(D59,'CRONOGRAMA DE METAS'!$G$8:$DJ$10,2,0) -> 46204 | J59: a | K59: =HLOOKUP(D59,'CRONOGRAMA DE METAS'!$G$8:$DJ$10,3,0) -> 46234 | M59: =S59/$H$21 -> #REF! | O59: =Y59/$H$21 -> #REF! | Q59: =AA59/$H$21 -> #REF! | S59: =HLOOKUP(D59,#REF!,697,0) -> #REF! | Y59: =AA58 -> #REF! | AA59: =S59+Y59 -> #REF! | AC59: =$H$21-AA59 -> #REF!
D60: 9 | H60: =HLOOKUP(D60,'CRONOGRAMA DE METAS'!$G$8:$DJ$10,2,0) -> 46235 | J60: a | K60: =HLOOKUP(D60,'CRONOGRAMA DE METAS'!$G$8:$DJ$10,3,0) -> 46265 | M60: =S60/$H$21 -> #REF! | O60: =Y60/$H$21 -> #REF! | Q60: =AA60/$H$21 -> #REF! | S60: =HLOOKUP(D60,#REF!,697,0) -> #REF! | Y60: =AA59 -> #REF! | AA60: =S60+Y60 -> #REF! | AC60: =$H$21-AA60 -> #REF!
D61: 10 | H61: =HLOOKUP(D61,'CRONOGRAMA DE METAS'!$G$8:$DJ$10,2,0) -> 46266 | J61: a | K61: =HLOOKUP(D61,'CRONOGRAMA DE METAS'!$G$8:$DJ$10,3,0) -> 46295 | M61: =S61/$H$21 -> #REF! | O61: =Y61/$H$21 -> #REF! | Q61: =AA61/$H$21 -> #REF! | S61: =HLOOKUP(D61,#REF!,697,0) -> #REF! | Y61: =AA60 -> #REF! | AA61: =S61+Y61 -> #REF! | AC61: =$H$21-AA61 -> #REF!
D62: 11 | H62: =HLOOKUP(D62,'CRONOGRAMA DE METAS'!$G$8:$DJ$10,2,0) -> 46296 | J62: a | K62: =HLOOKUP(D62,'CRONOGRAMA DE METAS'!$G$8:$DJ$10,3,0) -> 46326 | M62: =S62/$H$21 -> #REF! | O62: =Y62/$H$21 -> #REF! | Q62: =AA62/$H$21 -> #REF! | S62: =HLOOKUP(D62,#REF!,697,0) -> #REF! | Y62: =AA61 -> #REF! | AA62: =S62+Y62 -> #REF! | AC62: =$H$21-AA62 -> #REF!
D63: 12 | H63: =HLOOKUP(D63,'CRONOGRAMA DE METAS'!$G$8:$DJ$10,2,0) -> 46327 | J63: a | K63: =HLOOKUP(D63,'CRONOGRAMA DE METAS'!$G$8:$DJ$10,3,0) -> 46356 | M63: =S63/$H$21 -> #REF! | O63: =Y63/$H$21 -> #REF! | Q63: =AA63/$H$21 -> #REF! | S63: =HLOOKUP(D63,#REF!,697,0) -> #REF! | Y63: =AA62 -> #REF! | AA63: =S63+Y63 -> #REF! | AC63: =$H$21-AA63 -> #REF!
D64: 13 | H64: =HLOOKUP(D64,'CRONOGRAMA DE METAS'!$G$8:$DJ$10,2,0) -> 46357 | J64: a | K64: =HLOOKUP(D64,'CRONOGRAMA DE METAS'!$G$8:$DJ$10,3,0) -> 46387 | M64: =S64/$H$21 -> #REF! | O64: =Y64/$H$21 -> #REF! | Q64: =AA64/$H$21 -> #REF! | S64: =HLOOKUP(D64,#REF!,697,0) -> #REF! | Y64: =AA63 -> #REF! | AA64: =S64+Y64 -> #REF! | AC64: =$H$21-AA64 -> #REF!
D65: 14 | H65: =HLOOKUP(D65,'CRONOGRAMA DE METAS'!$G$8:$DJ$10,2,0) -> 46388 | J65: a | K65: =HLOOKUP(D65,'CRONOGRAMA DE METAS'!$G$8:$DJ$10,3,0) -> 46418 | M65: =S65/$H$21 -> #REF! | O65: =Y65/$H$21 -> #REF! | Q65: =AA65/$H$21 -> #REF! | S65: =HLOOKUP(D65,#REF!,697,0) -> #REF! | Y65: =AA64 -> #REF! | AA65: =S65+Y65 -> #REF! | AC65: =$H$21-AA65 -> #REF!
D66: 15 | H66: =HLOOKUP(D66,'CRONOGRAMA DE METAS'!$G$8:$DJ$10,2,0) -> 46419 | J66: a | K66: =HLOOKUP(D66,'CRONOGRAMA DE METAS'!$G$8:$DJ$10,3,0) -> 46446 | M66: =S66/$H$21 -> #REF! | O66: =Y66/$H$21 -> #REF! | Q66: =AA66/$H$21 -> #REF! | S66: =HLOOKUP(D66,#REF!,697,0) -> #REF! | Y66: =AA65 -> #REF! | AA66: =S66+Y66 -> #REF! | AC66: =$H$21-AA66 -> #REF!
D67: 16 | H67: =HLOOKUP(D67,'CRONOGRAMA DE METAS'!$G$8:$DJ$10,2,0) -> 46447 | J67: a | K67: =HLOOKUP(D67,'CRONOGRAMA DE METAS'!$G$8:$DJ$10,3,0) -> 46477 | M67: =S67/$H$21 -> #REF! | O67: =Y67/$H$21 -> #REF! | Q67: =AA67/$H$21 -> #REF! | S67: =HLOOKUP(D67,#REF!,697,0) -> #REF! | Y67: =AA66 -> #REF! | AA67: =S67+Y67 -> #REF! | AC67: =$H$21-AA67 -> #REF!
D68: 17 | H68: =HLOOKUP(D68,'CRONOGRAMA DE METAS'!$G$8:$DJ$10,2,0) -> 46478 | J68: a | K68: =HLOOKUP(D68,'CRONOGRAMA DE METAS'!$G$8:$DJ$10,3,0) -> 46507 | M68: =S68/$H$21 -> #REF! | O68: =Y68/$H$21 -> #REF! | Q68: =AA68/$H$21 -> #REF! | S68: =HLOOKUP(D68,#REF!,697,0) -> #REF! | Y68: =AA67 -> #REF! | AA68: =S68+Y68 -> #REF! | AC68: =$H$21-AA68 -> #REF!
... D87: 36 | H87: =HLOOKUP(D87,'CRONOGRAMA DE METAS'!$G$8:$DJ$10,2,0) -> 47058 | J87: a | K87: =HLOOKUP(D87,'CRONOGRAMA DE METAS'!$G$8:$DJ$10,3,0) -> 47087 | M87: =S87/$H$21 -> #REF! | O87: =Y87/$H$21 -> #REF! | Q87: =AA87/$H$21 -> #REF! | S87: =HLOOKUP(D87,#REF!,697,0) -> #REF! | Y87: =AA86 -> #REF! | AA87: =S87+Y87 -> #REF! | AC87: =$H$21-AA87 -> #REF!

Sheet EAP DE MEDIÇÃO
B1: EAP DE MEDIÇÃO
B3: Contratada: | F3: 62.009.288/0001-12
B4: Consórcio Juazeiro do Norte
B6: Objeto: | F6: 0.088939789
B7: Construção da Nova Sede da Justiça Federal em Juazeiro do Norte/CE | G7: 45992 | J7: 46023 | M7: 46054 | P7: 46082 | S7: 46113 | V7: 46143 | Y7: 46174 | AB7: 46204 | AE7: 46235 | AH7: 46266 | AK7: 46296 | AN7: 46327 | AQ7: 46357 | AT7: 46388 | AW7: 46419 | AZ7: 46447 | BC7: 46478 | BF7: 46508 | BI7: 46539 | BL7: 46569 | BO7: 46600 | BR7: 46631 | BU7: 46661 | BX7: 46692 | CA7: 46722 | CD7: 46753 | CG7: 46784 | CJ7: 46813 | CM7: 46844 | CP7: 46874 | CS7: 46905 | CV7: 46935 | CY7: 46966 | DB7: 46997 | DE7: 47027 | DH7: 47058 | DK7: Acumulado
G8: 1 | J8: 2 | M8: 3 | P8: 4 | S8: 5 | V8: 6 | Y8: 7 | AB8: 8 | AE8: 9 | AH8: 10 | AK8: 11 | AN8: 12 | AQ8: 13 | AT8: 14 | AW8: 15 | AZ8: 16 | BC8: 17 | BF8: 18 | BI8: 19 | BL8: 20 | BO8: 21 | BR8: 22 | BU8: 23 | BX8: 24 | CA8: 25 | CD8: 26 | CG8: 27 | CJ8: 28 | CM8: 29 | CP8: 30 | CS8: 31 | CV8: 32 | CY8: 33 | DB8: 34 | DE8: 35 | DH8: 36 | DK8: RESUMO MEDIÇÕES
G9: 46001 | H9: =G9 -> 46001 | J9: =EOMONTH(J7,-1)+1 -> 46023 | K9: =J9 -> 46023 | M9: =EOMONTH(M7,-1)+1 -> 46054 | N9: =M9 -> 46054
G10: =EOMONTH(G7,0) -> 46022 | H10: =G10 -> 46022 | J10: =EOMONTH(J7,0) -> 46053 | K10: =J10 -> 46053 | M10: =EOMONTH(M7,0) -> 46081 | N10: =M10 -> 46081
B11: ITEM | C11: DESCRIÇÃO | E11: PREÇO TOTAL R$ | G11: Medido (R$) | H11: % do mês | I11: % acumulado | J11: Medido (R$) | K11: % do mês | L11: % acumulado | M11: Medido (R$) | N11: % do mês | O11: % acumulado | P11: Medido (R$) | Q11: % do mês | R11: % acumulado | S11: Medido (R$) | T11: % do mês | U11: % acumulado | V11: Medido (R$) | W11: % do mês | X11: % acumulado | Y11: Medido (R$) | Z11: % do mês | AA11: % acumulado | AB11: Medido (R$) | AC11: % do mês | AD11: % acumulado | AE11: Medido (R$) | AF11: % do mês | AG11: % acumulado | AH11: Medido (R$) | AI11: % do mês | AJ11: % acumulado | AK11: Medido (R$) | AL11: % do mês | AM11: % acumulado | AN11: Medido (R$) | AO11: % do mês | AP11: % acumulado | AQ11: Medido (R$) | AR11: % do mês | AS11: % acumulado | AT11: Medido (R$) | AU11: % do mês | AV11: % acumulado | AW11: Medido (R$) | AX11: % do mês | AY11: % acumulado | AZ11: Medido (R$) | BA11: % do mês | BB11: % acumulado | BC11: Medido (R$) | BD11: % do mês | BE11: % acumulado | BF11: Medido (R$) | BG11: % do mês | BH11: % acumulado | BI11: Medido (R$) | BJ11: % do mês | BK11: % acumulado | BL11: Medido (R$) | BM11: % do mês | BN11: % acumulado | BO11: Medido (R$) | BP11: % do mês | BQ11: % acumulado | BR11: Medido (R$) | BS11: % do mês | BT11: % acumulado | BU11: Medido (R$) | BV11: % do mês | BW11: % acumulado | BX11: Medido (R$) | BY11: % do mês | BZ11: % acumulado | CA11: Medido (R$) | CB11: % do mês | CC11: % acumulado | CD11: Medido (R$) | CE11: % do mês | CF11: % acumulado | CG11: Medido (R$) | CH11: % do mês | CI11: % acumulado | CJ11: Medido (R$) | CK11: % do mês | CL11: % acumulado | CM11: Medido (R$) | CN11: % do mês | CO11: % acumulado | CP11: Medido (R$) | CQ11: % do mês | CR11: % acumulado | CS11: Medido (R$) | CT11: % do mês | CU11: % acumulado | CV11: Medido (R$) | CW11: % do mês | CX11: % acumulado | CY11: Medido (R$) | CZ11: % do mês | DA11: % acumulado | DB11: Medido (R$) | DC11: % do mês | DD11: % acumulado | DE11: Medido (R$) | DF11: % do mês | DG11: % acumulado | DH11: Medido (R$) | DI11: % do mês | DJ11: % acumulado | DK11: Acumulado (R$) | DL11: Saldo a medir (R$) | DM11: % acumulado
B12: 1 | C12: SERVIÇOS PRELIMINARES | E12: =VLOOKUP(B12,'[49]PLANILHA ORCAMENTARIA'!A:G,7,0) -> 684838.25 | G12: =SUMIF($A$13:$A$269,$B$12,G13:G269) -> 0 | H12: =IF(G12="","",G12/$E12) -> 0 | I12: =H12 -> 0 | J12: =SUMIF($A$13:$A$269,$B$12,J13:J269) -> 0 | K12: =IF(J12="","",J12/$E12) -> 0 | L12: =K12+I12 -> 0 | M12: =SUMIF($A$13:$A$269,$B$12,M13:M269) -> 338194.34 | N12: =IF(M12="","",M12/$E12) -> 0.49383097 | O12: =N12+L12 -> 0.49383097 | P12: =SUMIF($A$13:$A$269,$B$12,P13:P269) -> 340115.88 | Q12: =IF(P12="","",P12/$E12) -> 0.4966368 | R12: =Q12+O12 -> 0.99046778 | S12: =SUMIF($A$13:$A$269,$B$12,S13:S269) -> 0 | T12: =IF(S12="","",S12/$E12) -> 0 | U12: =T12+R12 -> 0.99046778 | V12: =SUMIF($A$13:$A$269,$B$12,V13:V269) -> 0 | W12: =IF(V12="","",V12/$E12) -> 0 | X12: =W12+U12 -> 0.99046778 | Y12: =SUMIF($A$13:$A$269,$B$12,Y13:Y269) -> 0 | Z12: =IF(Y12="","",Y12/$E12) -> 0 | AA12: =Z12+X12 -> 0.99046778 | AB12: =SUMIF($A$13:$A$269,$B$12,AB13:AB269) -> 0 | AC12: =IF(AB12="","",AB12/$E12) -> 0 | AD12: =AC12+AA12 -> 0.99046778 | AE12: =SUMIF($A$13:$A$269,$B$12,AE13:AE269) -> 0 | AF12: =IF(AE12="","",AE12/$E12) -> 0 | AG12: =AF12+AD12 -> 0.99046778 | AH12: =SUMIF($A$13:$A$269,$B$12,AH13:AH269) -> 0 | AI12: =IF(AH12="","",AH12/$E12) -> 0 | AJ12: =AI12+AG12 -> 0.99046778 | AK12: =SUMIF($A$13:$A$269,$B$12,AK13:AK269) -> 0 | AL12: =IF(AK12="","",AK12/$E12) -> 0 | AM12: =AL12+AJ12 -> 0.99046778 | AN12: =SUMIF($A$13:$A$269,$B$12,AN13:AN269) -> 0 | AO12: =IF(AN12="","",AN12/$E12) -> 0 | AP12: =AO12+AM12 -> 0.99046778 | AQ12: =SUMIF($A$13:$A$269,$B$12,AQ13:AQ269) -> 0 | AR12: =IF(AQ12="","",AQ12/$E12) -> 0 | AS12: =AR12+AP12 -> 0.99046778 | AT12: =SUMIF($A$13:$A$269,$B$12,AT13:AT269) -> 0 | AU12: =IF(AT12="","",AT12/$E12) -> 0 | AV12: =AU12+AS12 -> 0.99046778 | AW12: =SUMIF($A$13:$A$269,$B$12,AW13:AW269) -> 0 | AX12: =IF(AW12="","",AW12/$E12) -> 0 | AY12: =AX12+AV12 -> 0.99046778 | AZ12: =SUMIF($A$13:$A$269,$B$12,AZ13:AZ269) -> 0 | BA12: =IF(AZ12="","",AZ12/$E12) -> 0 | BB12: =BA12+AY12 -> 0.99046778 | BC12: =SUMIF($A$13:$A$269,$B$12,BC13:BC269) -> 0 | BD12: =IF(BC12="","",BC12/$E12) -> 0 | BE12: =BD12+BB12 -> 0.99046778 | BF12: =SUMIF($A$13:$A$269,$B$12,BF13:BF269) -> 0 | BG12: =IF(BF12="","",BF12/$E12) -> 0 | BH12: =BG12+BE12 -> 0.99046778 | BI12: =SUMIF($A$13:$A$269,$B$12,BI13:BI269) -> 0 | BJ12: =IF(BI12="","",BI12/$E12) -> 0 | BK12: =BJ12+BH12 -> 0.99046778 | BL12: =SUMIF($A$13:$A$269,$B$12,BL13:BL269) -> 0 | BM12: =IF(BL12="","",BL12/$E12) -> 0 | BN12: =BM12+BK12 -> 0.99046778 | BO12: =SUMIF($A$13:$A$269,$B$12,BO13:BO269) -> 0 | BP12: =IF(BO12="","",BO12/$E12) -> 0 | BQ12: =BP12+BN12 -> 0.99046778 | BR12: =SUMIF($A$13:$A$269,$B$12,BR13:BR269) -> 0 | BS12: =IF(BR12="","",BR12/$E12) -> 0 | BT12: =BS12+BQ12 -> 0.99046778 | BU12: =SUMIF($A$13:$A$269,$B$12,BU13:BU269) -> 0 | BV12: =IF(BU12="","",BU12/$E12) -> 0 | BW12: =BV12+BT12 -> 0.99046778 | BX12: =SUMIF($A$13:$A$269,$B$12,BX13:BX269) -> 0 | BY12: =IF(BX12="","",BX12/$E12) -> 0 | BZ12: =BY12+BW12 -> 0.99046778 | CA12: =SUMIF($A$13:$A$269,$B$12,CA13:CA269) -> 0 | CB12: =IF(CA12="","",CA12/$E12) -> 0 | CC12: =CB12+BZ12 -> 0.99046778 | CD12: =SUMIF($A$13:$A$269,$B$12,CD13:CD269) -> 0 | CE12: =IF(CD12="","",CD12/$E12) -> 0 | CF12: =CE12+CC12 -> 0.99046778 | CG12: =SUMIF($A$13:$A$269,$B$12,CG13:CG269) -> 0 | CH12: =IF(CG12="","",CG12/$E12) -> 0 | CI12: =CH12+CF12 -> 0.99046778 | CJ12: =SUMIF($A$13:$A$269,$B$12,CJ13:CJ269) -> 0 | CK12: =IF(CJ12="","",CJ12/$E12) -> 0 | CL12: =CK12+CI12 -> 0.99046778 | CM12: =SUMIF($A$13:$A$269,$B$12,CM13:CM269) -> 0 | CN12: =IF(CM12="","",CM12/$E12) -> 0 | CO12: =CN12+CL12 -> 0.99046778 | CP12: =SUMIF($A$13:$A$269,$B$12,CP13:CP269) -> 0 | CQ12: =IF(CP12="","",CP12/$E12) -> 0 | CR12: =CQ12+CO12 -> 0.99046778 | CS12: =SUMIF($A$13:$A$269,$B$12,CS13:CS269) -> 0 | CT12: =IF(CS12="","",CS12/$E12) -> 0 | CU12: =CT12+CR12 -> 0.99046778 | CV12: =SUMIF($A$13:$A$269,$B$12,CV13:CV269) -> 0 | CW12: =IF(CV12="","",CV12/$E12) -> 0 | CX12: =CW12+CU12 -> 0.99046778 | CY12: =SUMIF($A$13:$A$269,$B$12,CY13:CY269) -> 0 | CZ12: =IF(CY12="","",CY12/$E12) -> 0 | DA12: =CZ12+CX12 -> 0.99046778 | DB12: =SUMIF($A$13:$A$269,$B$12,DB13:DB269) -> 0 | DC12: =IF(DB12="","",DB12/$E12) -> 0 | DD12: =DC12+DA12 -> 0.99046778 | DE12: =SUMIF($A$13:$A$269,$B$12,DE13:DE269) -> 0 | DF12: =IF(DE12="","",DE12/$E12) -> 0 | DG12: =DF12+DD12 -> 0.99046778 | DH12: =SUMIF($A$13:$A$269,$B$12,DH13:DH269) -> 0 | DI12: =IF(DH12="","",DH12/$E12) -> 0 | DJ12: =DI12+DG12 -> 0.99046778 | DK12: =G12+J12+M12+P12+S12+V12+Y12+AB12+AE12+AH12+AK12+AN12+AQ12+AT12+AW12+AZ12+BC12+BF12+BI12+BL12+BO12+BR12+BU12+BX12+CA12+CD12+CG12+CJ12+CM12+CP12+CS12+CV12+CY12+DB12+DE12+DH12 -> 678310.22 | DL12: =E12-DK12 -> 6528.03 | DM12: =DK12/E12 -> 0.99046778
A13: =LEFT(B13,1) -> 1 | B13: 1.1 | C13: LIGAÇÕES PROVISORIAS / CANTEIRO DE OBRAS | E13: =VLOOKUP(B13,'[49]PLANILHA ORCAMENTARIA'!A:G,7,0) -> 254900.14 | G13: =IF(H13="","",H13*$E13) | I13: =H13 -> 0 | J13: =IF(K13="","",K13*$E13) | L13: =K13+I13 -> 0 | M13: =IF(N13="","",N13*$E13) -> 254900.14 | N13: 1 | O13: =N13+L13 -> 1 | P13: =IF(Q13="","",Q13*$E13) | R13: =Q13+O13 -> 1 | S13: =IF(T13="","",T13*$E13) | U13: =T13+R13 -> 1 | V13: =IF(W13="","",W13*$E13) | X13: =W13+U13 -> 1 | Y13: =IF(Z13="","",Z13*$E13) | AA13: =Z13+X13 -> 1 | AB13: =IF(AC13="","",AC13*$E13) | AD13: =AC13+AA13 -> 1 | AE13: =IF(AF13="","",AF13*$E13) | AG13: =AF13+AD13 -> 1 | AH13: =IF(AI13="","",AI13*$E13) | AJ13: =AI13+AG13 -> 1 | AK13: =IF(AL13="","",AL13*$E13) | AM13: =AL13+AJ13 -> 1 | AN13: =IF(AO13="","",AO13*$E13) | AP13: =AO13+AM13 -> 1 | AQ13: =IF(AR13="","",AR13*$E13) | AS13: =AR13+AP13 -> 1 | AT13: =IF(AU13="","",AU13*$E13) | AV13: =AU13+AS13 -> 1 | AW13: =IF(AX13="","",AX13*$E13) | AY13: =AX13+AV13 -> 1 | AZ13: =IF(BA13="","",BA13*$E13) | BB13: =BA13+AY13 -> 1 | BC13: =IF(BD13="","",BD13*$E13) | BE13: =BD13+BB13 -> 1 | BF13: =IF(BG13="","",BG13*$E13) | BH13: =BG13+BE13 -> 1 | BI13: =IF(BJ13="","",BJ13*$E13) | BK13: =BJ13+BH13 -> 1 | BL13: =IF(BM13="","",BM13*$E13) | BN13: =BM13+BK13 -> 1 | BO13: =IF(BP13="","",BP13*$E13) | BQ13: =BP13+BN13 -> 1 | BR13: =IF(BS13="","",BS13*$E13) | BT13: =BS13+BQ13 -> 1 | BU13: =IF(BV13="","",BV13*$E13) | BW13: =BV13+BT13 -> 1 | BX13: =IF(BY13="","",BY13*$E13) | BZ13: =BY13+BW13 -> 1 | CA13: =IF(CB13="","",CB13*$E13) | CC13: =CB13+BZ13 -> 1 | CD13: =IF(CE13="","",CE13*$E13) | CF13: =CE13+CC13 -> 1 | CG13: =IF(CH13="","",CH13*$E13) | CI13: =CH13+CF13 -> 1 | CJ13: =IF(CK13="","",CK13*$E13) | CL13: =CK13+CI13 -> 1 | CM13: =IF(CN13="","",CN13*$E13) | CO13: =CN13+CL13 -> 1 | CP13: =IF(CQ13="","",CQ13*$E13) | CR13: =CQ13+CO13 -> 1 | CS13: =IF(CT13="","",CT13*$E13) | CU13: =CT13+CR13 -> 1 | CV13: =IF(CW13="","",CW13*$E13) | CX13: =CW13+CU13 -> 1 | CY13: =IF(CZ13="","",CZ13*$E13) | DA13: =CZ13+CX13 -> 1 | DB13: =IF(DC13="","",DC13*$E13) | DD13: =DC13+DA13 -> 1 | DE13: =IF(DF13="","",DF13*$E13) | DG13: =DF13+DD13 -> 1 | DH13: =IF(DI13="","",DI13*$E13) | DJ13: =DI13+DG13 -> 1
A14: =LEFT(B14,1) -> 1 | B14: 1.2 | C14: TAPUMES | E14: =VLOOKUP(B14,'[49]PLANILHA ORCAMENTARIA'!A:G,7,0) -> 83294.2 | G14: =IF(H14="","",H14*$E14) | I14: =H14 -> 0 | J14: =IF(K14="","",K14*$E14) | L14: =K14+I14 -> 0 | M14: =IF(N14="","",N14*$E14) -> 83294.2 | N14: 1 | O14: =N14+L14 -> 1 | P14: =IF(Q14="","",Q14*$E14) | R14: =Q14+O14 -> 1 | S14: =IF(T14="","",T14*$E14) | U14: =T14+R14 -> 1 | V14: =IF(W14="","",W14*$E14) | X14: =W14+U14 -> 1 | Y14: =IF(Z14="","",Z14*$E14) | AA14: =Z14+X14 -> 1 | AB14: =IF(AC14="","",AC14*$E14) | AD14: =AC14+AA14 -> 1 | AE14: =IF(AF14="","",AF14*$E14) | AG14: =AF14+AD14 -> 1 | AH14: =IF(AI14="","",AI14*$E14) | AJ14: =AI14+AG14 -> 1 | AK14: =IF(AL14="","",AL14*$E14) | AM14: =AL14+AJ14 -> 1 | AN14: =IF(AO14="","",AO14*$E14) | AP14: =AO14+AM14 -> 1 | AQ14: =IF(AR14="","",AR14*$E14) | AS14: =AR14+AP14 -> 1 | AT14: =IF(AU14="","",AU14*$E14) | AV14: =AU14+AS14 -> 1 | AW14: =IF(AX14="","",AX14*$E14) | AY14: =AX14+AV14 -> 1 | AZ14: =IF(BA14="","",BA14*$E14) | BB14: =BA14+AY14 -> 1 | BC14: =IF(BD14="","",BD14*$E14) | BE14: =BD14+BB14 -> 1 | BF14: =IF(BG14="","",BG14*$E14) | BH14: =BG14+BE14 -> 1 | BI14: =IF(BJ14="","",BJ14*$E14) | BK14: =BJ14+BH14 -> 1 | BL14: =IF(BM14="","",BM14*$E14) | BN14: =BM14+BK14 -> 1 | BO14: =IF(BP14="","",BP14*$E14) | BQ14: =BP14+BN14 -> 1 | BR14: =IF(BS14="","",BS14*$E14) | BT14: =BS14+BQ14 -> 1 | BU14: =IF(BV14="","",BV14*$E14) | BW14: =BV14+BT14 -> 1 | BX14: =IF(BY14="","",BY14*$E14) | BZ14: =BY14+BW14 -> 1 | CA14: =IF(CB14="","",CB14*$E14) | CC14: =CB14+BZ14 -> 1 | CD14: =IF(CE14="","",CE14*$E14) | CF14: =CE14+CC14 -> 1 | CG14: =IF(CH14="","",CH14*$E14) | CI14: =CH14+CF14 -> 1 | CJ14: =IF(CK14="","",CK14*$E14) | CL14: =CK14+CI14 -> 1 | CM14: =IF(CN14="","",CN14*$E14) | CO14: =CN14+CL14 -> 1 | CP14: =IF(CQ14="","",CQ14*$E14) | CR14: =CQ14+CO14 -> 1 | CS14: =IF(CT14="","",CT14*$E14) | CU14: =CT14+CR14 -> 1 | CV14: =IF(CW14="","",CW14*$E14) | CX14: =CW14+CU14 -> 1 | CY14: =IF(CZ14="","",CZ14*$E14) | DA14: =CZ14+CX14 -> 1 | DB14: =IF(DC14="","",DC14*$E14) | DD14: =DC14+DA14 -> 1 | DE14: =IF(DF14="","",DF14*$E14) | DG14: =DF14+DD14 -> 1 | DH14: =IF(DI14="","",DI14*$E14) | DJ14: =DI14+DG14 -> 1
A15: =LEFT(B15,1) -> 1 | B15: 1.3 | C15: LOCAÇÃO DA OBRA | E15: =VLOOKUP(B15,'[49]PLANILHA ORCAMENTARIA'!A:G,7,0) -> 113076.45 | G15: =IF(H15="","",H15*$E15) | I15: =H15 -> 0 | J15: =IF(K15="","",K15*$E15) | L15: =K15+I15 -> 0 | M15: =IF(N15="","",N15*$E15) | O15: =N15+L15 -> 0 | P15: =IF(Q15="","",Q15*$E15) -> 113076.45 | Q15: 1 | R15: =Q15+O15 -> 1 | S15: =IF(T15="","",T15*$E15) | U15: =T15+R15 -> 1 | V15: =IF(W15="","",W15*$E15) | X15: =W15+U15 -> 1 | Y15: =IF(Z15="","",Z15*$E15) | AA15: =Z15+X15 -> 1 | AB15: =IF(AC15="","",AC15*$E15) | AD15: =AC15+AA15 -> 1 | AE15: =IF(AF15="","",AF15*$E15) | AG15: =AF15+AD15 -> 1 | AH15: =IF(AI15="","",AI15*$E15) | AJ15: =AI15+AG15 -> 1 | AK15: =IF(AL15="","",AL15*$E15) | AM15: =AL15+AJ15 -> 1 | AN15: =IF(AO15="","",AO15*$E15) | AP15: =AO15+AM15 -> 1 | AQ15: =IF(AR15="","",AR15*$E15) | AS15: =AR15+AP15 -> 1 | AT15: =IF(AU15="","",AU15*$E15) | AV15: =AU15+AS15 -> 1 | AW15: =IF(AX15="","",AX15*$E15) | AY15: =AX15+AV15 -> 1 | AZ15: =IF(BA15="","",BA15*$E15) | BB15: =BA15+AY15 -> 1 | BC15: =IF(BD15="","",BD15*$E15) | BE15: =BD15+BB15 -> 1 | BF15: =IF(BG15="","",BG15*$E15) | BH15: =BG15+BE15 -> 1 | BI15: =IF(BJ15="","",BJ15*$E15) | BK15: =BJ15+BH15 -> 1 | BL15: =IF(BM15="","",BM15*$E15) | BN15: =BM15+BK15 -> 1 | BO15: =IF(BP15="","",BP15*$E15) | BQ15: =BP15+BN15 -> 1 | BR15: =IF(BS15="","",BS15*$E15) | BT15: =BS15+BQ15 -> 1 | BU15: =IF(BV15="","",BV15*$E15) | BW15: =BV15+BT15 -> 1 | BX15: =IF(BY15="","",BY15*$E15) | BZ15: =BY15+BW15 -> 1 | CA15: =IF(CB15="","",CB15*$E15) | CC15: =CB15+BZ15 -> 1 | CD15: =IF(CE15="","",CE15*$E15) | CF15: =CE15+CC15 -> 1 | CG15: =IF(CH15="","",CH15*$E15) | CI15: =CH15+CF15 -> 1 | CJ15: =IF(CK15="","",CK15*$E15) | CL15: =CK15+CI15 -> 1 | CM15: =IF(CN15="","",CN15*$E15) | CO15: =CN15+CL15 -> 1 | CP15: =IF(CQ15="","",CQ15*$E15) | CR15: =CQ15+CO15 -> 1 | CS15: =IF(CT15="","",CT15*$E15) | CU15: =CT15+CR15 -> 1 | CV15: =IF(CW15="","",CW15*$E15) | CX15: =CW15+CU15 -> 1 | CY15: =IF(CZ15="","",CZ15*$E15) | DA15: =CZ15+CX15 -> 1 | DB15: =IF(DC15="","",DC15*$E15) | DD15: =DC15+DA15 -> 1 | DE15: =IF(DF15="","",DF15*$E15) | DG15: =DF15+DD15 -> 1 | DH15: =IF(DI15="","",DI15*$E15) | DJ15: =DI15+DG15 -> 1
A16: =LEFT(B16,1) -> 1 | B16: 1.4 | C16: TERRAPLANAGEM | E16: =VLOOKUP(B16,'[49]PLANILHA ORCAMENTARIA'!A:G,7,0) -> 227039.43 | G16: =IF(H16="","",H16*$E16) | I16: =H16 -> 0 | J16: =IF(K16="","",K16*$E16) | L16: =K16+I16 -> 0 | M16: =IF(N16="","",N16*$E16) | O16: =N16+L16 -> 0 | P16: =IF(Q16="","",Q16*$E16) -> 227039.43 | Q16: 1 | R16: =Q16+O16 -> 1 | S16: =IF(T16="","",T16*$E16) | U16: =T16+R16 -> 1 | V16: =IF(W16="","",W16*$E16) | X16: =W16+U16 -> 1 | Y16: =IF(Z16="","",Z16*$E16) | AA16: =Z16+X16 -> 1 | AB16: =IF(AC16="","",AC16*$E16) | AD16: =AC16+AA16 -> 1 | AE16: =IF(AF16="","",AF16*$E16) | AG16: =AF16+AD16 -> 1 | AH16: =IF(AI16="","",AI16*$E16) | AJ16: =AI16+AG16 -> 1 | AK16: =IF(AL16="","",AL16*$E16) | AM16: =AL16+AJ16 -> 1 | AN16: =IF(AO16="","",AO16*$E16) | AP16: =AO16+AM16 -> 1 | AQ16: =IF(AR16="","",AR16*$E16) | AS16: =AR16+AP16 -> 1 | AT16: =IF(AU16="","",AU16*$E16) | AV16: =AU16+AS16 -> 1 | AW16: =IF(AX16="","",AX16*$E16) | AY16: =AX16+AV16 -> 1 | AZ16: =IF(BA16="","",BA16*$E16) | BB16: =BA16+AY16 -> 1 | BC16: =IF(BD16="","",BD16*$E16) | BE16: =BD16+BB16 -> 1 | BF16: =IF(BG16="","",BG16*$E16) | BH16: =BG16+BE16 -> 1 | BI16: =IF(BJ16="","",BJ16*$E16) | BK16: =BJ16+BH16 -> 1 | BL16: =IF(BM16="","",BM16*$E16) | BN16: =BM16+BK16 -> 1 | BO16: =IF(BP16="","",BP16*$E16) | BQ16: =BP16+BN16 -> 1 | BR16: =IF(BS16="","",BS16*$E16) | BT16: =BS16+BQ16 -> 1 | BU16: =IF(BV16="","",BV16*$E16) | BW16: =BV16+BT16 -> 1 | BX16: =IF(BY16="","",BY16*$E16) | BZ16: =BY16+BW16 -> 1 | CA16: =IF(CB16="","",CB16*$E16) | CC16: =CB16+BZ16 -> 1 | CD16: =IF(CE16="","",CE16*$E16) | CF16: =CE16+CC16 -> 1 | CG16: =IF(CH16="","",CH16*$E16) | CI16: =CH16+CF16 -> 1 | CJ16: =IF(CK16="","",CK16*$E16) | CL16: =CK16+CI16 -> 1 | CM16: =IF(CN16="","",CN16*$E16) | CO16: =CN16+CL16 -> 1 | CP16: =IF(CQ16="","",CQ16*$E16) | CR16: =CQ16+CO16 -> 1 | CS16: =IF(CT16="","",CT16*$E16) | CU16: =CT16+CR16 -> 1 | CV16: =IF(CW16="","",CW16*$E16) | CX16: =CW16+CU16 -> 1 | CY16: =IF(CZ16="","",CZ16*$E16) | DA16: =CZ16+CX16 -> 1 | DB16: =IF(DC16="","",DC16*$E16) | DD16: =DC16+DA16 -> 1 | DE16: =IF(DF16="","",DF16*$E16) | DG16: =DF16+DD16 -> 1 | DH16: =IF(DI16="","",DI16*$E16) | DJ16: =DI16+DG16 -> 1
A17: =LEFT(B17,1) -> 1 | B17: 1.5 | C17: POÇO PROFUNDO | E17: =VLOOKUP(B17,'[49]PLANILHA ORCAMENTARIA'!A:G,7,0) -> 6528.03 | G17: =IF(H17="","",H17*$E17) | I17: =H17 -> 0 | J17: =IF(K17="","",K17*$E17) | L17: =K17+I17 -> 0 | M17: =IF(N17="","",N17*$E17) | O17: =N17+L17 -> 0 | P17: =IF(Q17="","",Q17*$E17) | R17: =Q17+O17 -> 0 | S17: =IF(T17="","",T17*$E17) | U17: =T17+R17 -> 0 | V17: =IF(W17="","",W17*$E17) | X17: =W17+U17 -> 0 | Y17: =IF(Z17="","",Z17*$E17) | AA17: =Z17+X17 -> 0 | AB17: =IF(AC17="","",AC17*$E17) | AD17: =AC17+AA17 -> 0 | AE17: =IF(AF17="","",AF17*$E17) | AG17: =AF17+AD17 -> 0 | AH17: =IF(AI17="","",AI17*$E17) | AJ17: =AI17+AG17 -> 0 | AK17: =IF(AL17="","",AL17*$E17) | AM17: =AL17+AJ17 -> 0 | AN17: =IF(AO17="","",AO17*$E17) | AP17: =AO17+AM17 -> 0 | AQ17: =IF(AR17="","",AR17*$E17) | AS17: =AR17+AP17 -> 0 | AT17: =IF(AU17="","",AU17*$E17) | AV17: =AU17+AS17 -> 0 | AW17: =IF(AX17="","",AX17*$E17) | AY17: =AX17+AV17 -> 0 | AZ17: =IF(BA17="","",BA17*$E17) | BB17: =BA17+AY17 -> 0 | BC17: =IF(BD17="","",BD17*$E17) | BE17: =BD17+BB17 -> 0 | BF17: =IF(BG17="","",BG17*$E17) | BH17: =BG17+BE17 -> 0 | BI17: =IF(BJ17="","",BJ17*$E17) | BK17: =BJ17+BH17 -> 0 | BL17: =IF(BM17="","",BM17*$E17) | BN17: =BM17+BK17 -> 0 | BO17: =IF(BP17="","",BP17*$E17) | BQ17: =BP17+BN17 -> 0 | BR17: =IF(BS17="","",BS17*$E17) | BT17: =BS17+BQ17 -> 0 | BU17: =IF(BV17="","",BV17*$E17) | BW17: =BV17+BT17 -> 0 | BX17: =IF(BY17="","",BY17*$E17) | BZ17: =BY17+BW17 -> 0 | CA17: =IF(CB17="","",CB17*$E17) | CC17: =CB17+BZ17 -> 0 | CD17: =IF(CE17="","",CE17*$E17) | CF17: =CE17+CC17 -> 0 | CG17: =IF(CH17="","",CH17*$E17) | CI17: =CH17+CF17 -> 0 | CJ17: =IF(CK17="","",CK17*$E17) | CL17: =CK17+CI17 -> 0 | CM17: =IF(CN17="","",CN17*$E17) | CO17: =CN17+CL17 -> 0 | CP17: =IF(CQ17="","",CQ17*$E17) | CR17: =CQ17+CO17 -> 0 | CS17: =IF(CT17="","",CT17*$E17) | CU17: =CT17+CR17 -> 0 | CV17: =IF(CW17="","",CW17*$E17) | CX17: =CW17+CU17 -> 0 | CY17: =IF(CZ17="","",CZ17*$E17) | DA17: =CZ17+CX17 -> 0 | DB17: =IF(DC17="","",DC17*$E17) | DD17: =DC17+DA17 -> 0 | DE17: =IF(DF17="","",DF17*$E17) | DG17: =DF17+DD17 -> 0 | DH17: =IF(DI17="","",DI17*$E17) | DJ17: =DI17+DG17 -> 0
A18: =LEFT(B18,1) -> 2 | B18: 2 | C18: ADMINISTRAÇÃO DA OBRA | E18: =VLOOKUP(B18,'[49]PLANILHA ORCAMENTARIA'!A:G,7,0) -> 2333205.8 | G18: =ROUND((G12+G19+G72+G221+G226+G247+G259+G265+G268)*$F$6,2) -> 0 | H18: =IF(G18="","",G18/$E18) -> 0 | I18: =H18 -> 0 | J18: =ROUND((J12+J19+J72+J221+J226+J247+J259+J265+J268)*$F$6,2) -> 0 | K18: =IF(J18="","",J18/$E18) -> 0 | L18: =K18+I18 -> 0 | M18: =ROUND((M12+M19+M72+M221+M226+M247+M259+M265+M268)*$F$6,2) -> 30078.93 | N18: =IF(M18="","",M18/$E18) -> 0.012891674 | O18: =N18+L18 -> 0.012891674 | P18: =ROUND((P12+P19+P72+P221+P226+P247+P259+P265+P268)*$F$6,2) -> 79105.47 | Q18: =IF(P18="","",P18/$E18) -> 0.033904197 | R18: =Q18+O18 -> 0.046795871 | S18: =ROUND((S12+S19+S72+S221+S226+S247+S259+S265+S268)*$F$6,2) -> 82391.2 | T18: =IF(S18="","",S18/$E18) -> 0.035312444 | U18: =T18+R18 -> 0.082108315 | V18: =ROUND((V12+V19+V72+V221+V226+V247+V259+V265+V268)*$F$6,2) -> 0 | W18: =IF(V18="","",V18/$E18) -> 0 | X18: =W18+U18 -> 0.082108315 | Y18: =ROUND((Y12+Y19+Y72+Y221+Y226+Y247+Y259+Y265+Y268)*$F$6,2) -> 0 | Z18: =IF(Y18="","",Y18/$E18) -> 0 | AA18: =Z18+X18 -> 0.082108315 | AB18: =ROUND((AB12+AB19+AB72+AB221+AB226+AB247+AB259+AB265+AB268)*$F$6,2) -> 0 | AC18: =IF(AB18="","",AB18/$E18) -> 0 | AD18: =AC18+AA18 -> 0.082108315 | AE18: =ROUND((AE12+AE19+AE72+AE221+AE226+AE247+AE259+AE265+AE268)*$F$6,2) -> 0 | AF18: =IF(AE18="","",AE18/$E18) -> 0 | AG18: =AF18+AD18 -> 0.082108315 | AH18: =ROUND((AH12+AH19+AH72+AH221+AH226+AH247+AH259+AH265+AH268)*$F$6,2) -> 0 | AI18: =IF(AH18="","",AH18/$E18) -> 0 | AJ18: =AI18+AG18 -> 0.082108315 | AK18: =ROUND((AK12+AK19+AK72+AK221+AK226+AK247+AK259+AK265+AK268)*$F$6,2) -> 0 | AL18: =IF(AK18="","",AK18/$E18) -> 0 | AM18: =AL18+AJ18 -> 0.082108315 | AN18: =ROUND((AN12+AN19+AN72+AN221+AN226+AN247+AN259+AN265+AN268)*$F$6,2) -> 0 | AO18: =IF(AN18="","",AN18/$E18) -> 0 | AP18: =AO18+AM18 -> 0.082108315 | AQ18: =ROUND((AQ12+AQ19+AQ72+AQ221+AQ226+AQ247+AQ259+AQ265+AQ268)*$F$6,2) -> 0 | AR18: =IF(AQ18="","",AQ18/$E18) -> 0 | AS18: =AR18+AP18 -> 0.082108315 | AT18: =ROUND((AT12+AT19+AT72+AT221+AT226+AT247+AT259+AT265+AT268)*$F$6,2) -> 0 | AU18: =IF(AT18="","",AT18/$E18) -> 0 | AV18: =AU18+AS18 -> 0.082108315 | AW18: =ROUND((AW12+AW19+AW72+AW221+AW226+AW247+AW259+AW265+AW268)*$F$6,2) -> 0 | AX18: =IF(AW18="","",AW18/$E18) -> 0 | AY18: =AX18+AV18 -> 0.082108315 | AZ18: =ROUND((AZ12+AZ19+AZ72+AZ221+AZ226+AZ247+AZ259+AZ265+AZ268)*$F$6,2) -> 0 | BA18: =IF(AZ18="","",AZ18/$E18) -> 0 | BB18: =BA18+AY18 -> 0.082108315 | BC18: =ROUND((BC12+BC19+BC72+BC221+BC226+BC247+BC259+BC265+BC268)*$F$6,2) -> 0 | BD18: =IF(BC18="","",BC18/$E18) -> 0 | BE18: =BD18+BB18 -> 0.082108315 | BF18: =ROUND((BF12+BF19+BF72+BF221+BF226+BF247+BF259+BF265+BF268)*$F$6,2) -> 0 | BG18: =IF(BF18="","",BF18/$E18) -> 0 | BH18: =BG18+BE18 -> 0.082108315 | BI18: =ROUND((BI12+BI19+BI72+BI221+BI226+BI247+BI259+BI265+BI268)*$F$6,2) -> 0 | BJ18: =IF(BI18="","",BI18/$E18) -> 0 | BK18: =BJ18+BH18 -> 0.082108315 | BL18: =ROUND((BL12+BL19+BL72+BL221+BL226+BL247+BL259+BL265+BL268)*$F$6,2) -> 0 | BM18: =IF(BL18="","",BL18/$E18) -> 0 | BN18: =BM18+BK18 -> 0.082108315 | BO18: =ROUND((BO12+BO19+BO72+BO221+BO226+BO247+BO259+BO265+BO268)*$F$6,2) -> 0 | BP18: =IF(BO18="","",BO18/$E18) -> 0 | BQ18: =BP18+BN18 -> 0.082108315 | BR18: =ROUND((BR12+BR19+BR72+BR221+BR226+BR247+BR259+BR265+BR268)*$F$6,2) -> 0 | BS18: =IF(BR18="","",BR18/$E18) -> 0 | BT18: =BS18+BQ18 -> 0.082108315 | BU18: =ROUND((BU12+BU19+BU72+BU221+BU226+BU247+BU259+BU265+BU268)*$F$6,2) -> 0 | BV18: =IF(BU18="","",BU18/$E18) -> 0 | BW18: =BV18+BT18 -> 0.082108315 | BX18: =ROUND((BX12+BX19+BX72+BX221+BX226+BX247+BX259+BX265+BX268)*$F$6,2) -> 0 | BY18: =IF(BX18="","",BX18/$E18) -> 0 | BZ18: =BY18+BW18 -> 0.082108315 | CA18: =ROUND((CA12+CA19+CA72+CA221+CA226+CA247+CA259+CA265+CA268)*$F$6,2) -> 0 | CB18: =IF(CA18="","",CA18/$E18) -> 0 | CC18: =CB18+BZ18 -> 0.082108315 | CD18: =ROUND((CD12+CD19+CD72+CD221+CD226+CD247+CD259+CD265+CD268)*$F$6,2) -> 0 | CE18: =IF(CD18="","",CD18/$E18) -> 0 | CF18: =CE18+CC18 -> 0.082108315 | CG18: =ROUND((CG12+CG19+CG72+CG221+CG226+CG247+CG259+CG265+CG268)*$F$6,2) -> 0 | CH18: =IF(CG18="","",CG18/$E18) -> 0 | CI18: =CH18+CF18 -> 0.082108315 | CJ18: =ROUND((CJ12+CJ19+CJ72+CJ221+CJ226+CJ247+CJ259+CJ265+CJ268)*$F$6,2) -> 0 | CK18: =IF(CJ18="","",CJ18/$E18) -> 0 | CL18: =CK18+CI18 -> 0.082108315 | CM18: =ROUND((CM12+CM19+CM72+CM221+CM226+CM247+CM259+CM265+CM268)*$F$6,2) -> 0 | CN18: =IF(CM18="","",CM18/$E18) -> 0 | CO18: =CN18+CL18 -> 0.082108315 | CP18: =ROUND((CP12+CP19+CP72+CP221+CP226+CP247+CP259+CP265+CP268)*$F$6,2) -> 0 | CQ18: =IF(CP18="","",CP18/$E18) -> 0 | CR18: =CQ18+CO18 -> 0.082108315 | CS18: =ROUND((CS12+CS19+CS72+CS221+CS226+CS247+CS259+CS265+CS268)*$F$6,2) -> 0 | CT18: =IF(CS18="","",CS18/$E18) -> 0 | CU18: =CT18+CR18 -> 0.082108315 | CV18: =ROUND((CV12+CV19+CV72+CV221+CV226+CV247+CV259+CV265+CV268)*$F$6,2) -> 0 | CW18: =IF(CV18="","",CV18/$E18) -> 0 | CX18: =CW18+CU18 -> 0.082108315 | CY18: =ROUND((CY12+CY19+CY72+CY221+CY226+CY247+CY259+CY265+CY268)*$F$6,2) -> 0 | CZ18: =IF(CY18="","",CY18/$E18) -> 0 | DA18: =CZ18+CX18 -> 0.082108315 | DB18: =ROUND((DB12+DB19+DB72+DB221+DB226+DB247+DB259+DB265+DB268)*$F$6,2) -> 0 | DC18: =IF(DB18="","",DB18/$E18) -> 0 | DD18: =DC18+DA18 -> 0.082108315 | DE18: =ROUND((DE12+DE19+DE72+DE221+DE226+DE247+DE259+DE265+DE268)*$F$6,2) -> 0 | DF18: =IF(DE18="","",DE18/$E18) -> 0 | DG18: =DF18+DD18 -> 0.082108315 | DH18: =ROUND((DH12+DH19+DH72+DH221+DH226+DH247+DH259+DH265+DH268)*$F$6,2) -> 0 | DI18: =IF(DH18="","",DH18/$E18) -> 0 | DJ18: =DI18+DG18 -> 0.082108315 | DK18: =G18+J18+M18+P18+S18+V18+Y18+AB18+AE18+AH18+AK18+AN18+AQ18+AT18+AW18+AZ18+BC18+BF18+BI18+BL18+BO18+BR18+BU18+BX18+CA18+CD18+CG18+CJ18+CM18+CP18+CS18+CV18+CY18+DB18+DE18+DH18 -> 191575.6 | DL18: =E18-DK18 -> 2141630.2 | DM18: =DK18/E18 -> 0.082108315
A19: 3 | B19: 3 | C19: FUNDAÇÕES E ESTRUTURAS | E19: =VLOOKUP(B19,'[49]PLANILHA ORCAMENTARIA'!A:G,7,0) -> 6067667.4 | G19: =SUM(G20:G71) -> 0 | H19: =IF(G19="","",G19/$E19) -> 0 | I19: =H19 -> 0 | J19: =SUM(J20:J71) -> 0 | K19: =IF(J19="","",J19/$E19) -> 0 | L19: =K19+I19 -> 0 | M19: =SUM(M20:M71) -> 0 | N19: =IF(M19="","",M19/$E19) -> 0 | O19: =N19+L19 -> 0 | P19: =SUM(P20:P71) -> 549311.32 | Q19: =IF(P19="","",P19/$E19) -> 0.090530888 | R19: =Q19+O19 -> 0.090530888 | S19: =SUM(S20:S71) -> 926370.58 | T19: =IF(S19="","",S19/$E19) -> 0.15267326 | U19: =T19+R19 -> 0.24320415 | V19: =SUM(V20:V71) -> 0 | W19: =IF(V19="","",V19/$E19) -> 0 | X19: =W19+U19 -> 0.24320415 | Y19: =SUM(Y20:Y71) -> 0 | Z19: =IF(Y19="","",Y19/$E19) -> 0 | AA19: =Z19+X19 -> 0.24320415 | AB19: =SUM(AB20:AB71) -> 0 | AC19: =IF(AB19="","",AB19/$E19) -> 0 | AD19: =AC19+AA19 -> 0.24320415 | AE19: =SUM(AE20:AE71) -> 0 | AF19: =IF(AE19="","",AE19/$E19) -> 0 | AG19: =AF19+AD19 -> 0.24320415 | AH19: =SUM(AH20:AH71) -> 0 | AI19: =IF(AH19="","",AH19/$E19) -> 0 | AJ19: =AI19+AG19 -> 0.24320415 | AK19: =SUM(AK20:AK71) -> 0 | AL19: =IF(AK19="","",AK19/$E19) -> 0 | AM19: =AL19+AJ19 -> 0.24320415 | AN19: =SUM(AN20:AN71) -> 0 | AO19: =IF(AN19="","",AN19/$E19) -> 0 | AP19: =AO19+AM19 -> 0.24320415 | AQ19: =SUM(AQ20:AQ71) -> 0 | AR19: =IF(AQ19="","",AQ19/$E19) -> 0 | AS19: =AR19+AP19 -> 0.24320415 | AT19: =SUM(AT20:AT71) -> 0 | AU19: =IF(AT19="","",AT19/$E19) -> 0 | AV19: =AU19+AS19 -> 0.24320415 | AW19: =SUM(AW20:AW71) -> 0 | AX19: =IF(AW19="","",AW19/$E19) -> 0 | AY19: =AX19+AV19 -> 0.24320415 | AZ19: =SUM(AZ20:AZ71) -> 0 | BA19: =IF(AZ19="","",AZ19/$E19) -> 0 | BB19: =BA19+AY19 -> 0.24320415 | BC19: =SUM(BC20:BC71) -> 0 | BD19: =IF(BC19="","",BC19/$E19) -> 0 | BE19: =BD19+BB19 -> 0.24320415 | BF19: =SUM(BF20:BF71) -> 0 | BG19: =IF(BF19="","",BF19/$E19) -> 0 | BH19: =BG19+BE19 -> 0.24320415 | BI19: =SUM(BI20:BI71) -> 0 | BJ19: =IF(BI19="","",BI19/$E19) -> 0 | BK19: =BJ19+BH19 -> 0.24320415 | BL19: =SUM(BL20:BL71) -> 0 | BM19: =IF(BL19="","",BL19/$E19) -> 0 | BN19: =BM19+BK19 -> 0.24320415 | BO19: =SUM(BO20:BO71) -> 0 | BP19: =IF(BO19="","",BO19/$E19) -> 0 | BQ19: =BP19+BN19 -> 0.24320415 | BR19: =SUM(BR20:BR71) -> 0 | BS19: =IF(BR19="","",BR19/$E19) -> 0 | BT19: =BS19+BQ19 -> 0.24320415 | BU19: =SUM(BU20:BU71) -> 0 | BV19: =IF(BU19="","",BU19/$E19) -> 0 | BW19: =BV19+BT19 -> 0.24320415 | BX19: =SUM(BX20:BX71) -> 0 | BY19: =IF(BX19="","",BX19/$E19) -> 0 | BZ19: =BY19+BW19 -> 0.24320415 | CA19: =SUM(CA20:CA71) -> 0 | CB19: =IF(CA19="","",CA19/$E19) -> 0 | CC19: =CB19+BZ19 -> 0.24320415 | CD19: =SUM(CD20:CD71) -> 0 | CE19: =IF(CD19="","",CD19/$E19) -> 0 | CF19: =CE19+CC19 -> 0.24320415 | CG19: =SUM(CG20:CG71) -> 0 | CH19: =IF(CG19="","",CG19/$E19) -> 0 | CI19: =CH19+CF19 -> 0.24320415 | CJ19: =SUM(CJ20:CJ71) -> 0 | CK19: =IF(CJ19="","",CJ19/$E19) -> 0 | CL19: =CK19+CI19 -> 0.24320415 | CM19: =SUM(CM20:CM71) -> 0 | CN19: =IF(CM19="","",CM19/$E19) -> 0 | CO19: =CN19+CL19 -> 0.24320415 | CP19: =SUM(CP20:CP71) -> 0 | CQ19: =IF(CP19="","",CP19/$E19) -> 0 | CR19: =CQ19+CO19 -> 0.24320415 | CS19: =SUM(CS20:CS71) -> 0 | CT19: =IF(CS19="","",CS19/$E19) -> 0 | CU19: =CT19+CR19 -> 0.24320415 | CV19: =SUM(CV20:CV71) -> 0 | CW19: =IF(CV19="","",CV19/$E19) -> 0 | CX19: =CW19+CU19 -> 0.24320415 | CY19: =SUM(CY20:CY71) -> 0 | CZ19: =IF(CY19="","",CY19/$E19) -> 0 | DA19: =CZ19+CX19 -> 0.24320415 | DB19: =SUM(DB20:DB71) -> 0 | DC19: =IF(DB19="","",DB19/$E19) -> 0 | DD19: =DC19+DA19 -> 0.24320415 | DE19: =SUM(DE20:DE71) -> 0 | DF19: =IF(DE19="","",DE19/$E19) -> 0 | DG19: =DF19+DD19 -> 0.24320415 | DH19: =SUM(DH20:DH71) -> 0 | DI19: =IF(DH19="","",DH19/$E19) -> 0 | DJ19: =DI19+DG19 -> 0.24320415 | DK19: =G19+J19+M19+P19+S19+V19+Y19+AB19+AE19+AH19+AK19+AN19+AQ19+AT19+AW19+AZ19+BC19+BF19+BI19+BL19+BO19+BR19+BU19+BX19+CA19+CD19+CG19+CJ19+CM19+CP19+CS19+CV19+CY19+DB19+DE19+DH19 -> 1475681.9 | DL19: =E19-DK19 -> 4591985.5 | DM19: =DK19/E19 -> 0.24320415
A20: 3 | B20: 3.1 | C20: FUNDAÇÕES | E20: =VLOOKUP(B20,'[49]PLANILHA ORCAMENTARIA'!A:G,7,0) -> 1777201.7
A21: 3 | B21: 3.1.1 | C21: BLOCO PRINCIPAL | E21: =VLOOKUP(B21,'[49]PLANILHA ORCAMENTARIA'!A:G,7,0) -> 1605873.1
A22: 3 | B22: 3.1.1.1 | C22: CONTENÇÃO | E22: =VLOOKUP(B22,'[49]PLANILHA ORCAMENTARIA'!A:G,7,0) -> 526764.81
A23: 3 | B23: 3.1.1.1.1 | C23: ESTACA ESCAVADA | E23: =VLOOKUP(B23,'[49]PLANILHA ORCAMENTARIA'!A:G,7,0) -> 158144.41 | G23: =IF(H23="","",H23*$E23) | I23: =H23 -> 0 | J23: =IF(K23="","",K23*$E23) | L23: =K23+I23 -> 0 | M23: =IF(N23="","",N23*$E23) | O23: =N23+L23 -> 0 | P23: =IF(Q23="","",Q23*$E23) -> 158144.41 | Q23: 1 | R23: =Q23+O23 -> 1 | S23: =IF(T23="","",T23*$E23) | U23: =T23+R23 -> 1 | V23: =IF(W23="","",W23*$E23) | X23: =W23+U23 -> 1 | Y23: =IF(Z23="","",Z23*$E23) | AA23: =Z23+X23 -> 1 | AB23: =IF(AC23="","",AC23*$E23) | AD23: =AC23+AA23 -> 1 | AE23: =IF(AF23="","",AF23*$E23) | AG23: =AF23+AD23 -> 1 | AH23: =IF(AI23="","",AI23*$E23) | AJ23: =AI23+AG23 -> 1 | AK23: =IF(AL23="","",AL23*$E23) | AM23: =AL23+AJ23 -> 1 | AN23: =IF(AO23="","",AO23*$E23) | AP23: =AO23+AM23 -> 1 | AQ23: =IF(AR23="","",AR23*$E23) | AS23: =AR23+AP23 -> 1 | AT23: =IF(AU23="","",AU23*$E23) | AV23: =AU23+AS23 -> 1 | AW23: =IF(AX23="","",AX23*$E23) | AY23: =AX23+AV23 -> 1 | AZ23: =IF(BA23="","",BA23*$E23) | BB23: =BA23+AY23 -> 1 | BC23: =IF(BD23="","",BD23*$E23) | BE23: =BD23+BB23 -> 1 | BF23: =IF(BG23="","",BG23*$E23) | BH23: =BG23+BE23 -> 1 | BI23: =IF(BJ23="","",BJ23*$E23) | BK23: =BJ23+BH23 -> 1 | BL23: =IF(BM23="","",BM23*$E23) | BN23: =BM23+BK23 -> 1 | BO23: =IF(BP23="","",BP23*$E23) | BQ23: =BP23+BN23 -> 1 | BR23: =IF(BS23="","",BS23*$E23) | BT23: =BS23+BQ23 -> 1 | BU23: =IF(BV23="","",BV23*$E23) | BW23: =BV23+BT23 -> 1 | BX23: =IF(BY23="","",BY23*$E23) | BZ23: =BY23+BW23 -> 1 | CA23: =IF(CB23="","",CB23*$E23) | CC23: =CB23+BZ23 -> 1 | CD23: =IF(CE23="","",CE23*$E23) | CF23: =CE23+CC23 -> 1 | CG23: =IF(CH23="","",CH23*$E23) | CI23: =CH23+CF23 -> 1 | CJ23: =IF(CK23="","",CK23*$E23) | CL23: =CK23+CI23 -> 1 | CM23: =IF(CN23="","",CN23*$E23) | CO23: =CN23+CL23 -> 1 | CP23: =IF(CQ23="","",CQ23*$E23) | CR23: =CQ23+CO23 -> 1 | CS23: =IF(CT23="","",CT23*$E23) | CU23: =CT23+CR23 -> 1 | CV23: =IF(CW23="","",CW23*$E23) | CX23: =CW23+CU23 -> 1 | CY23: =IF(CZ23="","",CZ23*$E23) | DA23: =CZ23+CX23 -> 1 | DB23: =IF(DC23="","",DC23*$E23) | DD23: =DC23+DA23 -> 1 | DE23: =IF(DF23="","",DF23*$E23) | DG23: =DF23+DD23 -> 1 | DH23: =IF(DI23="","",DI23*$E23) | DJ23: =DI23+DG23 -> 1
A24: 3 | B24: 3.1.1.1.2 | C24: VIGA DE COROAMENTO | E24: =VLOOKUP(B24,'[49]PLANILHA ORCAMENTARIA'!A:G,7,0) -> 115741.02 | G24: =IF(H24="","",H24*$E24) | I24: =H24 -> 0 | J24: =IF(K24="","",K24*$E24) | L24: =K24+I24 -> 0 | M24: =IF(N24="","",N24*$E24) | O24: =N24+L24 -> 0 | P24: =IF(Q24="","",Q24*$E24) -> 115741.02 | Q24: 1 | R24: =Q24+O24 -> 1 | S24: =IF(T24="","",T24*$E24) | U24: =T24+R24 -> 1 | V24: =IF(W24="","",W24*$E24) | X24: =W24+U24 -> 1 | Y24: =IF(Z24="","",Z24*$E24) | AA24: =Z24+X24 -> 1 | AB24: =IF(AC24="","",AC24*$E24) | AD24: =AC24+AA24 -> 1 | AE24: =IF(AF24="","",AF24*$E24) | AG24: =AF24+AD24 -> 1 | AH24: =IF(AI24="","",AI24*$E24) | AJ24: =AI24+AG24 -> 1 | AK24: =IF(AL24="","",AL24*$E24) | AM24: =AL24+AJ24 -> 1 | AN24: =IF(AO24="","",AO24*$E24) | AP24: =AO24+AM24 -> 1 | AQ24: =IF(AR24="","",AR24*$E24) | AS24: =AR24+AP24 -> 1 | AT24: =IF(AU24="","",AU24*$E24) | AV24: =AU24+AS24 -> 1 | AW24: =IF(AX24="","",AX24*$E24) | AY24: =AX24+AV24 -> 1 | AZ24: =IF(BA24="","",BA24*$E24) | BB24: =BA24+AY24 -> 1 | BC24: =IF(BD24="","",BD24*$E24) | BE24: =BD24+BB24 -> 1 | BF24: =IF(BG24="","",BG24*$E24) | BH24: =BG24+BE24 -> 1 | BI24: =IF(BJ24="","",BJ24*$E24) | BK24: =BJ24+BH24 -> 1 | BL24: =IF(BM24="","",BM24*$E24) | BN24: =BM24+BK24 -> 1 | BO24: =IF(BP24="","",BP24*$E24) | BQ24: =BP24+BN24 -> 1 | BR24: =IF(BS24="","",BS24*$E24) | BT24: =BS24+BQ24 -> 1 | BU24: =IF(BV24="","",BV24*$E24) | BW24: =BV24+BT24 -> 1 | BX24: =IF(BY24="","",BY24*$E24) | BZ24: =BY24+BW24 -> 1 | CA24: =IF(CB24="","",CB24*$E24) | CC24: =CB24+BZ24 -> 1 | CD24: =IF(CE24="","",CE24*$E24) | CF24: =CE24+CC24 -> 1 | CG24: =IF(CH24="","",CH24*$E24) | CI24: =CH24+CF24 -> 1 | CJ24: =IF(CK24="","",CK24*$E24) | CL24: =CK24+CI24 -> 1 | CM24: =IF(CN24="","",CN24*$E24) | CO24: =CN24+CL24 -> 1 | CP24: =IF(CQ24="","",CQ24*$E24) | CR24: =CQ24+CO24 -> 1 | CS24: =IF(CT24="","",CT24*$E24) | CU24: =CT24+CR24 -> 1 | CV24: =IF(CW24="","",CW24*$E24) | CX24: =CW24+CU24 -> 1 | CY24: =IF(CZ24="","",CZ24*$E24) | DA24: =CZ24+CX24 -> 1 | DB24: =IF(DC24="","",DC24*$E24) | DD24: =DC24+DA24 -> 1 | DE24: =IF(DF24="","",DF24*$E24) | DG24: =DF24+DD24 -> 1 | DH24: =IF(DI24="","",DI24*$E24) | DJ24: =DI24+DG24 -> 1
A25: 3 | B25: 3.1.1.1.3 | C25: PAREDE DE CONTENÇÃO | E25: =VLOOKUP(B25,'[49]PLANILHA ORCAMENTARIA'!A:G,7,0) -> 252879.38 | G25: =IF(H25="","",H25*$E25) | I25: =H25 -> 0 | J25: =IF(K25="","",K25*$E25) | L25: =K25+I25 -> 0 | M25: =IF(N25="","",N25*$E25) | O25: =N25+L25 -> 0 | P25: =IF(Q25="","",Q25*$E25) | R25: =Q25+O25 -> 0 | S25: =IF(T25="","",T25*$E25) -> 252879.38 | T25: 1 | U25: =T25+R25 -> 1 | V25: =IF(W25="","",W25*$E25) | X25: =W25+U25 -> 1 | Y25: =IF(Z25="","",Z25*$E25) | AA25: =Z25+X25 -> 1 | AB25: =IF(AC25="","",AC25*$E25) | AD25: =AC25+AA25 -> 1 | AE25: =IF(AF25="","",AF25*$E25) | AG25: =AF25+AD25 -> 1 | AH25: =IF(AI25="","",AI25*$E25) | AJ25: =AI25+AG25 -> 1 | AK25: =IF(AL25="","",AL25*$E25) | AM25: =AL25+AJ25 -> 1 | AN25: =IF(AO25="","",AO25*$E25) | AP25: =AO25+AM25 -> 1 | AQ25: =IF(AR25="","",AR25*$E25) | AS25: =AR25+AP25 -> 1 | AT25: =IF(AU25="","",AU25*$E25) | AV25: =AU25+AS25 -> 1 | AW25: =IF(AX25="","",AX25*$E25) | AY25: =AX25+AV25 -> 1 | AZ25: =IF(BA25="","",BA25*$E25) | BB25: =BA25+AY25 -> 1 | BC25: =IF(BD25="","",BD25*$E25) | BE25: =BD25+BB25 -> 1 | BF25: =IF(BG25="","",BG25*$E25) | BH25: =BG25+BE25 -> 1 | BI25: =IF(BJ25="","",BJ25*$E25) | BK25: =BJ25+BH25 -> 1 | BL25: =IF(BM25="","",BM25*$E25) | BN25: =BM25+BK25 -> 1 | BO25: =IF(BP25="","",BP25*$E25) | BQ25: =BP25+BN25 -> 1 | BR25: =IF(BS25="","",BS25*$E25) | BT25: =BS25+BQ25 -> 1 | BU25: =IF(BV25="","",BV25*$E25) | BW25: =BV25+BT25 -> 1 | BX25: =IF(BY25="","",BY25*$E25) | BZ25: =BY25+BW25 -> 1 | CA25: =IF(CB25="","",CB25*$E25) | CC25: =CB25+BZ25 -> 1 | CD25: =IF(CE25="","",CE25*$E25) | CF25: =CE25+CC25 -> 1 | CG25: =IF(CH25="","",CH25*$E25) | CI25: =CH25+CF25 -> 1 | CJ25: =IF(CK25="","",CK25*$E25) | CL25: =CK25+CI25 -> 1 | CM25: =IF(CN25="","",CN25*$E25) | CO25: =CN25+CL25 -> 1 | CP25: =IF(CQ25="","",CQ25*$E25) | CR25: =CQ25+CO25 -> 1 | CS25: =IF(CT25="","",CT25*$E25) | CU25: =CT25+CR25 -> 1 | CV25: =IF(CW25="","",CW25*$E25) | CX25: =CW25+CU25 -> 1 | CY25: =IF(CZ25="","",CZ25*$E25) | DA25: =CZ25+CX25 -> 1 | DB25: =IF(DC25="","",DC25*$E25) | DD25: =DC25+DA25 -> 1 | DE25: =IF(DF25="","",DF25*$E25) | DG25: =DF25+DD25 -> 1 | DH25: =IF(DI25="","",DI25*$E25) | DJ25: =DI25+DG25 -> 1
A26: 3 | B26: 3.1.1.2 | C26: ESTACAS HÉLICES | E26: =VLOOKUP(B26,'[49]PLANILHA ORCAMENTARIA'!A:G,7,0) -> 612872.71 | G26: =IF(H26="","",H26*E26) | J26: =IF(K26="","",K26*H26) | M26: =IF(N26="","",N26*K26) | P26: =IF(Q26="","",Q26*N26) | S26: =IF(T26="","",T26*Q26) | V26: =IF(W26="","",W26*T26) | Y26: =IF(Z26="","",Z26*W26) | AB26: =IF(AC26="","",AC26*Z26) | AE26: =IF(AF26="","",AF26*AC26) | AH26: =IF(AI26="","",AI26*AF26) | AK26: =IF(AL26="","",AL26*AI26) | AN26: =IF(AO26="","",AO26*AL26) | AQ26: =IF(AR26="","",AR26*AO26) | AT26: =IF(AU26="","",AU26*AR26) | AW26: =IF(AX26="","",AX26*AU26) | AZ26: =IF(BA26="","",BA26*AX26) | BC26: =IF(BD26="","",BD26*BA26) | BF26: =IF(BG26="","",BG26*BD26) | BI26: =IF(BJ26="","",BJ26*BG26) | BL26: =IF(BM26="","",BM26*BJ26) | BO26: =IF(BP26="","",BP26*BM26) | BR26: =IF(BS26="","",BS26*BP26) | BU26: =IF(BV26="","",BV26*BS26) | BX26: =IF(BY26="","",BY26*BV26) | CA26: =IF(CB26="","",CB26*BY26) | CD26: =IF(CE26="","",CE26*CB26) | CG26: =IF(CH26="","",CH26*CE26) | CJ26: =IF(CK26="","",CK26*CH26) | CM26: =IF(CN26="","",CN26*CK26) | CP26: =IF(CQ26="","",CQ26*CN26) | CS26: =IF(CT26="","",CT26*CQ26) | CV26: =IF(CW26="","",CW26*CT26) | CY26: =IF(CZ26="","",CZ26*CW26) | DB26: =IF(DC26="","",DC26*CZ26) | DE26: =IF(DF26="","",DF26*DC26) | DH26: =IF(DI26="","",DI26*DF26)
A27: 3 | B27: 3.1.1.2.1 | C27: SETOR 1 - ESTACA HÉLICES | E27: =VLOOKUP(B27,'[49]PLANILHA ORCAMENTARIA'!A:G,7,0) -> 140375.28 | G27: =IF(H27="","",H27*$E27) | I27: =H27 -> 0 | J27: =IF(K27="","",K27*$E27) | L27: =K27+I27 -> 0 | M27: =IF(N27="","",N27*$E27) | O27: =N27+L27 -> 0 | P27: =IF(Q27="","",Q27*$E27) -> 140375.28 | Q27: 1 | R27: =Q27+O27 -> 1 | S27: =IF(T27="","",T27*$E27) | U27: =T27+R27 -> 1 | V27: =IF(W27="","",W27*$E27) | X27: =W27+U27 -> 1 | Y27: =IF(Z27="","",Z27*$E27) | AA27: =Z27+X27 -> 1 | AB27: =IF(AC27="","",AC27*$E27) | AD27: =AC27+AA27 -> 1 | AE27: =IF(AF27="","",AF27*$E27) | AG27: =AF27+AD27 -> 1 | AH27: =IF(AI27="","",AI27*$E27) | AJ27: =AI27+AG27 -> 1 | AK27: =IF(AL27="","",AL27*$E27) | AM27: =AL27+AJ27 -> 1 | AN27: =IF(AO27="","",AO27*$E27) | AP27: =AO27+AM27 -> 1 | AQ27: =IF(AR27="","",AR27*$E27) | AS27: =AR27+AP27 -> 1 | AT27: =IF(AU27="","",AU27*$E27) | AV27: =AU27+AS27 -> 1 | AW27: =IF(AX27="","",AX27*$E27) | AY27: =AX27+AV27 -> 1 | AZ27: =IF(BA27="","",BA27*$E27) | BB27: =BA27+AY27 -> 1 | BC27: =IF(BD27="","",BD27*$E27) | BE27: =BD27+BB27 -> 1 | BF27: =IF(BG27="","",BG27*$E27) | BH27: =BG27+BE27 -> 1 | BI27: =IF(BJ27="","",BJ27*$E27) | BK27: =BJ27+BH27 -> 1 | BL27: =IF(BM27="","",BM27*$E27) | BN27: =BM27+BK27 -> 1 | BO27: =IF(BP27="","",BP27*$E27) | BQ27: =BP27+BN27 -> 1 | BR27: =IF(BS27="","",BS27*$E27) | BT27: =BS27+BQ27 -> 1 | BU27: =IF(BV27="","",BV27*$E27) | BW27: =BV27+BT27 -> 1 | BX27: =IF(BY27="","",BY27*$E27) | BZ27: =BY27+BW27 -> 1 | CA27: =IF(CB27="","",CB27*$E27) | CC27: =CB27+BZ27 -> 1 | CD27: =IF(CE27="","",CE27*$E27) | CF27: =CE27+CC27 -> 1 | CG27: =IF(CH27="","",CH27*$E27) | CI27: =CH27+CF27 -> 1 | CJ27: =IF(CK27="","",CK27*$E27) | CL27: =CK27+CI27 -> 1 | CM27: =IF(CN27="","",CN27*$E27) | CO27: =CN27+CL27 -> 1 | CP27: =IF(CQ27="","",CQ27*$E27) | CR27: =CQ27+CO27 -> 1 | CS27: =IF(CT27="","",CT27*$E27) | CU27: =CT27+CR27 -> 1 | CV27: =IF(CW27="","",CW27*$E27) | CX27: =CW27+CU27 -> 1 | CY27: =IF(CZ27="","",CZ27*$E27) | DA27: =CZ27+CX27 -> 1 | DB27: =IF(DC27="","",DC27*$E27) | DD27: =DC27+DA27 -> 1 | DE27: =IF(DF27="","",DF27*$E27) | DG27: =DF27+DD27 -> 1 | DH27: =IF(DI27="","",DI27*$E27) | DJ27: =DI27+DG27 -> 1
A28: 3 | B28: 3.1.1.2.2 | C28: SETOR 2 - ESTACA HÉLICES | E28: =VLOOKUP(B28,'[49]PLANILHA ORCAMENTARIA'!A:G,7,0) -> 159484.82 | G28: =IF(H28="","",H28*$E28) | I28: =H28 -> 0 | J28: =IF(K28="","",K28*$E28) | L28: =K28+I28 -> 0 | M28: =IF(N28="","",N28*$E28) | O28: =N28+L28 -> 0 | P28: =IF(Q28="","",Q28*$E28) | R28: =Q28+O28 -> 0 | S28: =IF(T28="","",T28*$E28) -> 159484.82 | T28: 1 | U28: =T28+R28 -> 1 | V28: =IF(W28="","",W28*$E28) | X28: =W28+U28 -> 1 | Y28: =IF(Z28="","",Z28*$E28) | AA28: =Z28+X28 -> 1 | AB28: =IF(AC28="","",AC28*$E28) | AD28: =AC28+AA28 -> 1 | AE28: =IF(AF28="","",AF28*$E28) | AG28: =AF28+AD28 -> 1 | AH28: =IF(AI28="","",AI28*$E28) | AJ28: =AI28+AG28 -> 1 | AK28: =IF(AL28="","",AL28*$E28) | AM28: =AL28+AJ28 -> 1 | AN28: =IF(AO28="","",AO28*$E28) | AP28: =AO28+AM28 -> 1 | AQ28: =IF(AR28="","",AR28*$E28) | AS28: =AR28+AP28 -> 1 | AT28: =IF(AU28="","",AU28*$E28) | AV28: =AU28+AS28 -> 1 | AW28: =IF(AX28="","",AX28*$E28) | AY28: =AX28+AV28 -> 1 | AZ28: =IF(BA28="","",BA28*$E28) | BB28: =BA28+AY28 -> 1 | BC28: =IF(BD28="","",BD28*$E28) | BE28: =BD28+BB28 -> 1 | BF28: =IF(BG28="","",BG28*$E28) | BH28: =BG28+BE28 -> 1 | BI28: =IF(BJ28="","",BJ28*$E28) | BK28: =BJ28+BH28 -> 1 | BL28: =IF(BM28="","",BM28*$E28) | BN28: =BM28+BK28 -> 1 | BO28: =IF(BP28="","",BP28*$E28) | BQ28: =BP28+BN28 -> 1 | BR28: =IF(BS28="","",BS28*$E28) | BT28: =BS28+BQ28 -> 1 | BU28: =IF(BV28="","",BV28*$E28) | BW28: =BV28+BT28 -> 1 | BX28: =IF(BY28="","",BY28*$E28) | BZ28: =BY28+BW28 -> 1 | CA28: =IF(CB28="","",CB28*$E28) | CC28: =CB28+BZ28 -> 1 | CD28: =IF(CE28="","",CE28*$E28) | CF28: =CE28+CC28 -> 1 | CG28: =IF(CH28="","",CH28*$E28) | CI28: =CH28+CF28 -> 1 | CJ28: =IF(CK28="","",CK28*$E28) | CL28: =CK28+CI28 -> 1 | CM28: =IF(CN28="","",CN28*$E28) | CO28: =CN28+CL28 -> 1 | CP28: =IF(CQ28="","",CQ28*$E28) | CR28: =CQ28+CO28 -> 1 | CS28: =IF(CT28="","",CT28*$E28) | CU28: =CT28+CR28 -> 1 | CV28: =IF(CW28="","",CW28*$E28) | CX28: =CW28+CU28 -> 1 | CY28: =IF(CZ28="","",CZ28*$E28) | DA28: =CZ28+CX28 -> 1 | DB28: =IF(DC28="","",DC28*$E28) | DD28: =DC28+DA28 -> 1 | DE28: =IF(DF28="","",DF28*$E28) | DG28: =DF28+DD28 -> 1 | DH28: =IF(DI28="","",DI28*$E28) | DJ28: =DI28+DG28 -> 1
A29: 3 | B29: 3.1.1.2.3 | C29: SETOR 3 - ESTACA HÉLICES | E29: =VLOOKUP(B29,'[49]PLANILHA ORCAMENTARIA'!A:G,7,0) -> 313012.61 | G29: =IF(H29="","",H29*$E29) | I29: =H29 -> 0 | J29: =IF(K29="","",K29*$E29) | L29: =K29+I29 -> 0 | M29: =IF(N29="","",N29*$E29) | O29: =N29+L29 -> 0 | P29: =IF(Q29="","",Q29*$E29) | R29: =Q29+O29 -> 0 | S29: =IF(T29="","",T29*$E29) -> 313012.61 | T29: 1 | U29: =T29+R29 -> 1 | V29: =IF(W29="","",W29*$E29) | X29: =W29+U29 -> 1 | Y29: =IF(Z29="","",Z29*$E29) | AA29: =Z29+X29 -> 1 | AB29: =IF(AC29="","",AC29*$E29) | AD29: =AC29+AA29 -> 1 | AE29: =IF(AF29="","",AF29*$E29) | AG29: =AF29+AD29 -> 1 | AH29: =IF(AI29="","",AI29*$E29) | AJ29: =AI29+AG29 -> 1 | AK29: =IF(AL29="","",AL29*$E29) | AM29: =AL29+AJ29 -> 1 | AN29: =IF(AO29="","",AO29*$E29) | AP29: =AO29+AM29 -> 1 | AQ29: =IF(AR29="","",AR29*$E29) | AS29: =AR29+AP29 -> 1 | AT29: =IF(AU29="","",AU29*$E29) | AV29: =AU29+AS29 -> 1 | AW29: =IF(AX29="","",AX29*$E29) | AY29: =AX29+AV29 -> 1 | AZ29: =IF(BA29="","",BA29*$E29) | BB29: =BA29+AY29 -> 1 | BC29: =IF(BD29="","",BD29*$E29) | BE29: =BD29+BB29 -> 1 | BF29: =IF(BG29="","",BG29*$E29) | BH29: =BG29+BE29 -> 1 | BI29: =IF(BJ29="","",BJ29*$E29) | BK29: =BJ29+BH29 -> 1 | BL29: =IF(BM29="","",BM29*$E29) | BN29: =BM29+BK29 -> 1 | BO29: =IF(BP29="","",BP29*$E29) | BQ29: =BP29+BN29 -> 1 | BR29: =IF(BS29="","",BS29*$E29) | BT29: =BS29+BQ29 -> 1 | BU29: =IF(BV29="","",BV29*$E29) | BW29: =BV29+BT29 -> 1 | BX29: =IF(BY29="","",BY29*$E29) | BZ29: =BY29+BW29 -> 1 | CA29: =IF(CB29="","",CB29*$E29) | CC29: =CB29+BZ29 -> 1 | CD29: =IF(CE29="","",CE29*$E29) | CF29: =CE29+CC29 -> 1 | CG29: =IF(CH29="","",CH29*$E29) | CI29: =CH29+CF29 -> 1 | CJ29: =IF(CK29="","",CK29*$E29) | CL29: =CK29+CI29 -> 1 | CM29: =IF(CN29="","",CN29*$E29) | CO29: =CN29+CL29 -> 1 | CP29: =IF(CQ29="","",CQ29*$E29) | CR29: =CQ29+CO29 -> 1 | CS29: =IF(CT29="","",CT29*$E29) | CU29: =CT29+CR29 -> 1 | CV29: =IF(CW29="","",CW29*$E29) | CX29: =CW29+CU29 -> 1 | CY29: =IF(CZ29="","",CZ29*$E29) | DA29: =CZ29+CX29 -> 1 | DB29: =IF(DC29="","",DC29*$E29) | DD29: =DC29+DA29 -> 1 | DE29: =IF(DF29="","",DF29*$E29) | DG29: =DF29+DD29 -> 1 | DH29: =IF(DI29="","",DI29*$E29) | DJ29: =DI29+DG29 -> 1
A30: 3 | B30: 3.1.1.3 | C30: BLOCOS DE FUNDAÇÃO | E30: =VLOOKUP(B30,'[49]PLANILHA ORCAMENTARIA'!A:G,7,0) -> 323614.08 | G30: =IF(H30="","",H30*E30) | J30: =IF(K30="","",K30*H30) | M30: =IF(N30="","",N30*K30) | P30: =IF(Q30="","",Q30*N30) | S30: =IF(T30="","",T30*Q30) | V30: =IF(W30="","",W30*T30) | Y30: =IF(Z30="","",Z30*W30) | AB30: =IF(AC30="","",AC30*Z30) | AE30: =IF(AF30="","",AF30*AC30) | AH30: =IF(AI30="","",AI30*AF30) | AK30: =IF(AL30="","",AL30*AI30) | AN30: =IF(AO30="","",AO30*AL30) | AQ30: =IF(AR30="","",AR30*AO30) | AT30: =IF(AU30="","",AU30*AR30) | AW30: =IF(AX30="","",AX30*AU30) | AZ30: =IF(BA30="","",BA30*AX30) | BC30: =IF(BD30="","",BD30*BA30) | BF30: =IF(BG30="","",BG30*BD30) | BI30: =IF(BJ30="","",BJ30*BG30) | BL30: =IF(BM30="","",BM30*BJ30) | BO30: =IF(BP30="","",BP30*BM30) | BR30: =IF(BS30="","",BS30*BP30) | BU30: =IF(BV30="","",BV30*BS30) | BX30: =IF(BY30="","",BY30*BV30) | CA30: =IF(CB30="","",CB30*BY30) | CD30: =IF(CE30="","",CE30*CB30) | CG30: =IF(CH30="","",CH30*CE30) | CJ30: =IF(CK30="","",CK30*CH30) | CM30: =IF(CN30="","",CN30*CK30) | CP30: =IF(CQ30="","",CQ30*CN30) | CS30: =IF(CT30="","",CT30*CQ30) | CV30: =IF(CW30="","",CW30*CT30) | CY30: =IF(CZ30="","",CZ30*CW30) | DB30: =IF(DC30="","",DC30*CZ30) | DE30: =IF(DF30="","",DF30*DC30) | DH30: =IF(DI30="","",DI30*DF30)
A31: 3 | B31: 3.1.1.3.1 | C31: SETOR 1 - BLOCO DE FUNDAÇÃO | E31: =VLOOKUP(B31,'[49]PLANILHA ORCAMENTARIA'!A:G,7,0) -> 78165.999 | G31: =IF(H31="","",H31*$E31) | I31: =H31 -> 0 | J31: =IF(K31="","",K31*$E31) | L31: =K31+I31 -> 0 | M31: =IF(N31="","",N31*$E31) | O31: =N31+L31 -> 0 | P31: =IF(Q31="","",Q31*$E31) | R31: =Q31+O31 -> 0 | S31: =IF(T31="","",T31*$E31) -> 78165.999 | T31: 1 | U31: =T31+R31 -> 1 | V31: =IF(W31="","",W31*$E31) | X31: =W31+U31 -> 1 | Y31: =IF(Z31="","",Z31*$E31) | AA31: =Z31+X31 -> 1 | AB31: =IF(AC31="","",AC31*$E31) | AD31: =AC31+AA31 -> 1 | AE31: =IF(AF31="","",AF31*$E31) | AG31: =AF31+AD31 -> 1 | AH31: =IF(AI31="","",AI31*$E31) | AJ31: =AI31+AG31 -> 1 | AK31: =IF(AL31="","",AL31*$E31) | AM31: =AL31+AJ31 -> 1 | AN31: =IF(AO31="","",AO31*$E31) | AP31: =AO31+AM31 -> 1 | AQ31: =IF(AR31="","",AR31*$E31) | AS31: =AR31+AP31 -> 1 | AT31: =IF(AU31="","",AU31*$E31) | AV31: =AU31+AS31 -> 1 | AW31: =IF(AX31="","",AX31*$E31) | AY31: =AX31+AV31 -> 1 | AZ31: =IF(BA31="","",BA31*$E31) | BB31: =BA31+AY31 -> 1 | BC31: =IF(BD31="","",BD31*$E31) | BE31: =BD31+BB31 -> 1 | BF31: =IF(BG31="","",BG31*$E31) | BH31: =BG31+BE31 -> 1 | BI31: =IF(BJ31="","",BJ31*$E31) | BK31: =BJ31+BH31 -> 1 | BL31: =IF(BM31="","",BM31*$E31) | BN31: =BM31+BK31 -> 1 | BO31: =IF(BP31="","",BP31*$E31) | BQ31: =BP31+BN31 -> 1 | BR31: =IF(BS31="","",BS31*$E31) | BT31: =BS31+BQ31 -> 1 | BU31: =IF(BV31="","",BV31*$E31) | BW31: =BV31+BT31 -> 1 | BX31: =IF(BY31="","",BY31*$E31) | BZ31: =BY31+BW31 -> 1 | CA31: =IF(CB31="","",CB31*$E31) | CC31: =CB31+BZ31 -> 1 | CD31: =IF(CE31="","",CE31*$E31) | CF31: =CE31+CC31 -> 1 | CG31: =IF(CH31="","",CH31*$E31) | CI31: =CH31+CF31 -> 1 | CJ31: =IF(CK31="","",CK31*$E31) | CL31: =CK31+CI31 -> 1 | CM31: =IF(CN31="","",CN31*$E31) | CO31: =CN31+CL31 -> 1 | CP31: =IF(CQ31="","",CQ31*$E31) | CR31: =CQ31+CO31 -> 1 | CS31: =IF(CT31="","",CT31*$E31) | CU31: =CT31+CR31 -> 1 | CV31: =IF(CW31="","",CW31*$E31) | CX31: =CW31+CU31 -> 1 | CY31: =IF(CZ31="","",CZ31*$E31) | DA31: =CZ31+CX31 -> 1 | DB31: =IF(DC31="","",DC31*$E31) | DD31: =DC31+DA31 -> 1 | DE31: =IF(DF31="","",DF31*$E31) | DG31: =DF31+DD31 -> 1 | DH31: =IF(DI31="","",DI31*$E31) | DJ31: =DI31+DG31 -> 1
A32: 3 | B32: 3.1.1.3.2 | C32: SETOR 2 - BLOCO DE FUNDAÇÃO | E32: =VLOOKUP(B32,'[49]PLANILHA ORCAMENTARIA'!A:G,7,0) -> 75886.205 | G32: =IF(H32="","",H32*$E32) | I32: =H32 -> 0 | J32: =IF(K32="","",K32*$E32) | L32: =K32+I32 -> 0 | M32: =IF(N32="","",N32*$E32) | O32: =N32+L32 -> 0 | P32: =IF(Q32="","",Q32*$E32) | R32: =Q32+O32 -> 0 | S32: =IF(T32="","",T32*$E32) | U32: =T32+R32 -> 0 | V32: =IF(W32="","",W32*$E32) | X32: =W32+U32 -> 0 | Y32: =IF(Z32="","",Z32*$E32) | AA32: =Z32+X32 -> 0 | AB32: =IF(AC32="","",AC32*$E32) | AD32: =AC32+AA32 -> 0 | AE32: =IF(AF32="","",AF32*$E32) | AG32: =AF32+AD32 -> 0 | AH32: =IF(AI32="","",AI32*$E32) | AJ32: =AI32+AG32 -> 0 | AK32: =IF(AL32="","",AL32*$E32) | AM32: =AL32+AJ32 -> 0 | AN32: =IF(AO32="","",AO32*$E32) | AP32: =AO32+AM32 -> 0 | AQ32: =IF(AR32="","",AR32*$E32) | AS32: =AR32+AP32 -> 0 | AT32: =IF(AU32="","",AU32*$E32) | AV32: =AU32+AS32 -> 0 | AW32: =IF(AX32="","",AX32*$E32) | AY32: =AX32+AV32 -> 0 | AZ32: =IF(BA32="","",BA32*$E32) | BB32: =BA32+AY32 -> 0 | BC32: =IF(BD32="","",BD32*$E32) | BE32: =BD32+BB32 -> 0 | BF32: =IF(BG32="","",BG32*$E32) | BH32: =BG32+BE32 -> 0 | BI32: =IF(BJ32="","",BJ32*$E32) | BK32: =BJ32+BH32 -> 0 | BL32: =IF(BM32="","",BM32*$E32) | BN32: =BM32+BK32 -> 0 | BO32: =IF(BP32="","",BP32*$E32) | BQ32: =BP32+BN32 -> 0 | BR32: =IF(BS32="","",BS32*$E32) | BT32: =BS32+BQ32 -> 0 | BU32: =IF(BV32="","",BV32*$E32) | BW32: =BV32+BT32 -> 0 | BX32: =IF(BY32="","",BY32*$E32) | BZ32: =BY32+BW32 -> 0 | CA32: =IF(CB32="","",CB32*$E32) | CC32: =CB32+BZ32 -> 0 | CD32: =IF(CE32="","",CE32*$E32) | CF32: =CE32+CC32 -> 0 | CG32: =IF(CH32="","",CH32*$E32) | CI32: =CH32+CF32 -> 0 | CJ32: =IF(CK32="","",CK32*$E32) | CL32: =CK32+CI32 -> 0 | CM32: =IF(CN32="","",CN32*$E32) | CO32: =CN32+CL32 -> 0 | CP32: =IF(CQ32="","",CQ32*$E32) | CR32: =CQ32+CO32 -> 0 | CS32: =IF(CT32="","",CT32*$E32) | CU32: =CT32+CR32 -> 0 | CV32: =IF(CW32="","",CW32*$E32) | CX32: =CW32+CU32 -> 0 | CY32: =IF(CZ32="","",CZ32*$E32) | DA32: =CZ32+CX32 -> 0 | DB32: =IF(DC32="","",DC32*$E32) | DD32: =DC32+DA32 -> 0 | DE32: =IF(DF32="","",DF32*$E32) | DG32: =DF32+DD32 -> 0 | DH32: =IF(DI32="","",DI32*$E32) | DJ32: =DI32+DG32 -> 0
A33: 3 | B33: 3.1.1.3.3 | C33: SETOR 3 - BLOCO DE FUNDAÇÃO | E33: =VLOOKUP(B33,'[49]PLANILHA ORCAMENTARIA'!A:G,7,0) -> 169561.88 | G33: =IF(H33="","",H33*$E33) | I33: =H33 -> 0 | J33: =IF(K33="","",K33*$E33) | L33: =K33+I33 -> 0 | M33: =IF(N33="","",N33*$E33) | O33: =N33+L33 -> 0 | P33: =IF(Q33="","",Q33*$E33) | R33: =Q33+O33 -> 0 | S33: =IF(T33="","",T33*$E33) | U33: =T33+R33 -> 0 | V33: =IF(W33="","",W33*$E33) | X33: =W33+U33 -> 0 | Y33: =IF(Z33="","",Z33*$E33) | AA33: =Z33+X33 -> 0 | AB33: =IF(AC33="","",AC33*$E33) | AD33: =AC33+AA33 -> 0 | AE33: =IF(AF33="","",AF33*$E33) | AG33: =AF33+AD33 -> 0 | AH33: =IF(AI33="","",AI33*$E33) | AJ33: =AI33+AG33 -> 0 | AK33: =IF(AL33="","",AL33*$E33) | AM33: =AL33+AJ33 -> 0 | AN33: =IF(AO33="","",AO33*$E33) | AP33: =AO33+AM33 -> 0 | AQ33: =IF(AR33="","",AR33*$E33) | AS33: =AR33+AP33 -> 0 | AT33: =IF(AU33="","",AU33*$E33) | AV33: =AU33+AS33 -> 0 | AW33: =IF(AX33="","",AX33*$E33) | AY33: =AX33+AV33 -> 0 | AZ33: =IF(BA33="","",BA33*$E33) | BB33: =BA33+AY33 -> 0 | BC33: =IF(BD33="","",BD33*$E33) | BE33: =BD33+BB33 -> 0 | BF33: =IF(BG33="","",BG33*$E33) | BH33: =BG33+BE33 -> 0 | BI33: =IF(BJ33="","",BJ33*$E33) | BK33: =BJ33+BH33 -> 0 | BL33: =IF(BM33="","",BM33*$E33) | BN33: =BM33+BK33 -> 0 | BO33: =IF(BP33="","",BP33*$E33) | BQ33: =BP33+BN33 -> 0 | BR33: =IF(BS33="","",BS33*$E33) | BT33: =BS33+BQ33 -> 0 | BU33: =IF(BV33="","",BV33*$E33) | BW33: =BV33+BT33 -> 0 | BX33: =IF(BY33="","",BY33*$E33) | BZ33: =BY33+BW33 -> 0 | CA33: =IF(CB33="","",CB33*$E33) | CC33: =CB33+BZ33 -> 0 | CD33: =IF(CE33="","",CE33*$E33) | CF33: =CE33+CC33 -> 0 | CG33: =IF(CH33="","",CH33*$E33) | CI33: =CH33+CF33 -> 0 | CJ33: =IF(CK33="","",CK33*$E33) | CL33: =CK33+CI33 -> 0 | CM33: =IF(CN33="","",CN33*$E33) | CO33: =CN33+CL33 -> 0 | CP33: =IF(CQ33="","",CQ33*$E33) | CR33: =CQ33+CO33 -> 0 | CS33: =IF(CT33="","",CT33*$E33) | CU33: =CT33+CR33 -> 0 | CV33: =IF(CW33="","",CW33*$E33) | CX33: =CW33+CU33 -> 0 | CY33: =IF(CZ33="","",CZ33*$E33) | DA33: =CZ33+CX33 -> 0 | DB33: =IF(DC33="","",DC33*$E33) | DD33: =DC33+DA33 -> 0 | DE33: =IF(DF33="","",DF33*$E33) | DG33: =DF33+DD33 -> 0 | DH33: =IF(DI33="","",DI33*$E33) | DJ33: =DI33+DG33 -> 0
A34: 3 | B34: 3.1.1.4 | C34: VIGAS BALDRAMES | E34: =VLOOKUP(B34,'[49]PLANILHA ORCAMENTARIA'!A:G,7,0) -> 128336.93 | G34: =IF(H34="","",H34*$E34) | I34: =H34 -> 0 | J34: =IF(K34="","",K34*$E34) | L34: =K34+I34 -> 0 | M34: =IF(N34="","",N34*$E34) | O34: =N34+L34 -> 0 | P34: =IF(Q34="","",Q34*$E34) | R34: =Q34+O34 -> 0 | S34: =IF(T34="","",T34*$E34) | U34: =T34+R34 -> 0 | V34: =IF(W34="","",W34*$E34) | X34: =W34+U34 -> 0 | Y34: =IF(Z34="","",Z34*$E34) | AA34: =Z34+X34 -> 0 | AB34: =IF(AC34="","",AC34*$E34) | AD34: =AC34+AA34 -> 0 | AE34: =IF(AF34="","",AF34*$E34) | AG34: =AF34+AD34 -> 0 | AH34: =IF(AI34="","",AI34*$E34) | AJ34: =AI34+AG34 -> 0 | AK34: =IF(AL34="","",AL34*$E34) | AM34: =AL34+AJ34 -> 0 | AN34: =IF(AO34="","",AO34*$E34) | AP34: =AO34+AM34 -> 0 | AQ34: =IF(AR34="","",AR34*$E34) | AS34: =AR34+AP34 -> 0 | AT34: =IF(AU34="","",AU34*$E34) | AV34: =AU34+AS34 -> 0 | AW34: =IF(AX34="","",AX34*$E34) | AY34: =AX34+AV34 -> 0 | AZ34: =IF(BA34="","",BA34*$E34) | BB34: =BA34+AY34 -> 0 | BC34: =IF(BD34="","",BD34*$E34) | BE34: =BD34+BB34 -> 0 | BF34: =IF(BG34="","",BG34*$E34) | BH34: =BG34+BE34 -> 0 | BI34: =IF(BJ34="","",BJ34*$E34) | BK34: =BJ34+BH34 -> 0 | BL34: =IF(BM34="","",BM34*$E34) | BN34: =BM34+BK34 -> 0 | BO34: =IF(BP34="","",BP34*$E34) | BQ34: =BP34+BN34 -> 0 | BR34: =IF(BS34="","",BS34*$E34) | BT34: =BS34+BQ34 -> 0 | BU34: =IF(BV34="","",BV34*$E34) | BW34: =BV34+BT34 -> 0 | BX34: =IF(BY34="","",BY34*$E34) | BZ34: =BY34+BW34 -> 0 | CA34: =IF(CB34="","",CB34*$E34) | CC34: =CB34+BZ34 -> 0 | CD34: =IF(CE34="","",CE34*$E34) | CF34: =CE34+CC34 -> 0 | CG34: =IF(CH34="","",CH34*$E34) | CI34: =CH34+CF34 -> 0 | CJ34: =IF(CK34="","",CK34*$E34) | CL34: =CK34+CI34 -> 0 | CM34: =IF(CN34="","",CN34*$E34) | CO34: =CN34+CL34 -> 0 | CP34: =IF(CQ34="","",CQ34*$E34) | CR34: =CQ34+CO34 -> 0 | CS34: =IF(CT34="","",CT34*$E34) | CU34: =CT34+CR34 -> 0 | CV34: =IF(CW34="","",CW34*$E34) | CX34: =CW34+CU34 -> 0 | CY34: =IF(CZ34="","",CZ34*$E34) | DA34: =CZ34+CX34 -> 0 | DB34: =IF(DC34="","",DC34*$E34) | DD34: =DC34+DA34 -> 0 | DE34: =IF(DF34="","",DF34*$E34) | DG34: =DF34+DD34 -> 0 | DH34: =IF(DI34="","",DI34*$E34) | DJ34: =DI34+DG34 -> 0
A35: 3 | B35: 3.1.1.5 | C35: ESCAVAÇÕES / ATERRO | E35: =VLOOKUP(B35,'[49]PLANILHA ORCAMENTARIA'!A:G,7,0) -> 14284.56 | G35: =IF(H35="","",H35*$E35) | I35: =H35 -> 0 | J35: =IF(K35="","",K35*$E35) | L35: =K35+I35 -> 0 | M35: =IF(N35="","",N35*$E35) | O35: =N35+L35 -> 0 | P35: =IF(Q35="","",Q35*$E35) | R35: =Q35+O35 -> 0 | S35: =IF(T35="","",T35*$E35) | U35: =T35+R35 -> 0 | V35: =IF(W35="","",W35*$E35) | X35: =W35+U35 -> 0 | Y35: =IF(Z35="","",Z35*$E35) | AA35: =Z35+X35 -> 0 | AB35: =IF(AC35="","",AC35*$E35) | AD35: =AC35+AA35 -> 0 | AE35: =IF(AF35="","",AF35*$E35) | AG35: =AF35+AD35 -> 0 | AH35: =IF(AI35="","",AI35*$E35) | AJ35: =AI35+AG35 -> 0 | AK35: =IF(AL35="","",AL35*$E35) | AM35: =AL35+AJ35 -> 0 | AN35: =IF(AO35="","",AO35*$E35) | AP35: =AO35+AM35 -> 0 | AQ35: =IF(AR35="","",AR35*$E35) | AS35: =AR35+AP35 -> 0 | AT35: =IF(AU35="","",AU35*$E35) | AV35: =AU35+AS35 -> 0 | AW35: =IF(AX35="","",AX35*$E35) | AY35: =AX35+AV35 -> 0 | AZ35: =IF(BA35="","",BA35*$E35) | BB35: =BA35+AY35 -> 0 | BC35: =IF(BD35="","",BD35*$E35) | BE35: =BD35+BB35 -> 0 | BF35: =IF(BG35="","",BG35*$E35) | BH35: =BG35+BE35 -> 0 | BI35: =IF(BJ35="","",BJ35*$E35) | BK35: =BJ35+BH35 -> 0 | BL35: =IF(BM35="","",BM35*$E35) | BN35: =BM35+BK35 -> 0 | BO35: =IF(BP35="","",BP35*$E35) | BQ35: =BP35+BN35 -> 0 | BR35: =IF(BS35="","",BS35*$E35) | BT35: =BS35+BQ35 -> 0 | BU35: =IF(BV35="","",BV35*$E35) | BW35: =BV35+BT35 -> 0 | BX35: =IF(BY35="","",BY35*$E35) | BZ35: =BY35+BW35 -> 0 | CA35: =IF(CB35="","",CB35*$E35) | CC35: =CB35+BZ35 -> 0 | CD35: =IF(CE35="","",CE35*$E35) | CF35: =CE35+CC35 -> 0 | CG35: =IF(CH35="","",CH35*$E35) | CI35: =CH35+CF35 -> 0 | CJ35: =IF(CK35="","",CK35*$E35) | CL35: =CK35+CI35 -> 0 | CM35: =IF(CN35="","",CN35*$E35) | CO35: =CN35+CL35 -> 0 | CP35: =IF(CQ35="","",CQ35*$E35) | CR35: =CQ35+CO35 -> 0 | CS35: =IF(CT35="","",CT35*$E35) | CU35: =CT35+CR35 -> 0 | CV35: =IF(CW35="","",CW35*$E35) | CX35: =CW35+CU35 -> 0 | CY35: =IF(CZ35="","",CZ35*$E35) | DA35: =CZ35+CX35 -> 0 | DB35: =IF(DC35="","",DC35*$E35) | DD35: =DC35+DA35 -> 0 | DE35: =IF(DF35="","",DF35*$E35) | DG35: =DF35+DD35 -> 0 | DH35: =IF(DI35="","",DI35*$E35) | DJ35: =DI35+DG35 -> 0
A36: 3 | B36: 3.1.2 | C36: BLOCO ANEXO | E36: =VLOOKUP(B36,'[49]PLANILHA ORCAMENTARIA'!A:G,7,0) -> 120167.37 | G36: =IF(H36="","",H36*E36) | J36: =IF(K36="","",K36*H36) | M36: =IF(N36="","",N36*K36) | P36: =IF(Q36="","",Q36*N36) | S36: =IF(T36="","",T36*Q36) | V36: =IF(W36="","",W36*T36) | Y36: =IF(Z36="","",Z36*W36) | AB36: =IF(AC36="","",AC36*Z36) | AE36: =IF(AF36="","",AF36*AC36) | AH36: =IF(AI36="","",AI36*AF36) | AK36: =IF(AL36="","",AL36*AI36) | AN36: =IF(AO36="","",AO36*AL36) | AQ36: =IF(AR36="","",AR36*AO36) | AT36: =IF(AU36="","",AU36*AR36) | AW36: =IF(AX36="","",AX36*AU36) | AZ36: =IF(BA36="","",BA36*AX36) | BC36: =IF(BD36="","",BD36*BA36) | BF36: =IF(BG36="","",BG36*BD36) | BI36: =IF(BJ36="","",BJ36*BG36) | BL36: =IF(BM36="","",BM36*BJ36) | BO36: =IF(BP36="","",BP36*BM36) | BR36: =IF(BS36="","",BS36*BP36) | BU36: =IF(BV36="","",BV36*BS36) | BX36: =IF(BY36="","",BY36*BV36) | CA36: =IF(CB36="","",CB36*BY36) | CD36: =IF(CE36="","",CE36*CB36) | CG36: =IF(CH36="","",CH36*CE36) | CJ36: =IF(CK36="","",CK36*CH36) | CM36: =IF(CN36="","",CN36*CK36) | CP36: =IF(CQ36="","",CQ36*CN36) | CS36: =IF(CT36="","",CT36*CQ36) | CV36: =IF(CW36="","",CW36*CT36) | CY36: =IF(CZ36="","",CZ36*CW36) | DB36: =IF(DC36="","",DC36*CZ36) | DE36: =IF(DF36="","",DF36*DC36) | DH36: =IF(DI36="","",DI36*DF36)
A37: 3 | B37: 3.1.2.1 | C37: BLOCOS DE FUNDAÇÃO / VIGAS BALDRAMES | E37: =VLOOKUP(B37,'[49]PLANILHA ORCAMENTARIA'!A:G,7,0) -> 120167.37 | G37: =IF(H37="","",H37*$E37) | I37: =H37 -> 0 | J37: =IF(K37="","",K37*$E37) | L37: =K37+I37 -> 0 | M37: =IF(N37="","",N37*$E37) | O37: =N37+L37 -> 0 | P37: =IF(Q37="","",Q37*$E37) -> 120167.37 | Q37: 1 | R37: =Q37+O37 -> 1 | S37: =IF(T37="","",T37*$E37) | U37: =T37+R37 -> 1 | V37: =IF(W37="","",W37*$E37) | X37: =W37+U37 -> 1 | Y37: =IF(Z37="","",Z37*$E37) | AA37: =Z37+X37 -> 1 | AB37: =IF(AC37="","",AC37*$E37) | AD37: =AC37+AA37 -> 1 | AE37: =IF(AF37="","",AF37*$E37) | AG37: =AF37+AD37 -> 1 | AH37: =IF(AI37="","",AI37*$E37) | AJ37: =AI37+AG37 -> 1 | AK37: =IF(AL37="","",AL37*$E37) | AM37: =AL37+AJ37 -> 1 | AN37: =IF(AO37="","",AO37*$E37) | AP37: =AO37+AM37 -> 1 | AQ37: =IF(AR37="","",AR37*$E37) | AS37: =AR37+AP37 -> 1 | AT37: =IF(AU37="","",AU37*$E37) | AV37: =AU37+AS37 -> 1 | AW37: =IF(AX37="","",AX37*$E37) | AY37: =AX37+AV37 -> 1 | AZ37: =IF(BA37="","",BA37*$E37) | BB37: =BA37+AY37 -> 1 | BC37: =IF(BD37="","",BD37*$E37) | BE37: =BD37+BB37 -> 1 | BF37: =IF(BG37="","",BG37*$E37) | BH37: =BG37+BE37 -> 1 | BI37: =IF(BJ37="","",BJ37*$E37) | BK37: =BJ37+BH37 -> 1 | BL37: =IF(BM37="","",BM37*$E37) | BN37: =BM37+BK37 -> 1 | BO37: =IF(BP37="","",BP37*$E37) | BQ37: =BP37+BN37 -> 1 | BR37: =IF(BS37="","",BS37*$E37) | BT37: =BS37+BQ37 -> 1 | BU37: =IF(BV37="","",BV37*$E37) | BW37: =BV37+BT37 -> 1 | BX37: =IF(BY37="","",BY37*$E37) | BZ37: =BY37+BW37 -> 1 | CA37: =IF(CB37="","",CB37*$E37) | CC37: =CB37+BZ37 -> 1 | CD37: =IF(CE37="","",CE37*$E37) | CF37: =CE37+CC37 -> 1 | CG37: =IF(CH37="","",CH37*$E37) | CI37: =CH37+CF37 -> 1 | CJ37: =IF(CK37="","",CK37*$E37) | CL37: =CK37+CI37 -> 1 | CM37: =IF(CN37="","",CN37*$E37) | CO37: =CN37+CL37 -> 1 | CP37: =IF(CQ37="","",CQ37*$E37) | CR37: =CQ37+CO37 -> 1 | CS37: =IF(CT37="","",CT37*$E37) | CU37: =CT37+CR37 -> 1 | CV37: =IF(CW37="","",CW37*$E37) | CX37: =CW37+CU37 -> 1 | CY37: =IF(CZ37="","",CZ37*$E37) | DA37: =CZ37+CX37 -> 1 | DB37: =IF(DC37="","",DC37*$E37) | DD37: =DC37+DA37 -> 1 | DE37: =IF(DF37="","",DF37*$E37) | DG37: =DF37+DD37 -> 1 | DH37: =IF(DI37="","",DI37*$E37) | DJ37: =DI37+DG37 -> 1
A38: 3 | B38: 3.1.3 | C38: BLOCOS AUXILIARES ( CISTERNA / SUBESTAÇÃO / LIXEIRA / GERADOR ) | E38: =VLOOKUP(B38,'[49]PLANILHA ORCAMENTARIA'!A:G,7,0) -> 51161.233 | G38: =IF(H38="","",H38*E38) | I38: =H38 -> 0 | J38: =IF(K38="","",K38*H38) | L38: =K38 -> 0 | M38: =IF(N38="","",N38*K38) | O38: =N38 -> 0 | P38: =IF(Q38="","",Q38*N38) | R38: =Q38 -> 0 | S38: =IF(T38="","",T38*Q38) | U38: =T38 -> 0 | V38: =IF(W38="","",W38*T38) | X38: =W38 -> 0 | Y38: =IF(Z38="","",Z38*W38) | AA38: =Z38 -> 0 | AB38: =IF(AC38="","",AC38*Z38) | AD38: =AC38 -> 0 | AE38: =IF(AF38="","",AF38*AC38) | AG38: =AF38 -> 0 | AH38: =IF(AI38="","",AI38*AF38) | AJ38: =AI38 -> 0 | AK38: =IF(AL38="","",AL38*AI38) | AM38: =AL38 -> 0 | AN38: =IF(AO38="","",AO38*AL38) | AP38: =AO38 -> 0 | AQ38: =IF(AR38="","",AR38*AO38) | AS38: =AR38 -> 0 | AT38: =IF(AU38="","",AU38*AR38) | AV38: =AU38 -> 0 | AW38: =IF(AX38="","",AX38*AU38) | AY38: =AX38 -> 0 | AZ38: =IF(BA38="","",BA38*AX38) | BB38: =BA38 -> 0 | BC38: =IF(BD38="","",BD38*BA38) | BE38: =BD38 -> 0 | BF38: =IF(BG38="","",BG38*BD38) | BH38: =BG38 -> 0 | BI38: =IF(BJ38="","",BJ38*BG38) | BK38: =BJ38 -> 0 | BL38: =IF(BM38="","",BM38*BJ38) | BN38: =BM38 -> 0 | BO38: =IF(BP38="","",BP38*BM38) | BQ38: =BP38 -> 0 | BR38: =IF(BS38="","",BS38*BP38) | BT38: =BS38 -> 0 | BU38: =IF(BV38="","",BV38*BS38) | BW38: =BV38 -> 0 | BX38: =IF(BY38="","",BY38*BV38) | BZ38: =BY38 -> 0 | CA38: =IF(CB38="","",CB38*BY38) | CC38: =CB38 -> 0 | CD38: =IF(CE38="","",CE38*CB38) | CF38: =CE38 -> 0 | CG38: =IF(CH38="","",CH38*CE38) | CI38: =CH38 -> 0 | CJ38: =IF(CK38="","",CK38*CH38) | CL38: =CK38 -> 0 | CM38: =IF(CN38="","",CN38*CK38) | CO38: =CN38 -> 0 | CP38: =IF(CQ38="","",CQ38*CN38) | CR38: =CQ38 -> 0 | CS38: =IF(CT38="","",CT38*CQ38) | CU38: =CT38 -> 0 | CV38: =IF(CW38="","",CW38*CT38) | CX38: =CW38 -> 0 | CY38: =IF(CZ38="","",CZ38*CW38) | DA38: =CZ38 -> 0 | DB38: =IF(DC38="","",DC38*CZ38) | DD38: =DC38 -> 0 | DE38: =IF(DF38="","",DF38*DC38) | DG38: =DF38 -> 0 | DH38: =IF(DI38="","",DI38*DF38) | DJ38: =DI38 -> 0
A39: 3 | B39: 3.1.3 | C39: BLOCOS DE FUNDAÇÃO / VIGAS BALDRAMES | E39: =VLOOKUP(B39,'[49]PLANILHA ORCAMENTARIA'!A:G,7,0) -> 51161.233 | G39: =IF(H39="","",H39*$E39) | I39: =H39 -> 0 | J39: =IF(K39="","",K39*$E39) | L39: =K39+I39 -> 0 | M39: =IF(N39="","",N39*$E39) | O39: =N39+L39 -> 0 | P39: =IF(Q39="","",Q39*$E39) | R39: =Q39+O39 -> 0 | S39: =IF(T39="","",T39*$E39) | U39: =T39+R39 -> 0 | V39: =IF(W39="","",W39*$E39) | X39: =W39+U39 -> 0 | Y39: =IF(Z39="","",Z39*$E39) | AA39: =Z39+X39 -> 0 | AB39: =IF(AC39="","",AC39*$E39) | AD39: =AC39+AA39 -> 0 | AE39: =IF(AF39="","",AF39*$E39) | AG39: =AF39+AD39 -> 0 | AH39: =IF(AI39="","",AI39*$E39) | AJ39: =AI39+AG39 -> 0 | AK39: =IF(AL39="","",AL39*$E39) | AM39: =AL39+AJ39 -> 0 | AN39: =IF(AO39="","",AO39*$E39) | AP39: =AO39+AM39 -> 0 | AQ39: =IF(AR39="","",AR39*$E39) | AS39: =AR39+AP39 -> 0 | AT39: =IF(AU39="","",AU39*$E39) | AV39: =AU39+AS39 -> 0 | AW39: =IF(AX39="","",AX39*$E39) | AY39: =AX39+AV39 -> 0 | AZ39: =IF(BA39="","",BA39*$E39) | BB39: =BA39+AY39 -> 0 | BC39: =IF(BD39="","",BD39*$E39) | BE39: =BD39+BB39 -> 0 | BF39: =IF(BG39="","",BG39*$E39) | BH39: =BG39+BE39 -> 0 | BI39: =IF(BJ39="","",BJ39*$E39) | BK39: =BJ39+BH39 -> 0 | BL39: =IF(BM39="","",BM39*$E39) | BN39: =BM39+BK39 -> 0 | BO39: =IF(BP39="","",BP39*$E39) | BQ39: =BP39+BN39 -> 0 | BR39: =IF(BS39="","",BS39*$E39) | BT39: =BS39+BQ39 -> 0 | BU39: =IF(BV39="","",BV39*$E39) | BW39: =BV39+BT39 -> 0 | BX39: =IF(BY39="","",BY39*$E39) | BZ39: =BY39+BW39 -> 0 | CA39: =IF(CB39="","",CB39*$E39) | CC39: =CB39+BZ39 -> 0 | CD39: =IF(CE39="","",CE39*$E39) | CF39: =CE39+CC39 -> 0 | CG39: =IF(CH39="","",CH39*$E39) | CI39: =CH39+CF39 -> 0 | CJ39: =IF(CK39="","",CK39*$E39) | CL39: =CK39+CI39 -> 0 | CM39: =IF(CN39="","",CN39*$E39) | CO39: =CN39+CL39 -> 0 | CP39: =IF(CQ39="","",CQ39*$E39) | CR39: =CQ39+CO39 -> 0 | CS39: =IF(CT39="","",CT39*$E39) | CU39: =CT39+CR39 -> 0 | CV39: =IF(CW39="","",CW39*$E39) | CX39: =CW39+CU39 -> 0 | CY39: =IF(CZ39="","",CZ39*$E39) | DA39: =CZ39+CX39 -> 0 | DB39: =IF(DC39="","",DC39*$E39) | DD39: =DC39+DA39 -> 0 | DE39: =IF(DF39="","",DF39*$E39) | DG39: =DF39+DD39 -> 0 | DH39: =IF(DI39="","",DI39*$E39) | DJ39: =DI39+DG39 -> 0
A40: 3 | B40: 3.2 | C40: ESTRUTURAS | E40: =VLOOKUP(B40,'[49]PLANILHA ORCAMENTARIA'!A:G,7,0) -> 4290465.7
A41: 3 | B41: 3.2.1 | C41: BLOCO PRINCIPAL | E41: =VLOOKUP(B41,'[49]PLANILHA ORCAMENTARIA'!A:G,7,0) -> 4103844.3
A42: 3 | B42: 3.2.1.1 | C42: PILARES - TÉRREO | E42: =VLOOKUP(B42,'[49]PLANILHA ORCAMENTARIA'!A:G,7,0) -> 193892.67
A43: 3 | B43: 3.2.1.1.1 | C43: SETOR 1 - PILARES | E43: =VLOOKUP(B43,'[49]PLANILHA ORCAMENTARIA'!A:G,7,0) -> 52335.486 | G43: =IF(H43="","",H43*$E43) | I43: =H43 -> 0 | J43: =IF(K43="","",K43*$E43) | L43: =K43+I43 -> 0 | M43: =IF(N43="","",N43*$E43) | O43: =N43+L43 -> 0 | P43: =IF(Q43="","",Q43*$E43) | R43: =Q43+O43 -> 0 | S43: =IF(T43="","",T43*$E43) | U43: =T43+R43 -> 0 | V43: =IF(W43="","",W43*$E43) | X43: =W43+U43 -> 0 | Y43: =IF(Z43="","",Z43*$E43) | AA43: =Z43+X43 -> 0 | AB43: =IF(AC43="","",AC43*$E43) | AD43: =AC43+AA43 -> 0 | AE43: =IF(AF43="","",AF43*$E43) | AG43: =AF43+AD43 -> 0 | AH43: =IF(AI43="","",AI43*$E43) | AJ43: =AI43+AG43 -> 0 | AK43: =IF(AL43="","",AL43*$E43) | AM43: =AL43+AJ43 -> 0 | AN43: =IF(AO43="","",AO43*$E43) | AP43: =AO43+AM43 -> 0 | AQ43: =IF(AR43="","",AR43*$E43) | AS43: =AR43+AP43 -> 0 | AT43: =IF(AU43="","",AU43*$E43) | AV43: =AU43+AS43 -> 0 | AW43: =IF(AX43="","",AX43*$E43) | AY43: =AX43+AV43 -> 0 | AZ43: =IF(BA43="","",BA43*$E43) | BB43: =BA43+AY43 -> 0 | BC43: =IF(BD43="","",BD43*$E43) | BE43: =BD43+BB43 -> 0 | BF43: =IF(BG43="","",BG43*$E43) | BH43: =BG43+BE43 -> 0 | BI43: =IF(BJ43="","",BJ43*$E43) | BK43: =BJ43+BH43 -> 0 | BL43: =IF(BM43="","",BM43*$E43) | BN43: =BM43+BK43 -> 0 | BO43: =IF(BP43="","",BP43*$E43) | BQ43: =BP43+BN43 -> 0 | BR43: =IF(BS43="","",BS43*$E43) | BT43: =BS43+BQ43 -> 0 | BU43: =IF(BV43="","",BV43*$E43) | BW43: =BV43+BT43 -> 0 | BX43: =IF(BY43="","",BY43*$E43) | BZ43: =BY43+BW43 -> 0 | CA43: =IF(CB43="","",CB43*$E43) | CC43: =CB43+BZ43 -> 0 | CD43: =IF(CE43="","",CE43*$E43) | CF43: =CE43+CC43 -> 0 | CG43: =IF(CH43="","",CH43*$E43) | CI43: =CH43+CF43 -> 0 | CJ43: =IF(CK43="","",CK43*$E43) | CL43: =CK43+CI43 -> 0 | CM43: =IF(CN43="","",CN43*$E43) | CO43: =CN43+CL43 -> 0 | CP43: =IF(CQ43="","",CQ43*$E43) | CR43: =CQ43+CO43 -> 0 | CS43: =IF(CT43="","",CT43*$E43) | CU43: =CT43+CR43 -> 0 | CV43: =IF(CW43="","",CW43*$E43) | CX43: =CW43+CU43 -> 0 | CY43: =IF(CZ43="","",CZ43*$E43) | DA43: =CZ43+CX43 -> 0 | DB43: =IF(DC43="","",DC43*$E43) | DD43: =DC43+DA43 -> 0 | DE43: =IF(DF43="","",DF43*$E43) | DG43: =DF43+DD43 -> 0 | DH43: =IF(DI43="","",DI43*$E43) | DJ43: =DI43+DG43 -> 0
A44: 3 | B44: 3.2.1.1.2 | C44: SETOR 2 - PILARES | E44: =VLOOKUP(B44,'[49]PLANILHA ORCAMENTARIA'!A:G,7,0) -> 41355.52 | G44: =IF(H44="","",H44*$E44) | I44: =H44 -> 0 | J44: =IF(K44="","",K44*$E44) | L44: =K44+I44 -> 0 | M44: =IF(N44="","",N44*$E44) | O44: =N44+L44 -> 0 | P44: =IF(Q44="","",Q44*$E44) | R44: =Q44+O44 -> 0 | S44: =IF(T44="","",T44*$E44) | U44: =T44+R44 -> 0 | V44: =IF(W44="","",W44*$E44) | X44: =W44+U44 -> 0 | Y44: =IF(Z44="","",Z44*$E44) | AA44: =Z44+X44 -> 0 | AB44: =IF(AC44="","",AC44*$E44) | AD44: =AC44+AA44 -> 0 | AE44: =IF(AF44="","",AF44*$E44) | AG44: =AF44+AD44 -> 0 | AH44: =IF(AI44="","",AI44*$E44) | AJ44: =AI44+AG44 -> 0 | AK44: =IF(AL44="","",AL44*$E44) | AM44: =AL44+AJ44 -> 0 | AN44: =IF(AO44="","",AO44*$E44) | AP44: =AO44+AM44 -> 0 | AQ44: =IF(AR44="","",AR44*$E44) | AS44: =AR44+AP44 -> 0 | AT44: =IF(AU44="","",AU44*$E44) | AV44: =AU44+AS44 -> 0 | AW44: =IF(AX44="","",AX44*$E44) | AY44: =AX44+AV44 -> 0 | AZ44: =IF(BA44="","",BA44*$E44) | BB44: =BA44+AY44 -> 0 | BC44: =IF(BD44="","",BD44*$E44) | BE44: =BD44+BB44 -> 0 | BF44: =IF(BG44="","",BG44*$E44) | BH44: =BG44+BE44 -> 0 | BI44: =IF(BJ44="","",BJ44*$E44) | BK44: =BJ44+BH44 -> 0 | BL44: =IF(BM44="","",BM44*$E44) | BN44: =BM44+BK44 -> 0 | BO44: =IF(BP44="","",BP44*$E44) | BQ44: =BP44+BN44 -> 0 | BR44: =IF(BS44="","",BS44*$E44) | BT44: =BS44+BQ44 -> 0 | BU44: =IF(BV44="","",BV44*$E44) | BW44: =BV44+BT44 -> 0 | BX44: =IF(BY44="","",BY44*$E44) | BZ44: =BY44+BW44 -> 0 | CA44: =IF(CB44="","",CB44*$E44) | CC44: =CB44+BZ44 -> 0 | CD44: =IF(CE44="","",CE44*$E44) | CF44: =CE44+CC44 -> 0 | CG44: =IF(CH44="","",CH44*$E44) | CI44: =CH44+CF44 -> 0 | CJ44: =IF(CK44="","",CK44*$E44) | CL44: =CK44+CI44 -> 0 | CM44: =IF(CN44="","",CN44*$E44) | CO44: =CN44+CL44 -> 0 | CP44: =IF(CQ44="","",CQ44*$E44) | CR44: =CQ44+CO44 -> 0 | CS44: =IF(CT44="","",CT44*$E44) | CU44: =CT44+CR44 -> 0 | CV44: =IF(CW44="","",CW44*$E44) | CX44: =CW44+CU44 -> 0 | CY44: =IF(CZ44="","",CZ44*$E44) | DA44: =CZ44+CX44 -> 0 | DB44: =IF(DC44="","",DC44*$E44) | DD44: =DC44+DA44 -> 0 | DE44: =IF(DF44="","",DF44*$E44) | DG44: =DF44+DD44 -> 0 | DH44: =IF(DI44="","",DI44*$E44) | DJ44: =DI44+DG44 -> 0
A45: 3 | B45: 3.2.1.1.3 | C45: SETOR 3 - PILARES | E45: =VLOOKUP(B45,'[49]PLANILHA ORCAMENTARIA'!A:G,7,0) -> 100201.66 | G45: =IF(H45="","",H45*$E45) | I45: =H45 -> 0 | J45: =IF(K45="","",K45*$E45) | L45: =K45+I45 -> 0 | M45: =IF(N45="","",N45*$E45) | O45: =N45+L45 -> 0 | P45: =IF(Q45="","",Q45*$E45) | R45: =Q45+O45 -> 0 | S45: =IF(T45="","",T45*$E45) | U45: =T45+R45 -> 0 | V45: =IF(W45="","",W45*$E45) | X45: =W45+U45 -> 0 | Y45: =IF(Z45="","",Z45*$E45) | AA45: =Z45+X45 -> 0 | AB45: =IF(AC45="","",AC45*$E45) | AD45: =AC45+AA45 -> 0 | AE45: =IF(AF45="","",AF45*$E45) | AG45: =AF45+AD45 -> 0 | AH45: =IF(AI45="","",AI45*$E45) | AJ45: =AI45+AG45 -> 0 | AK45: =IF(AL45="","",AL45*$E45) | AM45: =AL45+AJ45 -> 0 | AN45: =IF(AO45="","",AO45*$E45) | AP45: =AO45+AM45 -> 0 | AQ45: =IF(AR45="","",AR45*$E45) | AS45: =AR45+AP45 -> 0 | AT45: =IF(AU45="","",AU45*$E45) | AV45: =AU45+AS45 -> 0 | AW45: =IF(AX45="","",AX45*$E45) | AY45: =AX45+AV45 -> 0 | AZ45: =IF(BA45="","",BA45*$E45) | BB45: =BA45+AY45 -> 0 | BC45: =IF(BD45="","",BD45*$E45) | BE45: =BD45+BB45 -> 0 | BF45: =IF(BG45="","",BG45*$E45) | BH45: =BG45+BE45 -> 0 | BI45: =IF(BJ45="","",BJ45*$E45) | BK45: =BJ45+BH45 -> 0 | BL45: =IF(BM45="","",BM45*$E45) | BN45: =BM45+BK45 -> 0 | BO45: =IF(BP45="","",BP45*$E45) | BQ45: =BP45+BN45 -> 0 | BR45: =IF(BS45="","",BS45*$E45) | BT45: =BS45+BQ45 -> 0 | BU45: =IF(BV45="","",BV45*$E45) | BW45: =BV45+BT45 -> 0 | BX45: =IF(BY45="","",BY45*$E45) | BZ45: =BY45+BW45 -> 0 | CA45: =IF(CB45="","",CB45*$E45) | CC45: =CB45+BZ45 -> 0 | CD45: =IF(CE45="","",CE45*$E45) | CF45: =CE45+CC45 -> 0 | CG45: =IF(CH45="","",CH45*$E45) | CI45: =CH45+CF45 -> 0 | CJ45: =IF(CK45="","",CK45*$E45) | CL45: =CK45+CI45 -> 0 | CM45: =IF(CN45="","",CN45*$E45) | CO45: =CN45+CL45 -> 0 | CP45: =IF(CQ45="","",CQ45*$E45) | CR45: =CQ45+CO45 -> 0 | CS45: =IF(CT45="","",CT45*$E45) | CU45: =CT45+CR45 -> 0 | CV45: =IF(CW45="","",CW45*$E45) | CX45: =CW45+CU45 -> 0 | CY45: =IF(CZ45="","",CZ45*$E45) | DA45: =CZ45+CX45 -> 0 | DB45: =IF(DC45="","",DC45*$E45) | DD45: =DC45+DA45 -> 0 | DE45: =IF(DF45="","",DF45*$E45) | DG45: =DF45+DD45 -> 0 | DH45: =IF(DI45="","",DI45*$E45) | DJ45: =DI45+DG45 -> 0
A46: 3 | B46: 3.2.1.2 | C46: PILARES - 1 ANDAR | E46: =VLOOKUP(B46,'[49]PLANILHA ORCAMENTARIA'!A:G,7,0) -> 171557.03 | G46: =IF(H46="","",H46*E46) | I46: =H46 -> 0 | J46: =IF(K46="","",K46*H46) | L46: =K46 -> 0 | M46: =IF(N46="","",N46*K46) | O46: =N46 -> 0 | P46: =IF(Q46="","",Q46*N46) | R46: =Q46 -> 0 | S46: =IF(T46="","",T46*Q46) | U46: =T46 -> 0 | V46: =IF(W46="","",W46*T46) | X46: =W46 -> 0 | Y46: =IF(Z46="","",Z46*W46) | AA46: =Z46 -> 0 | AB46: =IF(AC46="","",AC46*Z46) | AD46: =AC46 -> 0 | AE46: =IF(AF46="","",AF46*AC46) | AG46: =AF46 -> 0 | AH46: =IF(AI46="","",AI46*AF46) | AJ46: =AI46 -> 0 | AK46: =IF(AL46="","",AL46*AI46) | AM46: =AL46 -> 0 | AN46: =IF(AO46="","",AO46*AL46) | AP46: =AO46 -> 0 | AQ46: =IF(AR46="","",AR46*AO46) | AS46: =AR46 -> 0 | AT46: =IF(AU46="","",AU46*AR46) | AV46: =AU46 -> 0 | AW46: =IF(AX46="","",AX46*AU46) | AY46: =AX46 -> 0 | AZ46: =IF(BA46="","",BA46*AX46) | BB46: =BA46 -> 0 | BC46: =IF(BD46="","",BD46*BA46) | BE46: =BD46 -> 0 | BF46: =IF(BG46="","",BG46*BD46) | BH46: =BG46 -> 0 | BI46: =IF(BJ46="","",BJ46*BG46) | BK46: =BJ46 -> 0 | BL46: =IF(BM46="","",BM46*BJ46) | BN46: =BM46 -> 0 | BO46: =IF(BP46="","",BP46*BM46) | BQ46: =BP46 -> 0 | BR46: =IF(BS46="","",BS46*BP46) | BT46: =BS46 -> 0 | BU46: =IF(BV46="","",BV46*BS46) | BW46: =BV46 -> 0 | BX46: =IF(BY46="","",BY46*BV46) | BZ46: =BY46 -> 0 | CA46: =IF(CB46="","",CB46*BY46) | CC46: =CB46 -> 0 | CD46: =IF(CE46="","",CE46*CB46) | CF46: =CE46 -> 0 | CG46: =IF(CH46="","",CH46*CE46) | CI46: =CH46 -> 0 | CJ46: =IF(CK46="","",CK46*CH46) | CL46: =CK46 -> 0 | CM46: =IF(CN46="","",CN46*CK46) | CO46: =CN46 -> 0 | CP46: =IF(CQ46="","",CQ46*CN46) | CR46: =CQ46 -> 0 | CS46: =IF(CT46="","",CT46*CQ46) | CU46: =CT46 -> 0 | CV46: =IF(CW46="","",CW46*CT46) | CX46: =CW46 -> 0 | CY46: =IF(CZ46="","",CZ46*CW46) | DA46: =CZ46 -> 0 | DB46: =IF(DC46="","",DC46*CZ46) | DD46: =DC46 -> 0 | DE46: =IF(DF46="","",DF46*DC46) | DG46: =DF46 -> 0 | DH46: =IF(DI46="","",DI46*DF46) | DJ46: =DI46 -> 0
A47: 3 | B47: 3.2.1.2.1 | C47: SETOR 1 - PILARES | E47: =VLOOKUP(B47,'[49]PLANILHA ORCAMENTARIA'!A:G,7,0) -> 44883.988 | G47: =IF(H47="","",H47*$E47) | I47: =H47 -> 0 | J47: =IF(K47="","",K47*$E47) | L47: =K47+I47 -> 0 | M47: =IF(N47="","",N47*$E47) | O47: =N47+L47 -> 0 | P47: =IF(Q47="","",Q47*$E47) | R47: =Q47+O47 -> 0 | S47: =IF(T47="","",T47*$E47) | U47: =T47+R47 -> 0 | V47: =IF(W47="","",W47*$E47) | X47: =W47+U47 -> 0 | Y47: =IF(Z47="","",Z47*$E47) | AA47: =Z47+X47 -> 0 | AB47: =IF(AC47="","",AC47*$E47) | AD47: =AC47+AA47 -> 0 | AE47: =IF(AF47="","",AF47*$E47) | AG47: =AF47+AD47 -> 0 | AH47: =IF(AI47="","",AI47*$E47) | AJ47: =AI47+AG47 -> 0 | AK47: =IF(AL47="","",AL47*$E47) | AM47: =AL47+AJ47 -> 0 | AN47: =IF(AO47="","",AO47*$E47) | AP47: =AO47+AM47 -> 0 | AQ47: =IF(AR47="","",AR47*$E47) | AS47: =AR47+AP47 -> 0 | AT47: =IF(AU47="","",AU47*$E47) | AV47: =AU47+AS47 -> 0 | AW47: =IF(AX47="","",AX47*$E47) | AY47: =AX47+AV47 -> 0 | AZ47: =IF(BA47="","",BA47*$E47) | BB47: =BA47+AY47 -> 0 | BC47: =IF(BD47="","",BD47*$E47) | BE47: =BD47+BB47 -> 0 | BF47: =IF(BG47="","",BG47*$E47) | BH47: =BG47+BE47 -> 0 | BI47: =IF(BJ47="","",BJ47*$E47) | BK47: =BJ47+BH47 -> 0 | BL47: =IF(BM47="","",BM47*$E47) | BN47: =BM47+BK47 -> 0 | BO47: =IF(BP47="","",BP47*$E47) | BQ47: =BP47+BN47 -> 0 | BR47: =IF(BS47="","",BS47*$E47) | BT47: =BS47+BQ47 -> 0 | BU47: =IF(BV47="","",BV47*$E47) | BW47: =BV47+BT47 -> 0 | BX47: =IF(BY47="","",BY47*$E47) | BZ47: =BY47+BW47 -> 0 | CA47: =IF(CB47="","",CB47*$E47) | CC47: =CB47+BZ47 -> 0 | CD47: =IF(CE47="","",CE47*$E47) | CF47: =CE47+CC47 -> 0 | CG47: =IF(CH47="","",CH47*$E47) | CI47: =CH47+CF47 -> 0 | CJ47: =IF(CK47="","",CK47*$E47) | CL47: =CK47+CI47 -> 0 | CM47: =IF(CN47="","",CN47*$E47) | CO47: =CN47+CL47 -> 0 | CP47: =IF(CQ47="","",CQ47*$E47) | CR47: =CQ47+CO47 -> 0 | CS47: =IF(CT47="","",CT47*$E47) | CU47: =CT47+CR47 -> 0 | CV47: =IF(CW47="","",CW47*$E47) | CX47: =CW47+CU47 -> 0 | CY47: =IF(CZ47="","",CZ47*$E47) | DA47: =CZ47+CX47 -> 0 | DB47: =IF(DC47="","",DC47*$E47) | DD47: =DC47+DA47 -> 0 | DE47: =IF(DF47="","",DF47*$E47) | DG47: =DF47+DD47 -> 0 | DH47: =IF(DI47="","",DI47*$E47) | DJ47: =DI47+DG47 -> 0
A48: 3 | B48: 3.2.1.2.2 | C48: SETOR 2 - PILARES | E48: =VLOOKUP(B48,'[49]PLANILHA ORCAMENTARIA'!A:G,7,0) -> 40133.212 | G48: =IF(H48="","",H48*$E48) | I48: =H48 -> 0 | J48: =IF(K48="","",K48*$E48) | L48: =K48+I48 -> 0 | M48: =IF(N48="","",N48*$E48) | O48: =N48+L48 -> 0 | P48: =IF(Q48="","",Q48*$E48) | R48: =Q48+O48 -> 0 | S48: =IF(T48="","",T48*$E48) | U48: =T48+R48 -> 0 | V48: =IF(W48="","",W48*$E48) | X48: =W48+U48 -> 0 | Y48: =IF(Z48="","",Z48*$E48) | AA48: =Z48+X48 -> 0 | AB48: =IF(AC48="","",AC48*$E48) | AD48: =AC48+AA48 -> 0 | AE48: =IF(AF48="","",AF48*$E48) | AG48: =AF48+AD48 -> 0 | AH48: =IF(AI48="","",AI48*$E48) | AJ48: =AI48+AG48 -> 0 | AK48: =IF(AL48="","",AL48*$E48) | AM48: =AL48+AJ48 -> 0 | AN48: =IF(AO48="","",AO48*$E48) | AP48: =AO48+AM48 -> 0 | AQ48: =IF(AR48="","",AR48*$E48) | AS48: =AR48+AP48 -> 0 | AT48: =IF(AU48="","",AU48*$E48) | AV48: =AU48+AS48 -> 0 | AW48: =IF(AX48="","",AX48*$E48) | AY48: =AX48+AV48 -> 0 | AZ48: =IF(BA48="","",BA48*$E48) | BB48: =BA48+AY48 -> 0 | BC48: =IF(BD48="","",BD48*$E48) | BE48: =BD48+BB48 -> 0 | BF48: =IF(BG48="","",BG48*$E48) | BH48: =BG48+BE48 -> 0 | BI48: =IF(BJ48="","",BJ48*$E48) | BK48: =BJ48+BH48 -> 0 | BL48: =IF(BM48="","",BM48*$E48) | BN48: =BM48+BK48 -> 0 | BO48: =IF(BP48="","",BP48*$E48) | BQ48: =BP48+BN48 -> 0 | BR48: =IF(BS48="","",BS48*$E48) | BT48: =BS48+BQ48 -> 0 | BU48: =IF(BV48="","",BV48*$E48) | BW48: =BV48+BT48 -> 0 | BX48: =IF(BY48="","",BY48*$E48) | BZ48: =BY48+BW48 -> 0 | CA48: =IF(CB48="","",CB48*$E48) | CC48: =CB48+BZ48 -> 0 | CD48: =IF(CE48="","",CE48*$E48) | CF48: =CE48+CC48 -> 0 | CG48: =IF(CH48="","",CH48*$E48) | CI48: =CH48+CF48 -> 0 | CJ48: =IF(CK48="","",CK48*$E48) | CL48: =CK48+CI48 -> 0 | CM48: =IF(CN48="","",CN48*$E48) | CO48: =CN48+CL48 -> 0 | CP48: =IF(CQ48="","",CQ48*$E48) | CR48: =CQ48+CO48 -> 0 | CS48: =IF(CT48="","",CT48*$E48) | CU48: =CT48+CR48 -> 0 | CV48: =IF(CW48="","",CW48*$E48) | CX48: =CW48+CU48 -> 0 | CY48: =IF(CZ48="","",CZ48*$E48) | DA48: =CZ48+CX48 -> 0 | DB48: =IF(DC48="","",DC48*$E48) | DD48: =DC48+DA48 -> 0 | DE48: =IF(DF48="","",DF48*$E48) | DG48: =DF48+DD48 -> 0 | DH48: =IF(DI48="","",DI48*$E48) | DJ48: =DI48+DG48 -> 0
A49: 3 | B49: 3.2.1.2.3 | C49: SETOR 3 - PILARES | E49: =VLOOKUP(B49,'[49]PLANILHA ORCAMENTARIA'!A:G,7,0) -> 86539.828 | G49: =IF(H49="","",H49*$E49) | I49: =H49 -> 0 | J49: =IF(K49="","",K49*$E49) | L49: =K49+I49 -> 0 | M49: =IF(N49="","",N49*$E49) | O49: =N49+L49 -> 0 | P49: =IF(Q49="","",Q49*$E49) | R49: =Q49+O49 -> 0 | S49: =IF(T49="","",T49*$E49) | U49: =T49+R49 -> 0 | V49: =IF(W49="","",W49*$E49) | X49: =W49+U49 -> 0 | Y49: =IF(Z49="","",Z49*$E49) | AA49: =Z49+X49 -> 0 | AB49: =IF(AC49="","",AC49*$E49) | AD49: =AC49+AA49 -> 0 | AE49: =IF(AF49="","",AF49*$E49) | AG49: =AF49+AD49 -> 0 | AH49: =IF(AI49="","",AI49*$E49) | AJ49: =AI49+AG49 -> 0 | AK49: =IF(AL49="","",AL49*$E49) | AM49: =AL49+AJ49 -> 0 | AN49: =IF(AO49="","",AO49*$E49) | AP49: =AO49+AM49 -> 0 | AQ49: =IF(AR49="","",AR49*$E49) | AS49: =AR49+AP49 -> 0 | AT49: =IF(AU49="","",AU49*$E49) | AV49: =AU49+AS49 -> 0 | AW49: =IF(AX49="","",AX49*$E49) | AY49: =AX49+AV49 -> 0 | AZ49: =IF(BA49="","",BA49*$E49) | BB49: =BA49+AY49 -> 0 | BC49: =IF(BD49="","",BD49*$E49) | BE49: =BD49+BB49 -> 0 | BF49: =IF(BG49="","",BG49*$E49) | BH49: =BG49+BE49 -> 0 | BI49: =IF(BJ49="","",BJ49*$E49) | BK49: =BJ49+BH49 -> 0 | BL49: =IF(BM49="","",BM49*$E49) | BN49: =BM49+BK49 -> 0 | BO49: =IF(BP49="","",BP49*$E49) | BQ49: =BP49+BN49 -> 0 | BR49: =IF(BS49="","",BS49*$E49) | BT49: =BS49+BQ49 -> 0 | BU49: =IF(BV49="","",BV49*$E49) | BW49: =BV49+BT49 -> 0 | BX49: =IF(BY49="","",BY49*$E49) | BZ49: =BY49+BW49 -> 0 | CA49: =IF(CB49="","",CB49*$E49) | CC49: =CB49+BZ49 -> 0 | CD49: =IF(CE49="","",CE49*$E49) | CF49: =CE49+CC49 -> 0 | CG49: =IF(CH49="","",CH49*$E49) | CI49: =CH49+CF49 -> 0 | CJ49: =IF(CK49="","",CK49*$E49) | CL49: =CK49+CI49 -> 0 | CM49: =IF(CN49="","",CN49*$E49) | CO49: =CN49+CL49 -> 0 | CP49: =IF(CQ49="","",CQ49*$E49) | CR49: =CQ49+CO49 -> 0 | CS49: =IF(CT49="","",CT49*$E49) | CU49: =CT49+CR49 -> 0 | CV49: =IF(CW49="","",CW49*$E49) | CX49: =CW49+CU49 -> 0 | CY49: =IF(CZ49="","",CZ49*$E49) | DA49: =CZ49+CX49 -> 0 | DB49: =IF(DC49="","",DC49*$E49) | DD49: =DC49+DA49 -> 0 | DE49: =IF(DF49="","",DF49*$E49) | DG49: =DF49+DD49 -> 0 | DH49: =IF(DI49="","",DI49*$E49) | DJ49: =DI49+DG49 -> 0
A50: 3 | B50: 3.2.1.3 | C50: PILARES - 2 ANDAR | E50: =VLOOKUP(B50,'[49]PLANILHA ORCAMENTARIA'!A:G,7,0) -> 186046.49 | G50: =IF(H50="","",H50*E50) | I50: =H50 -> 0 | J50: =IF(K50="","",K50*H50) | L50: =K50 -> 0 | M50: =IF(N50="","",N50*K50) | O50: =N50 -> 0 | P50: =IF(Q50="","",Q50*N50) | R50: =Q50 -> 0 | S50: =IF(T50="","",T50*Q50) | U50: =T50 -> 0 | V50: =IF(W50="","",W50*T50) | X50: =W50 -> 0 | Y50: =IF(Z50="","",Z50*W50) | AA50: =Z50 -> 0 | AB50: =IF(AC50="","",AC50*Z50) | AD50: =AC50 -> 0 | AE50: =IF(AF50="","",AF50*AC50) | AG50: =AF50 -> 0 | AH50: =IF(AI50="","",AI50*AF50) | AJ50: =AI50 -> 0 | AK50: =IF(AL50="","",AL50*AI50) | AM50: =AL50 -> 0 | AN50: =IF(AO50="","",AO50*AL50) | AP50: =AO50 -> 0 | AQ50: =IF(AR50="","",AR50*AO50) | AS50: =AR50 -> 0 | AT50: =IF(AU50="","",AU50*AR50) | AV50: =AU50 -> 0 | AW50: =IF(AX50="","",AX50*AU50) | AY50: =AX50 -> 0 | AZ50: =IF(BA50="","",BA50*AX50) | BB50: =BA50 -> 0 | BC50: =IF(BD50="","",BD50*BA50) | BE50: =BD50 -> 0 | BF50: =IF(BG50="","",BG50*BD50) | BH50: =BG50 -> 0 | BI50: =IF(BJ50="","",BJ50*BG50) | BK50: =BJ50 -> 0 | BL50: =IF(BM50="","",BM50*BJ50) | BN50: =BM50 -> 0 | BO50: =IF(BP50="","",BP50*BM50) | BQ50: =BP50 -> 0 | BR50: =IF(BS50="","",BS50*BP50) | BT50: =BS50 -> 0 | BU50: =IF(BV50="","",BV50*BS50) | BW50: =BV50 -> 0 | BX50: =IF(BY50="","",BY50*BV50) | BZ50: =BY50 -> 0 | CA50: =IF(CB50="","",CB50*BY50) | CC50: =CB50 -> 0 | CD50: =IF(CE50="","",CE50*CB50) | CF50: =CE50 -> 0 | CG50: =IF(CH50="","",CH50*CE50) | CI50: =CH50 -> 0 | CJ50: =IF(CK50="","",CK50*CH50) | CL50: =CK50 -> 0 | CM50: =IF(CN50="","",CN50*CK50) | CO50: =CN50 -> 0 | CP50: =IF(CQ50="","",CQ50*CN50) | CR50: =CQ50 -> 0 | CS50: =IF(CT50="","",CT50*CQ50) | CU50: =CT50 -> 0 | CV50: =IF(CW50="","",CW50*CT50) | CX50: =CW50 -> 0 | CY50: =IF(CZ50="","",CZ50*CW50) | DA50: =CZ50 -> 0 | DB50: =IF(DC50="","",DC50*CZ50) | DD50: =DC50 -> 0 | DE50: =IF(DF50="","",DF50*DC50) | DG50: =DF50 -> 0 | DH50: =IF(DI50="","",DI50*DF50) | DJ50: =DI50 -> 0
A51: 3 | B51: 3.2.1.3.1 | C51: SETOR 1 - PILARES | E51: =VLOOKUP(B51,'[49]PLANILHA ORCAMENTARIA'!A:G,7,0) -> 46793.295 | G51: =IF(H51="","",H51*$E51) | I51: =H51 -> 0 | J51: =IF(K51="","",K51*$E51) | L51: =K51+I51 -> 0 | M51: =IF(N51="","",N51*$E51) | O51: =N51+L51 -> 0 | P51: =IF(Q51="","",Q51*$E51) | R51: =Q51+O51 -> 0 | S51: =IF(T51="","",T51*$E51) | U51: =T51+R51 -> 0 | V51: =IF(W51="","",W51*$E51) | X51: =W51+U51 -> 0 | Y51: =IF(Z51="","",Z51*$E51) | AA51: =Z51+X51 -> 0 | AB51: =IF(AC51="","",AC51*$E51) | AD51: =AC51+AA51 -> 0 | AE51: =IF(AF51="","",AF51*$E51) | AG51: =AF51+AD51 -> 0 | AH51: =IF(AI51="","",AI51*$E51) | AJ51: =AI51+AG51 -> 0 | AK51: =IF(AL51="","",AL51*$E51) | AM51: =AL51+AJ51 -> 0 | AN51: =IF(AO51="","",AO51*$E51) | AP51: =AO51+AM51 -> 0 | AQ51: =IF(AR51="","",AR51*$E51) | AS51: =AR51+AP51 -> 0 | AT51: =IF(AU51="","",AU51*$E51) | AV51: =AU51+AS51 -> 0 | AW51: =IF(AX51="","",AX51*$E51) | AY51: =AX51+AV51 -> 0 | AZ51: =IF(BA51="","",BA51*$E51) | BB51: =BA51+AY51 -> 0 | BC51: =IF(BD51="","",BD51*$E51) | BE51: =BD51+BB51 -> 0 | BF51: =IF(BG51="","",BG51*$E51) | BH51: =BG51+BE51 -> 0 | BI51: =IF(BJ51="","",BJ51*$E51) | BK51: =BJ51+BH51 -> 0 | BL51: =IF(BM51="","",BM51*$E51) | BN51: =BM51+BK51 -> 0 | BO51: =IF(BP51="","",BP51*$E51) | BQ51: =BP51+BN51 -> 0 | BR51: =IF(BS51="","",BS51*$E51) | BT51: =BS51+BQ51 -> 0 | BU51: =IF(BV51="","",BV51*$E51) | BW51: =BV51+BT51 -> 0 | BX51: =IF(BY51="","",BY51*$E51) | BZ51: =BY51+BW51 -> 0 | CA51: =IF(CB51="","",CB51*$E51) | CC51: =CB51+BZ51 -> 0 | CD51: =IF(CE51="","",CE51*$E51) | CF51: =CE51+CC51 -> 0 | CG51: =IF(CH51="","",CH51*$E51) | CI51: =CH51+CF51 -> 0 | CJ51: =IF(CK51="","",CK51*$E51) | CL51: =CK51+CI51 -> 0 | CM51: =IF(CN51="","",CN51*$E51) | CO51: =CN51+CL51 -> 0 | CP51: =IF(CQ51="","",CQ51*$E51) | CR51: =CQ51+CO51 -> 0 | CS51: =IF(CT51="","",CT51*$E51) | CU51: =CT51+CR51 -> 0 | CV51: =IF(CW51="","",CW51*$E51) | CX51: =CW51+CU51 -> 0 | CY51: =IF(CZ51="","",CZ51*$E51) | DA51: =CZ51+CX51 -> 0 | DB51: =IF(DC51="","",DC51*$E51) | DD51: =DC51+DA51 -> 0 | DE51: =IF(DF51="","",DF51*$E51) | DG51: =DF51+DD51 -> 0 | DH51: =IF(DI51="","",DI51*$E51) | DJ51: =DI51+DG51 -> 0
A52: 3 | B52: 3.2.1.3.2 | C52: SETOR 2 - PILARES | E52: =VLOOKUP(B52,'[49]PLANILHA ORCAMENTARIA'!A:G,7,0) -> 46694.375 | G52: =IF(H52="","",H52*$E52) | I52: =H52 -> 0 | J52: =IF(K52="","",K52*$E52) | L52: =K52+I52 -> 0 | M52: =IF(N52="","",N52*$E52) | O52: =N52+L52 -> 0 | P52: =IF(Q52="","",Q52*$E52) | R52: =Q52+O52 -> 0 | S52: =IF(T52="","",T52*$E52) | U52: =T52+R52 -> 0 | V52: =IF(W52="","",W52*$E52) | X52: =W52+U52 -> 0 | Y52: =IF(Z52="","",Z52*$E52) | AA52: =Z52+X52 -> 0 | AB52: =IF(AC52="","",AC52*$E52) | AD52: =AC52+AA52 -> 0 | AE52: =IF(AF52="","",AF52*$E52) | AG52: =AF52+AD52 -> 0 | AH52: =IF(AI52="","",AI52*$E52) | AJ52: =AI52+AG52 -> 0 | AK52: =IF(AL52="","",AL52*$E52) | AM52: =AL52+AJ52 -> 0 | AN52: =IF(AO52="","",AO52*$E52) | AP52: =AO52+AM52 -> 0 | AQ52: =IF(AR52="","",AR52*$E52) | AS52: =AR52+AP52 -> 0 | AT52: =IF(AU52="","",AU52*$E52) | AV52: =AU52+AS52 -> 0 | AW52: =IF(AX52="","",AX52*$E52) | AY52: =AX52+AV52 -> 0 | AZ52: =IF(BA52="","",BA52*$E52) | BB52: =BA52+AY52 -> 0 | BC52: =IF(BD52="","",BD52*$E52) | BE52: =BD52+BB52 -> 0 | BF52: =IF(BG52="","",BG52*$E52) | BH52: =BG52+BE52 -> 0 | BI52: =IF(BJ52="","",BJ52*$E52) | BK52: =BJ52+BH52 -> 0 | BL52: =IF(BM52="","",BM52*$E52) | BN52: =BM52+BK52 -> 0 | BO52: =IF(BP52="","",BP52*$E52) | BQ52: =BP52+BN52 -> 0 | BR52: =IF(BS52="","",BS52*$E52) | BT52: =BS52+BQ52 -> 0 | BU52: =IF(BV52="","",BV52*$E52) | BW52: =BV52+BT52 -> 0 | BX52: =IF(BY52="","",BY52*$E52) | BZ52: =BY52+BW52 -> 0 | CA52: =IF(CB52="","",CB52*$E52) | CC52: =CB52+BZ52 -> 0 | CD52: =IF(CE52="","",CE52*$E52) | CF52: =CE52+CC52 -> 0 | CG52: =IF(CH52="","",CH52*$E52) | CI52: =CH52+CF52 -> 0 | CJ52: =IF(CK52="","",CK52*$E52) | CL52: =CK52+CI52 -> 0 | CM52: =IF(CN52="","",CN52*$E52) | CO52: =CN52+CL52 -> 0 | CP52: =IF(CQ52="","",CQ52*$E52) | CR52: =CQ52+CO52 -> 0 | CS52: =IF(CT52="","",CT52*$E52) | CU52: =CT52+CR52 -> 0 | CV52: =IF(CW52="","",CW52*$E52) | CX52: =CW52+CU52 -> 0 | CY52: =IF(CZ52="","",CZ52*$E52) | DA52: =CZ52+CX52 -> 0 | DB52: =IF(DC52="","",DC52*$E52) | DD52: =DC52+DA52 -> 0 | DE52: =IF(DF52="","",DF52*$E52) | DG52: =DF52+DD52 -> 0 | DH52: =IF(DI52="","",DI52*$E52) | DJ52: =DI52+DG52 -> 0
A53: 3 | B53: 3.2.1.3.3 | C53: SETOR 3 - PILARES | E53: =VLOOKUP(B53,'[49]PLANILHA ORCAMENTARIA'!A:G,7,0) -> 92558.822 | G53: =IF(H53="","",H53*$E53) | I53: =H53 -> 0 | J53: =IF(K53="","",K53*$E53) | L53: =K53+I53 -> 0 | M53: =IF(N53="","",N53*$E53) | O53: =N53+L53 -> 0 | P53: =IF(Q53="","",Q53*$E53) | R53: =Q53+O53 -> 0 | S53: =IF(T53="","",T53*$E53) | U53: =T53+R53 -> 0 | V53: =IF(W53="","",W53*$E53) | X53: =W53+U53 -> 0 | Y53: =IF(Z53="","",Z53*$E53) | AA53: =Z53+X53 -> 0 | AB53: =IF(AC53="","",AC53*$E53) | AD53: =AC53+AA53 -> 0 | AE53: =IF(AF53="","",AF53*$E53) | AG53: =AF53+AD53 -> 0 | AH53: =IF(AI53="","",AI53*$E53) | AJ53: =AI53+AG53 -> 0 | AK53: =IF(AL53="","",AL53*$E53) | AM53: =AL53+AJ53 -> 0 | AN53: =IF(AO53="","",AO53*$E53) | AP53: =AO53+AM53 -> 0 | AQ53: =IF(AR53="","",AR53*$E53) | AS53: =AR53+AP53 -> 0 | AT53: =IF(AU53="","",AU53*$E53) | AV53: =AU53+AS53 -> 0 | AW53: =IF(AX53="","",AX53*$E53) | AY53: =AX53+AV53 -> 0 | AZ53: =IF(BA53="","",BA53*$E53) | BB53: =BA53+AY53 -> 0 | BC53: =IF(BD53="","",BD53*$E53) | BE53: =BD53+BB53 -> 0 | BF53: =IF(BG53="","",BG53*$E53) | BH53: =BG53+BE53 -> 0 | BI53: =IF(BJ53="","",BJ53*$E53) | BK53: =BJ53+BH53 -> 0 | BL53: =IF(BM53="","",BM53*$E53) | BN53: =BM53+BK53 -> 0 | BO53: =IF(BP53="","",BP53*$E53) | BQ53: =BP53+BN53 -> 0 | BR53: =IF(BS53="","",BS53*$E53) | BT53: =BS53+BQ53 -> 0 | BU53: =IF(BV53="","",BV53*$E53) | BW53: =BV53+BT53 -> 0 | BX53: =IF(BY53="","",BY53*$E53) | BZ53: =BY53+BW53 -> 0 | CA53: =IF(CB53="","",CB53*$E53) | CC53: =CB53+BZ53 -> 0 | CD53: =IF(CE53="","",CE53*$E53) | CF53: =CE53+CC53 -> 0 | CG53: =IF(CH53="","",CH53*$E53) | CI53: =CH53+CF53 -> 0 | CJ53: =IF(CK53="","",CK53*$E53) | CL53: =CK53+CI53 -> 0 | CM53: =IF(CN53="","",CN53*$E53) | CO53: =CN53+CL53 -> 0 | CP53: =IF(CQ53="","",CQ53*$E53) | CR53: =CQ53+CO53 -> 0 | CS53: =IF(CT53="","",CT53*$E53) | CU53: =CT53+CR53 -> 0 | CV53: =IF(CW53="","",CW53*$E53) | CX53: =CW53+CU53 -> 0 | CY53: =IF(CZ53="","",CZ53*$E53) | DA53: =CZ53+CX53 -> 0 | DB53: =IF(DC53="","",DC53*$E53) | DD53: =DC53+DA53 -> 0 | DE53: =IF(DF53="","",DF53*$E53) | DG53: =DF53+DD53 -> 0 | DH53: =IF(DI53="","",DI53*$E53) | DJ53: =DI53+DG53 -> 0
A54: 3 | B54: 3.2.1.4 | C54: LAJE COM ESCORAMENTO E CIMBRAMENTO - INCLUSO VIGAS - 1 ANDAR | E54: =VLOOKUP(B54,'[49]PLANILHA ORCAMENTARIA'!A:G,7,0) -> 982810.61 | G54: =IF(H54="","",H54*E54) | I54: =H54 -> 0 | J54: =IF(K54="","",K54*H54) | L54: =K54 -> 0 | M54: =IF(N54="","",N54*K54) | O54: =N54 -> 0 | P54: =IF(Q54="","",Q54*N54) | R54: =Q54 -> 0 | S54: =IF(T54="","",T54*Q54) | U54: =T54 -> 0 | V54: =IF(W54="","",W54*T54) | X54: =W54 -> 0 | Y54: =IF(Z54="","",Z54*W54) | AA54: =Z54 -> 0 | AB54: =IF(AC54="","",AC54*Z54) | AD54: =AC54 -> 0 | AE54: =IF(AF54="","",AF54*AC54) | AG54: =AF54 -> 0 | AH54: =IF(AI54="","",AI54*AF54) | AJ54: =AI54 -> 0 | AK54: =IF(AL54="","",AL54*AI54) | AM54: =AL54 -> 0 | AN54: =IF(AO54="","",AO54*AL54) | AP54: =AO54 -> 0 | AQ54: =IF(AR54="","",AR54*AO54) | AS54: =AR54 -> 0 | AT54: =IF(AU54="","",AU54*AR54) | AV54: =AU54 -> 0 | AW54: =IF(AX54="","",AX54*AU54) | AY54: =AX54 -> 0 | AZ54: =IF(BA54="","",BA54*AX54) | BB54: =BA54 -> 0 | BC54: =IF(BD54="","",BD54*BA54) | BE54: =BD54 -> 0 | BF54: =IF(BG54="","",BG54*BD54) | BH54: =BG54 -> 0 | BI54: =IF(BJ54="","",BJ54*BG54) | BK54: =BJ54 -> 0 | BL54: =IF(BM54="","",BM54*BJ54) | BN54: =BM54 -> 0 | BO54: =IF(BP54="","",BP54*BM54) | BQ54: =BP54 -> 0 | BR54: =IF(BS54="","",BS54*BP54) | BT54: =BS54 -> 0 | BU54: =IF(BV54="","",BV54*BS54) | BW54: =BV54 -> 0 | BX54: =IF(BY54="","",BY54*BV54) | BZ54: =BY54 -> 0 | CA54: =IF(CB54="","",CB54*BY54) | CC54: =CB54 -> 0 | CD54: =IF(CE54="","",CE54*CB54) | CF54: =CE54 -> 0 | CG54: =IF(CH54="","",CH54*CE54) | CI54: =CH54 -> 0 | CJ54: =IF(CK54="","",CK54*CH54) | CL54: =CK54 -> 0 | CM54: =IF(CN54="","",CN54*CK54) | CO54: =CN54 -> 0 | CP54: =IF(CQ54="","",CQ54*CN54) | CR54: =CQ54 -> 0 | CS54: =IF(CT54="","",CT54*CQ54) | CU54: =CT54 -> 0 | CV54: =IF(CW54="","",CW54*CT54) | CX54: =CW54 -> 0 | CY54: =IF(CZ54="","",CZ54*CW54) | DA54: =CZ54 -> 0 | DB54: =IF(DC54="","",DC54*CZ54) | DD54: =DC54 -> 0 | DE54: =IF(DF54="","",DF54*DC54) | DG54: =DF54 -> 0 | DH54: =IF(DI54="","",DI54*DF54) | DJ54: =DI54 -> 0
A55: 3 | B55: 3.2.1.4.1 | C55: SETOR 1 - LAJE COM ESCORAMENTO E CIMBRAMENTO - INCLUSO VIGAS | E55: =VLOOKUP(B55,'[49]PLANILHA ORCAMENTARIA'!A:G,7,0) -> 307445.59 | G55: =IF(H55="","",H55*$E55) | I55: =H55 -> 0 | J55: =IF(K55="","",K55*$E55) | L55: =K55+I55 -> 0 | M55: =IF(N55="","",N55*$E55) | O55: =N55+L55 -> 0 | P55: =IF(Q55="","",Q55*$E55) | R55: =Q55+O55 -> 0 | S55: =IF(T55="","",T55*$E55) | U55: =T55+R55 -> 0 | V55: =IF(W55="","",W55*$E55) | X55: =W55+U55 -> 0 | Y55: =IF(Z55="","",Z55*$E55) | AA55: =Z55+X55 -> 0 | AB55: =IF(AC55="","",AC55*$E55) | AD55: =AC55+AA55 -> 0 | AE55: =IF(AF55="","",AF55*$E55) | AG55: =AF55+AD55 -> 0 | AH55: =IF(AI55="","",AI55*$E55) | AJ55: =AI55+AG55 -> 0 | AK55: =IF(AL55="","",AL55*$E55) | AM55: =AL55+AJ55 -> 0 | AN55: =IF(AO55="","",AO55*$E55) | AP55: =AO55+AM55 -> 0 | AQ55: =IF(AR55="","",AR55*$E55) | AS55: =AR55+AP55 -> 0 | AT55: =IF(AU55="","",AU55*$E55) | AV55: =AU55+AS55 -> 0 | AW55: =IF(AX55="","",AX55*$E55) | AY55: =AX55+AV55 -> 0 | AZ55: =IF(BA55="","",BA55*$E55) | BB55: =BA55+AY55 -> 0 | BC55: =IF(BD55="","",BD55*$E55) | BE55: =BD55+BB55 -> 0 | BF55: =IF(BG55="","",BG55*$E55) | BH55: =BG55+BE55 -> 0 | BI55: =IF(BJ55="","",BJ55*$E55) | BK55: =BJ55+BH55 -> 0 | BL55: =IF(BM55="","",BM55*$E55) | BN55: =BM55+BK55 -> 0 | BO55: =IF(BP55="","",BP55*$E55) | BQ55: =BP55+BN55 -> 0 | BR55: =IF(BS55="","",BS55*$E55) | BT55: =BS55+BQ55 -> 0 | BU55: =IF(BV55="","",BV55*$E55) | BW55: =BV55+BT55 -> 0 | BX55: =IF(BY55="","",BY55*$E55) | BZ55: =BY55+BW55 -> 0 | CA55: =IF(CB55="","",CB55*$E55) | CC55: =CB55+BZ55 -> 0 | CD55: =IF(CE55="","",CE55*$E55) | CF55: =CE55+CC55 -> 0 | CG55: =IF(CH55="","",CH55*$E55) | CI55: =CH55+CF55 -> 0 | CJ55: =IF(CK55="","",CK55*$E55) | CL55: =CK55+CI55 -> 0 | CM55: =IF(CN55="","",CN55*$E55) | CO55: =CN55+CL55 -> 0 | CP55: =IF(CQ55="","",CQ55*$E55) | CR55: =CQ55+CO55 -> 0 | CS55: =IF(CT55="","",CT55*$E55) | CU55: =CT55+CR55 -> 0 | CV55: =IF(CW55="","",CW55*$E55) | CX55: =CW55+CU55 -> 0 | CY55: =IF(CZ55="","",CZ55*$E55) | DA55: =CZ55+CX55 -> 0 | DB55: =IF(DC55="","",DC55*$E55) | DD55: =DC55+DA55 -> 0 | DE55: =IF(DF55="","",DF55*$E55) | DG55: =DF55+DD55 -> 0 | DH55: =IF(DI55="","",DI55*$E55) | DJ55: =DI55+DG55 -> 0
A56: 3 | B56: 3.2.1.4.2 | C56: SETOR 2 - LAJE COM ESCORAMENTO E CIMBRAMENTO - INCLUSO VIGAS | E56: =VLOOKUP(B56,'[49]PLANILHA ORCAMENTARIA'!A:G,7,0) -> 246389.03 | G56: =IF(H56="","",H56*$E56) | I56: =H56 -> 0 | J56: =IF(K56="","",K56*$E56) | L56: =K56+I56 -> 0 | M56: =IF(N56="","",N56*$E56) | O56: =N56+L56 -> 0 | P56: =IF(Q56="","",Q56*$E56) | R56: =Q56+O56 -> 0 | S56: =IF(T56="","",T56*$E56) | U56: =T56+R56 -> 0 | V56: =IF(W56="","",W56*$E56) | X56: =W56+U56 -> 0 | Y56: =IF(Z56="","",Z56*$E56) | AA56: =Z56+X56 -> 0 | AB56: =IF(AC56="","",AC56*$E56) | AD56: =AC56+AA56 -> 0 | AE56: =IF(AF56="","",AF56*$E56) | AG56: =AF56+AD56 -> 0 | AH56: =IF(AI56="","",AI56*$E56) | AJ56: =AI56+AG56 -> 0 | AK56: =IF(AL56="","",AL56*$E56) | AM56: =AL56+AJ56 -> 0 | AN56: =IF(AO56="","",AO56*$E56) | AP56: =AO56+AM56 -> 0 | AQ56: =IF(AR56="","",AR56*$E56) | AS56: =AR56+AP56 -> 0 | AT56: =IF(AU56="","",AU56*$E56) | AV56: =AU56+AS56 -> 0 | AW56: =IF(AX56="","",AX56*$E56) | AY56: =AX56+AV56 -> 0 | AZ56: =IF(BA56="","",BA56*$E56) | BB56: =BA56+AY56 -> 0 | BC56: =IF(BD56="","",BD56*$E56) | BE56: =BD56+BB56 -> 0 | BF56: =IF(BG56="","",BG56*$E56) | BH56: =BG56+BE56 -> 0 | BI56: =IF(BJ56="","",BJ56*$E56) | BK56: =BJ56+BH56 -> 0 | BL56: =IF(BM56="","",BM56*$E56) | BN56: =BM56+BK56 -> 0 | BO56: =IF(BP56="","",BP56*$E56) | BQ56: =BP56+BN56 -> 0 | BR56: =IF(BS56="","",BS56*$E56) | BT56: =BS56+BQ56 -> 0 | BU56: =IF(BV56="","",BV56*$E56) | BW56: =BV56+BT56 -> 0 | BX56: =IF(BY56="","",BY56*$E56) | BZ56: =BY56+BW56 -> 0 | CA56: =IF(CB56="","",CB56*$E56) | CC56: =CB56+BZ56 -> 0 | CD56: =IF(CE56="","",CE56*$E56) | CF56: =CE56+CC56 -> 0 | CG56: =IF(CH56="","",CH56*$E56) | CI56: =CH56+CF56 -> 0 | CJ56: =IF(CK56="","",CK56*$E56) | CL56: =CK56+CI56 -> 0 | CM56: =IF(CN56="","",CN56*$E56) | CO56: =CN56+CL56 -> 0 | CP56: =IF(CQ56="","",CQ56*$E56) | CR56: =CQ56+CO56 -> 0 | CS56: =IF(CT56="","",CT56*$E56) | CU56: =CT56+CR56 -> 0 | CV56: =IF(CW56="","",CW56*$E56) | CX56: =CW56+CU56 -> 0 | CY56: =IF(CZ56="","",CZ56*$E56) | DA56: =CZ56+CX56 -> 0 | DB56: =IF(DC56="","",DC56*$E56) | DD56: =DC56+DA56 -> 0 | DE56: =IF(DF56="","",DF56*$E56) | DG56: =DF56+DD56 -> 0 | DH56: =IF(DI56="","",DI56*$E56) | DJ56: =DI56+DG56 -> 0
A57: 3 | B57: 3.2.1.4.3 | C57: SETOR 3 - LAJE COM ESCORAMENTO E CIMBRAMENTO - INCLUSO VIGAS | E57: =VLOOKUP(B57,'[49]PLANILHA ORCAMENTARIA'!A:G,7,0) -> 428975.99 | G57: =IF(H57="","",H57*$E57) | I57: =H57 -> 0 | J57: =IF(K57="","",K57*$E57) | L57: =K57+I57 -> 0 | M57: =IF(N57="","",N57*$E57) | O57: =N57+L57 -> 0 | P57: =IF(Q57="","",Q57*$E57) | R57: =Q57+O57 -> 0 | S57: =IF(T57="","",T57*$E57) | U57: =T57+R57 -> 0 | V57: =IF(W57="","",W57*$E57) | X57: =W57+U57 -> 0 | Y57: =IF(Z57="","",Z57*$E57) | AA57: =Z57+X57 -> 0 | AB57: =IF(AC57="","",AC57*$E57) | AD57: =AC57+AA57 -> 0 | AE57: =IF(AF57="","",AF57*$E57) | AG57: =AF57+AD57 -> 0 | AH57: =IF(AI57="","",AI57*$E57) | AJ57: =AI57+AG57 -> 0 | AK57: =IF(AL57="","",AL57*$E57) | AM57: =AL57+AJ57 -> 0 | AN57: =IF(AO57="","",AO57*$E57) | AP57: =AO57+AM57 -> 0 | AQ57: =IF(AR57="","",AR57*$E57) | AS57: =AR57+AP57 -> 0 | AT57: =IF(AU57="","",AU57*$E57) | AV57: =AU57+AS57 -> 0 | AW57: =IF(AX57="","",AX57*$E57) | AY57: =AX57+AV57 -> 0 | AZ57: =IF(BA57="","",BA57*$E57) | BB57: =BA57+AY57 -> 0 | BC57: =IF(BD57="","",BD57*$E57) | BE57: =BD57+BB57 -> 0 | BF57: =IF(BG57="","",BG57*$E57) | BH57: =BG57+BE57 -> 0 | BI57: =IF(BJ57="","",BJ57*$E57) | BK57: =BJ57+BH57 -> 0 | BL57: =IF(BM57="","",BM57*$E57) | BN57: =BM57+BK57 -> 0 | BO57: =IF(BP57="","",BP57*$E57) | BQ57: =BP57+BN57 -> 0 | BR57: =IF(BS57="","",BS57*$E57) | BT57: =BS57+BQ57 -> 0 | BU57: =IF(BV57="","",BV57*$E57) | BW57: =BV57+BT57 -> 0 | BX57: =IF(BY57="","",BY57*$E57) | BZ57: =BY57+BW57 -> 0 | CA57: =IF(CB57="","",CB57*$E57) | CC57: =CB57+BZ57 -> 0 | CD57: =IF(CE57="","",CE57*$E57) | CF57: =CE57+CC57 -> 0 | CG57: =IF(CH57="","",CH57*$E57) | CI57: =CH57+CF57 -> 0 | CJ57: =IF(CK57="","",CK57*$E57) | CL57: =CK57+CI57 -> 0 | CM57: =IF(CN57="","",CN57*$E57) | CO57: =CN57+CL57 -> 0 | CP57: =IF(CQ57="","",CQ57*$E57) | CR57: =CQ57+CO57 -> 0 | CS57: =IF(CT57="","",CT57*$E57) | CU57: =CT57+CR57 -> 0 | CV57: =IF(CW57="","",CW57*$E57) | CX57: =CW57+CU57 -> 0 | CY57: =IF(CZ57="","",CZ57*$E57) | DA57: =CZ57+CX57 -> 0 | DB57: =IF(DC57="","",DC57*$E57) | DD57: =DC57+DA57 -> 0 | DE57: =IF(DF57="","",DF57*$E57) | DG57: =DF57+DD57 -> 0 | DH57: =IF(DI57="","",DI57*$E57) | DJ57: =DI57+DG57 -> 0
A58: 3 | B58: 3.2.1.5 | C58: LAJE COM ESCORAMENTO E CIMBRAMENTO - INCLUSO VIGAS - 2 ANDAR | E58: =VLOOKUP(B58,'[49]PLANILHA ORCAMENTARIA'!A:G,7,0) -> 1044004.8 | G58: =IF(H58="","",H58*E58) | I58: =H58 -> 0 | J58: =IF(K58="","",K58*H58) | L58: =K58 -> 0 | M58: =IF(N58="","",N58*K58) | O58: =N58 -> 0 | P58: =IF(Q58="","",Q58*N58) | R58: =Q58 -> 0 | S58: =IF(T58="","",T58*Q58) | U58: =T58 -> 0 | V58: =IF(W58="","",W58*T58) | X58: =W58 -> 0 | Y58: =IF(Z58="","",Z58*W58) | AA58: =Z58 -> 0 | AB58: =IF(AC58="","",AC58*Z58) | AD58: =AC58 -> 0 | AE58: =IF(AF58="","",AF58*AC58) | AG58: =AF58 -> 0 | AH58: =IF(AI58="","",AI58*AF58) | AJ58: =AI58 -> 0 | AK58: =IF(AL58="","",AL58*AI58) | AM58: =AL58 -> 0 | AN58: =IF(AO58="","",AO58*AL58) | AP58: =AO58 -> 0 | AQ58: =IF(AR58="","",AR58*AO58) | AS58: =AR58 -> 0 | AT58: =IF(AU58="","",AU58*AR58) | AV58: =AU58 -> 0 | AW58: =IF(AX58="","",AX58*AU58) | AY58: =AX58 -> 0 | AZ58: =IF(BA58="","",BA58*AX58) | BB58: =BA58 -> 0 | BC58: =IF(BD58="","",BD58*BA58) | BE58: =BD58 -> 0 | BF58: =IF(BG58="","",BG58*BD58) | BH58: =BG58 -> 0 | BI58: =IF(BJ58="","",BJ58*BG58) | BK58: =BJ58 -> 0 | BL58: =IF(BM58="","",BM58*BJ58) | BN58: =BM58 -> 0 | BO58: =IF(BP58="","",BP58*BM58) | BQ58: =BP58 -> 0 | BR58: =IF(BS58="","",BS58*BP58) | BT58: =BS58 -> 0 | BU58: =IF(BV58="","",BV58*BS58) | BW58: =BV58 -> 0 | BX58: =IF(BY58="","",BY58*BV58) | BZ58: =BY58 -> 0 | CA58: =IF(CB58="","",CB58*BY58) | CC58: =CB58 -> 0 | CD58: =IF(CE58="","",CE58*CB58) | CF58: =CE58 -> 0 | CG58: =IF(CH58="","",CH58*CE58) | CI58: =CH58 -> 0 | CJ58: =IF(CK58="","",CK58*CH58) | CL58: =CK58 -> 0 | CM58: =IF(CN58="","",CN58*CK58) | CO58: =CN58 -> 0 | CP58: =IF(CQ58="","",CQ58*CN58) | CR58: =CQ58 -> 0 | CS58: =IF(CT58="","",CT58*CQ58) | CU58: =CT58 -> 0 | CV58: =IF(CW58="","",CW58*CT58) | CX58: =CW58 -> 0 | CY58: =IF(CZ58="","",CZ58*CW58) | DA58: =CZ58 -> 0 | DB58: =IF(DC58="","",DC58*CZ58) | DD58: =DC58 -> 0 | DE58: =IF(DF58="","",DF58*DC58) | DG58: =DF58 -> 0 | DH58: =IF(DI58="","",DI58*DF58) | DJ58: =DI58 -> 0
A59: 3 | B59: 3.2.1.5.1 | C59: SETOR 1 - LAJE COM ESCORAMENTO E CIMBRAMENTO - INCLUSO VIGAS | E59: =VLOOKUP(B59,'[49]PLANILHA ORCAMENTARIA'!A:G,7,0) -> 284613.97 | G59: =IF(H59="","",H59*$E59) | I59: =H59 -> 0 | J59: =IF(K59="","",K59*$E59) | L59: =K59+I59 -> 0 | M59: =IF(N59="","",N59*$E59) | O59: =N59+L59 -> 0 | P59: =IF(Q59="","",Q59*$E59) | R59: =Q59+O59 -> 0 | S59: =IF(T59="","",T59*$E59) | U59: =T59+R59 -> 0 | V59: =IF(W59="","",W59*$E59) | X59: =W59+U59 -> 0 | Y59: =IF(Z59="","",Z59*$E59) | AA59: =Z59+X59 -> 0 | AB59: =IF(AC59="","",AC59*$E59) | AD59: =AC59+AA59 -> 0 | AE59: =IF(AF59="","",AF59*$E59) | AG59: =AF59+AD59 -> 0 | AH59: =IF(AI59="","",AI59*$E59) | AJ59: =AI59+AG59 -> 0 | AK59: =IF(AL59="","",AL59*$E59) | AM59: =AL59+AJ59 -> 0 | AN59: =IF(AO59="","",AO59*$E59) | AP59: =AO59+AM59 -> 0 | AQ59: =IF(AR59="","",AR59*$E59) | AS59: =AR59+AP59 -> 0 | AT59: =IF(AU59="","",AU59*$E59) | AV59: =AU59+AS59 -> 0 | AW59: =IF(AX59="","",AX59*$E59) | AY59: =AX59+AV59 -> 0 | AZ59: =IF(BA59="","",BA59*$E59) | BB59: =BA59+AY59 -> 0 | BC59: =IF(BD59="","",BD59*$E59) | BE59: =BD59+BB59 -> 0 | BF59: =IF(BG59="","",BG59*$E59) | BH59: =BG59+BE59 -> 0 | BI59: =IF(BJ59="","",BJ59*$E59) | BK59: =BJ59+BH59 -> 0 | BL59: =IF(BM59="","",BM59*$E59) | BN59: =BM59+BK59 -> 0 | BO59: =IF(BP59="","",BP59*$E59) | BQ59: =BP59+BN59 -> 0 | BR59: =IF(BS59="","",BS59*$E59) | BT59: =BS59+BQ59 -> 0 | BU59: =IF(BV59="","",BV59*$E59) | BW59: =BV59+BT59 -> 0 | BX59: =IF(BY59="","",BY59*$E59) | BZ59: =BY59+BW59 -> 0 | CA59: =IF(CB59="","",CB59*$E59) | CC59: =CB59+BZ59 -> 0 | CD59: =IF(CE59="","",CE59*$E59) | CF59: =CE59+CC59 -> 0 | CG59: =IF(CH59="","",CH59*$E59) | CI59: =CH59+CF59 -> 0 | CJ59: =IF(CK59="","",CK59*$E59) | CL59: =CK59+CI59 -> 0 | CM59: =IF(CN59="","",CN59*$E59) | CO59: =CN59+CL59 -> 0 | CP59: =IF(CQ59="","",CQ59*$E59) | CR59: =CQ59+CO59 -> 0 | CS59: =IF(CT59="","",CT59*$E59) | CU59: =CT59+CR59 -> 0 | CV59: =IF(CW59="","",CW59*$E59) | CX59: =CW59+CU59 -> 0 | CY59: =IF(CZ59="","",CZ59*$E59) | DA59: =CZ59+CX59 -> 0 | DB59: =IF(DC59="","",DC59*$E59) | DD59: =DC59+DA59 -> 0 | DE59: =IF(DF59="","",DF59*$E59) | DG59: =DF59+DD59 -> 0 | DH59: =IF(DI59="","",DI59*$E59) | DJ59: =DI59+DG59 -> 0
A60: 3 | B60: 3.2.1.5.2 | C60: SETOR 2 - LAJE COM ESCORAMENTO E CIMBRAMENTO - INCLUSO VIGAS | E60: =VLOOKUP(B60,'[49]PLANILHA ORCAMENTARIA'!A:G,7,0) -> 284613.97 | G60: =IF(H60="","",H60*$E60) | I60: =H60 -> 0 | J60: =IF(K60="","",K60*$E60) | L60: =K60+I60 -> 0 | M60: =IF(N60="","",N60*$E60) | O60: =N60+L60 -> 0 | P60: =IF(Q60="","",Q60*$E60) | R60: =Q60+O60 -> 0 | S60: =IF(T60="","",T60*$E60) | U60: =T60+R60 -> 0 | V60: =IF(W60="","",W60*$E60) | X60: =W60+U60 -> 0 | Y60: =IF(Z60="","",Z60*$E60) | AA60: =Z60+X60 -> 0 | AB60: =IF(AC60="","",AC60*$E60) | AD60: =AC60+AA60 -> 0 | AE60: =IF(AF60="","",AF60*$E60) | AG60: =AF60+AD60 -> 0 | AH60: =IF(AI60="","",AI60*$E60) | AJ60: =AI60+AG60 -> 0 | AK60: =IF(AL60="","",AL60*$E60) | AM60: =AL60+AJ60 -> 0 | AN60: =IF(AO60="","",AO60*$E60) | AP60: =AO60+AM60 -> 0 | AQ60: =IF(AR60="","",AR60*$E60) | AS60: =AR60+AP60 -> 0 | AT60: =IF(AU60="","",AU60*$E60) | AV60: =AU60+AS60 -> 0 | AW60: =IF(AX60="","",AX60*$E60) | AY60: =AX60+AV60 -> 0 | AZ60: =IF(BA60="","",BA60*$E60) | BB60: =BA60+AY60 -> 0 | BC60: =IF(BD60="","",BD60*$E60) | BE60: =BD60+BB60 -> 0 | BF60: =IF(BG60="","",BG60*$E60) | BH60: =BG60+BE60 -> 0 | BI60: =IF(BJ60="","",BJ60*$E60) | BK60: =BJ60+BH60 -> 0 | BL60: =IF(BM60="","",BM60*$E60) | BN60: =BM60+BK60 -> 0 | BO60: =IF(BP60="","",BP60*$E60) | BQ60: =BP60+BN60 -> 0 | BR60: =IF(BS60="","",BS60*$E60) | BT60: =BS60+BQ60 -> 0 | BU60: =IF(BV60="","",BV60*$E60) | BW60: =BV60+BT60 -> 0 | BX60: =IF(BY60="","",BY60*$E60) | BZ60: =BY60+BW60 -> 0 | CA60: =IF(CB60="","",CB60*$E60) | CC60: =CB60+BZ60 -> 0 | CD60: =IF(CE60="","",CE60*$E60) | CF60: =CE60+CC60 -> 0 | CG60: =IF(CH60="","",CH60*$E60) | CI60: =CH60+CF60 -> 0 | CJ60: =IF(CK60="","",CK60*$E60) | CL60: =CK60+CI60 -> 0 | CM60: =IF(CN60="","",CN60*$E60) | CO60: =CN60+CL60 -> 0 | CP60: =IF(CQ60="","",CQ60*$E60) | CR60: =CQ60+CO60 -> 0 | CS60: =IF(CT60="","",CT60*$E60) | CU60: =CT60+CR60 -> 0 | CV60: =IF(CW60="","",CW60*$E60) | CX60: =CW60+CU60 -> 0 | CY60: =IF(CZ60="","",CZ60*$E60) | DA60: =CZ60+CX60 -> 0 | DB60: =IF(DC60="","",DC60*$E60) | DD60: =DC60+DA60 -> 0 | DE60: =IF(DF60="","",DF60*$E60) | DG60: =DF60+DD60 -> 0 | DH60: =IF(DI60="","",DI60*$E60) | DJ60: =DI60+DG60 -> 0
A61: 3 | B61: 3.2.1.5.3 | C61: SETOR 3 - LAJE COM ESCORAMENTO E CIMBRAMENTO - INCLUSO VIGAS | E61: =VLOOKUP(B61,'[49]PLANILHA ORCAMENTARIA'!A:G,7,0) -> 474776.84 | G61: =IF(H61="","",H61*$E61) | I61: =H61 -> 0 | J61: =IF(K61="","",K61*$E61) | L61: =K61+I61 -> 0 | M61: =IF(N61="","",N61*$E61) | O61: =N61+L61 -> 0 | P61: =IF(Q61="","",Q61*$E61) | R61: =Q61+O61 -> 0 | S61: =IF(T61="","",T61*$E61) | U61: =T61+R61 -> 0 | V61: =IF(W61="","",W61*$E61) | X61: =W61+U61 -> 0 | Y61: =IF(Z61="","",Z61*$E61) | AA61: =Z61+X61 -> 0 | AB61: =IF(AC61="","",AC61*$E61) | AD61: =AC61+AA61 -> 0 | AE61: =IF(AF61="","",AF61*$E61) | AG61: =AF61+AD61 -> 0 | AH61: =IF(AI61="","",AI61*$E61) | AJ61: =AI61+AG61 -> 0 | AK61: =IF(AL61="","",AL61*$E61) | AM61: =AL61+AJ61 -> 0 | AN61: =IF(AO61="","",AO61*$E61) | AP61: =AO61+AM61 -> 0 | AQ61: =IF(AR61="","",AR61*$E61) | AS61: =AR61+AP61 -> 0 | AT61: =IF(AU61="","",AU61*$E61) | AV61: =AU61+AS61 -> 0 | AW61: =IF(AX61="","",AX61*$E61) | AY61: =AX61+AV61 -> 0 | AZ61: =IF(BA61="","",BA61*$E61) | BB61: =BA61+AY61 -> 0 | BC61: =IF(BD61="","",BD61*$E61) | BE61: =BD61+BB61 -> 0 | BF61: =IF(BG61="","",BG61*$E61) | BH61: =BG61+BE61 -> 0 | BI61: =IF(BJ61="","",BJ61*$E61) | BK61: =BJ61+BH61 -> 0 | BL61: =IF(BM61="","",BM61*$E61) | BN61: =BM61+BK61 -> 0 | BO61: =IF(BP61="","",BP61*$E61) | BQ61: =BP61+BN61 -> 0 | BR61: =IF(BS61="","",BS61*$E61) | BT61: =BS61+BQ61 -> 0 | BU61: =IF(BV61="","",BV61*$E61) | BW61: =BV61+BT61 -> 0 | BX61: =IF(BY61="","",BY61*$E61) | BZ61: =BY61+BW61 -> 0 | CA61: =IF(CB61="","",CB61*$E61) | CC61: =CB61+BZ61 -> 0 | CD61: =IF(CE61="","",CE61*$E61) | CF61: =CE61+CC61 -> 0 | CG61: =IF(CH61="","",CH61*$E61) | CI61: =CH61+CF61 -> 0 | CJ61: =IF(CK61="","",CK61*$E61) | CL61: =CK61+CI61 -> 0 | CM61: =IF(CN61="","",CN61*$E61) | CO61: =CN61+CL61 -> 0 | CP61: =IF(CQ61="","",CQ61*$E61) | CR61: =CQ61+CO61 -> 0 | CS61: =IF(CT61="","",CT61*$E61) | CU61: =CT61+CR61 -> 0 | CV61: =IF(CW61="","",CW61*$E61) | CX61: =CW61+CU61 -> 0 | CY61: =IF(CZ61="","",CZ61*$E61) | DA61: =CZ61+CX61 -> 0 | DB61: =IF(DC61="","",DC61*$E61) | DD61: =DC61+DA61 -> 0 | DE61: =IF(DF61="","",DF61*$E61) | DG61: =DF61+DD61 -> 0 | DH61: =IF(DI61="","",DI61*$E61) | DJ61: =DI61+DG61 -> 0
A62: 3 | B62: 3.2.1.6 | C62: LAJE COM ESCORAMENTO E CIMBRAMENTO - INCLUSO VIGAS - COBERTA | E62: =VLOOKUP(B62,'[49]PLANILHA ORCAMENTARIA'!A:G,7,0) -> 1525532.7 | G62: =IF(H62="","",H62*E62) | I62: =H62 -> 0 | J62: =IF(K62="","",K62*H62) | L62: =K62 -> 0 | M62: =IF(N62="","",N62*K62) | O62: =N62 -> 0 | P62: =IF(Q62="","",Q62*N62) | R62: =Q62 -> 0 | S62: =IF(T62="","",T62*Q62) | U62: =T62 -> 0 | V62: =IF(W62="","",W62*T62) | X62: =W62 -> 0 | Y62: =IF(Z62="","",Z62*W62) | AA62: =Z62 -> 0 | AB62: =IF(AC62="","",AC62*Z62) | AD62: =AC62 -> 0 | AE62: =IF(AF62="","",AF62*AC62) | AG62: =AF62 -> 0 | AH62: =IF(AI62="","",AI62*AF62) | AJ62: =AI62 -> 0 | AK62: =IF(AL62="","",AL62*AI62) | AM62: =AL62 -> 0 | AN62: =IF(AO62="","",AO62*AL62) | AP62: =AO62 -> 0 | AQ62: =IF(AR62="","",AR62*AO62) | AS62: =AR62 -> 0 | AT62: =IF(AU62="","",AU62*AR62) | AV62: =AU62 -> 0 | AW62: =IF(AX62="","",AX62*AU62) | AY62: =AX62 -> 0 | AZ62: =IF(BA62="","",BA62*AX62) | BB62: =BA62 -> 0 | BC62: =IF(BD62="","",BD62*BA62) | BE62: =BD62 -> 0 | BF62: =IF(BG62="","",BG62*BD62) | BH62: =BG62 -> 0 | BI62: =IF(BJ62="","",BJ62*BG62) | BK62: =BJ62 -> 0 | BL62: =IF(BM62="","",BM62*BJ62) | BN62: =BM62 -> 0 | BO62: =IF(BP62="","",BP62*BM62) | BQ62: =BP62 -> 0 | BR62: =IF(BS62="","",BS62*BP62) | BT62: =BS62 -> 0 | BU62: =IF(BV62="","",BV62*BS62) | BW62: =BV62 -> 0 | BX62: =IF(BY62="","",BY62*BV62) | BZ62: =BY62 -> 0 | CA62: =IF(CB62="","",CB62*BY62) | CC62: =CB62 -> 0 | CD62: =IF(CE62="","",CE62*CB62) | CF62: =CE62 -> 0 | CG62: =IF(CH62="","",CH62*CE62) | CI62: =CH62 -> 0 | CJ62: =IF(CK62="","",CK62*CH62) | CL62: =CK62 -> 0 | CM62: =IF(CN62="","",CN62*CK62) | CO62: =CN62 -> 0 | CP62: =IF(CQ62="","",CQ62*CN62) | CR62: =CQ62 -> 0 | CS62: =IF(CT62="","",CT62*CQ62) | CU62: =CT62 -> 0 | CV62: =IF(CW62="","",CW62*CT62) | CX62: =CW62 -> 0 | CY62: =IF(CZ62="","",CZ62*CW62) | DA62: =CZ62 -> 0 | DB62: =IF(DC62="","",DC62*CZ62) | DD62: =DC62 -> 0 | DE62: =IF(DF62="","",DF62*DC62) | DG62: =DF62 -> 0 | DH62: =IF(DI62="","",DI62*DF62) | DJ62: =DI62 -> 0
A63: 3 | B63: 3.2.1.6.1 | C63: SETOR 1 - LAJE COM ESCORAMENTO E CIMBRAMENTO - INCLUSO VIGAS | E63: =VLOOKUP(B63,'[49]PLANILHA ORCAMENTARIA'!A:G,7,0) -> 392654.36 | G63: =IF(H63="","",H63*$E63) | I63: =H63 -> 0 | J63: =IF(K63="","",K63*$E63) | L63: =K63+I63 -> 0 | M63: =IF(N63="","",N63*$E63) | O63: =N63+L63 -> 0 | P63: =IF(Q63="","",Q63*$E63) | R63: =Q63+O63 -> 0 | S63: =IF(T63="","",T63*$E63) | U63: =T63+R63 -> 0 | V63: =IF(W63="","",W63*$E63) | X63: =W63+U63 -> 0 | Y63: =IF(Z63="","",Z63*$E63) | AA63: =Z63+X63 -> 0 | AB63: =IF(AC63="","",AC63*$E63) | AD63: =AC63+AA63 -> 0 | AE63: =IF(AF63="","",AF63*$E63) | AG63: =AF63+AD63 -> 0 | AH63: =IF(AI63="","",AI63*$E63) | AJ63: =AI63+AG63 -> 0 | AK63: =IF(AL63="","",AL63*$E63) | AM63: =AL63+AJ63 -> 0 | AN63: =IF(AO63="","",AO63*$E63) | AP63: =AO63+AM63 -> 0 | AQ63: =IF(AR63="","",AR63*$E63) | AS63: =AR63+AP63 -> 0 | AT63: =IF(AU63="","",AU63*$E63) | AV63: =AU63+AS63 -> 0 | AW63: =IF(AX63="","",AX63*$E63) | AY63: =AX63+AV63 -> 0 | AZ63: =IF(BA63="","",BA63*$E63) | BB63: =BA63+AY63 -> 0 | BC63: =IF(BD63="","",BD63*$E63) | BE63: =BD63+BB63 -> 0 | BF63: =IF(BG63="","",BG63*$E63) | BH63: =BG63+BE63 -> 0 | BI63: =IF(BJ63="","",BJ63*$E63) | BK63: =BJ63+BH63 -> 0 | BL63: =IF(BM63="","",BM63*$E63) | BN63: =BM63+BK63 -> 0 | BO63: =IF(BP63="","",BP63*$E63) | BQ63: =BP63+BN63 -> 0 | BR63: =IF(BS63="","",BS63*$E63) | BT63: =BS63+BQ63 -> 0 | BU63: =IF(BV63="","",BV63*$E63) | BW63: =BV63+BT63 -> 0 | BX63: =IF(BY63="","",BY63*$E63) | BZ63: =BY63+BW63 -> 0 | CA63: =IF(CB63="","",CB63*$E63) | CC63: =CB63+BZ63 -> 0 | CD63: =IF(CE63="","",CE63*$E63) | CF63: =CE63+CC63 -> 0 | CG63: =IF(CH63="","",CH63*$E63) | CI63: =CH63+CF63 -> 0 | CJ63: =IF(CK63="","",CK63*$E63) | CL63: =CK63+CI63 -> 0 | CM63: =IF(CN63="","",CN63*$E63) | CO63: =CN63+CL63 -> 0 | CP63: =IF(CQ63="","",CQ63*$E63) | CR63: =CQ63+CO63 -> 0 | CS63: =IF(CT63="","",CT63*$E63) | CU63: =CT63+CR63 -> 0 | CV63: =IF(CW63="","",CW63*$E63) | CX63: =CW63+CU63 -> 0 | CY63: =IF(CZ63="","",CZ63*$E63) | DA63: =CZ63+CX63 -> 0 | DB63: =IF(DC63="","",DC63*$E63) | DD63: =DC63+DA63 -> 0 | DE63: =IF(DF63="","",DF63*$E63) | DG63: =DF63+DD63 -> 0 | DH63: =IF(DI63="","",DI63*$E63) | DJ63: =DI63+DG63 -> 0
A64: 3 | B64: 3.2.1.6.2 | C64: SETOR 2 - LAJE COM ESCORAMENTO E CIMBRAMENTO - INCLUSO VIGAS | E64: =VLOOKUP(B64,'[49]PLANILHA ORCAMENTARIA'!A:G,7,0) -> 392654.36 | G64: =IF(H64="","",H64*$E64) | I64: =H64 -> 0 | J64: =IF(K64="","",K64*$E64) | L64: =K64+I64 -> 0 | M64: =IF(N64="","",N64*$E64) | O64: =N64+L64 -> 0 | P64: =IF(Q64="","",Q64*$E64) | R64: =Q64+O64 -> 0 | S64: =IF(T64="","",T64*$E64) | U64: =T64+R64 -> 0 | V64: =IF(W64="","",W64*$E64) | X64: =W64+U64 -> 0 | Y64: =IF(Z64="","",Z64*$E64) | AA64: =Z64+X64 -> 0 | AB64: =IF(AC64="","",AC64*$E64) | AD64: =AC64+AA64 -> 0 | AE64: =IF(AF64="","",AF64*$E64) | AG64: =AF64+AD64 -> 0 | AH64: =IF(AI64="","",AI64*$E64) | AJ64: =AI64+AG64 -> 0 | AK64: =IF(AL64="","",AL64*$E64) | AM64: =AL64+AJ64 -> 0 | AN64: =IF(AO64="","",AO64*$E64) | AP64: =AO64+AM64 -> 0 | AQ64: =IF(AR64="","",AR64*$E64) | AS64: =AR64+AP64 -> 0 | AT64: =IF(AU64="","",AU64*$E64) | AV64: =AU64+AS64 -> 0 | AW64: =IF(AX64="","",AX64*$E64) | AY64: =AX64+AV64 -> 0 | AZ64: =IF(BA64="","",BA64*$E64) | BB64: =BA64+AY64 -> 0 | BC64: =IF(BD64="","",BD64*$E64) | BE64: =BD64+BB64 -> 0 | BF64: =IF(BG64="","",BG64*$E64) | BH64: =BG64+BE64 -> 0 | BI64: =IF(BJ64="","",BJ64*$E64) | BK64: =BJ64+BH64 -> 0 | BL64: =IF(BM64="","",BM64*$E64) | BN64: =BM64+BK64 -> 0 | BO64: =IF(BP64="","",BP64*$E64) | BQ64: =BP64+BN64 -> 0 | BR64: =IF(BS64="","",BS64*$E64) | BT64: =BS64+BQ64 -> 0 | BU64: =IF(BV64="","",BV64*$E64) | BW64: =BV64+BT64 -> 0 | BX64: =IF(BY64="","",BY64*$E64) | BZ64: =BY64+BW64 -> 0 | CA64: =IF(CB64="","",CB64*$E64) | CC64: =CB64+BZ64 -> 0 | CD64: =IF(CE64="","",CE64*$E64) | CF64: =CE64+CC64 -> 0 | CG64: =IF(CH64="","",CH64*$E64) | CI64: =CH64+CF64 -> 0 | CJ64: =IF(CK64="","",CK64*$E64) | CL64: =CK64+CI64 -> 0 | CM64: =IF(CN64="","",CN64*$E64) | CO64: =CN64+CL64 -> 0 | CP64: =IF(CQ64="","",CQ64*$E64) | CR64: =CQ64+CO64 -> 0 | CS64: =IF(CT64="","",CT64*$E64) | CU64: =CT64+CR64 -> 0 | CV64: =IF(CW64="","",CW64*$E64) | CX64: =CW64+CU64 -> 0 | CY64: =IF(CZ64="","",CZ64*$E64) | DA64: =CZ64+CX64 -> 0 | DB64: =IF(DC64="","",DC64*$E64) | DD64: =DC64+DA64 -> 0 | DE64: =IF(DF64="","",DF64*$E64) | DG64: =DF64+DD64 -> 0 | DH64: =IF(DI64="","",DI64*$E64) | DJ64: =DI64+DG64 -> 0
A65: 3 | B65: 3.2.1.6.3 | C65: SETOR 3 - LAJE COM ESCORAMENTO E CIMBRAMENTO - INCLUSO VIGAS | E65: =VLOOKUP(B65,'[49]PLANILHA ORCAMENTARIA'!A:G,7,0) -> 740224.02 | G65: =IF(H65="","",H65*$E65) | I65: =H65 -> 0 | J65: =IF(K65="","",K65*$E65) | L65: =K65+I65 -> 0 | M65: =IF(N65="","",N65*$E65) | O65: =N65+L65 -> 0 | P65: =IF(Q65="","",Q65*$E65) | R65: =Q65+O65 -> 0 | S65: =IF(T65="","",T65*$E65) | U65: =T65+R65 -> 0 | V65: =IF(W65="","",W65*$E65) | X65: =W65+U65 -> 0 | Y65: =IF(Z65="","",Z65*$E65) | AA65: =Z65+X65 -> 0 | AB65: =IF(AC65="","",AC65*$E65) | AD65: =AC65+AA65 -> 0 | AE65: =IF(AF65="","",AF65*$E65) | AG65: =AF65+AD65 -> 0 | AH65: =IF(AI65="","",AI65*$E65) | AJ65: =AI65+AG65 -> 0 | AK65: =IF(AL65="","",AL65*$E65) | AM65: =AL65+AJ65 -> 0 | AN65: =IF(AO65="","",AO65*$E65) | AP65: =AO65+AM65 -> 0 | AQ65: =IF(AR65="","",AR65*$E65) | AS65: =AR65+AP65 -> 0 | AT65: =IF(AU65="","",AU65*$E65) | AV65: =AU65+AS65 -> 0 | AW65: =IF(AX65="","",AX65*$E65) | AY65: =AX65+AV65 -> 0 | AZ65: =IF(BA65="","",BA65*$E65) | BB65: =BA65+AY65 -> 0 | BC65: =IF(BD65="","",BD65*$E65) | BE65: =BD65+BB65 -> 0 | BF65: =IF(BG65="","",BG65*$E65) | BH65: =BG65+BE65 -> 0 | BI65: =IF(BJ65="","",BJ65*$E65) | BK65: =BJ65+BH65 -> 0 | BL65: =IF(BM65="","",BM65*$E65) | BN65: =BM65+BK65 -> 0 | BO65: =IF(BP65="","",BP65*$E65) | BQ65: =BP65+BN65 -> 0 | BR65: =IF(BS65="","",BS65*$E65) | BT65: =BS65+BQ65 -> 0 | BU65: =IF(BV65="","",BV65*$E65) | BW65: =BV65+BT65 -> 0 | BX65: =IF(BY65="","",BY65*$E65) | BZ65: =BY65+BW65 -> 0 | CA65: =IF(CB65="","",CB65*$E65) | CC65: =CB65+BZ65 -> 0 | CD65: =IF(CE65="","",CE65*$E65) | CF65: =CE65+CC65 -> 0 | CG65: =IF(CH65="","",CH65*$E65) | CI65: =CH65+CF65 -> 0 | CJ65: =IF(CK65="","",CK65*$E65) | CL65: =CK65+CI65 -> 0 | CM65: =IF(CN65="","",CN65*$E65) | CO65: =CN65+CL65 -> 0 | CP65: =IF(CQ65="","",CQ65*$E65) | CR65: =CQ65+CO65 -> 0 | CS65: =IF(CT65="","",CT65*$E65) | CU65: =CT65+CR65 -> 0 | CV65: =IF(CW65="","",CW65*$E65) | CX65: =CW65+CU65 -> 0 | CY65: =IF(CZ65="","",CZ65*$E65) | DA65: =CZ65+CX65 -> 0 | DB65: =IF(DC65="","",DC65*$E65) | DD65: =DC65+DA65 -> 0 | DE65: =IF(DF65="","",DF65*$E65) | DG65: =DF65+DD65 -> 0 | DH65: =IF(DI65="","",DI65*$E65) | DJ65: =DI65+DG65 -> 0
A66: 3 | B66: 3.2.2 | C66: BLOCO ANEXO | E66: =VLOOKUP(B66,'[49]PLANILHA ORCAMENTARIA'!A:G,7,0) -> 137711.02 | G66: =IF(H66="","",H66*E66) | I66: =H66 -> 0 | J66: =IF(K66="","",K66*H66) | L66: =K66 -> 0 | M66: =IF(N66="","",N66*K66) | O66: =N66 -> 0 | P66: =IF(Q66="","",Q66*N66) | R66: =Q66 -> 0 | S66: =IF(T66="","",T66*Q66) | U66: =T66 -> 0 | V66: =IF(W66="","",W66*T66) | X66: =W66 -> 0 | Y66: =IF(Z66="","",Z66*W66) | AA66: =Z66 -> 0 | AB66: =IF(AC66="","",AC66*Z66) | AD66: =AC66 -> 0 | AE66: =IF(AF66="","",AF66*AC66) | AG66: =AF66 -> 0 | AH66: =IF(AI66="","",AI66*AF66) | AJ66: =AI66 -> 0 | AK66: =IF(AL66="","",AL66*AI66) | AM66: =AL66 -> 0 | AN66: =IF(AO66="","",AO66*AL66) | AP66: =AO66 -> 0 | AQ66: =IF(AR66="","",AR66*AO66) | AS66: =AR66 -> 0 | AT66: =IF(AU66="","",AU66*AR66) | AV66: =AU66 -> 0 | AW66: =IF(AX66="","",AX66*AU66) | AY66: =AX66 -> 0 | AZ66: =IF(BA66="","",BA66*AX66) | BB66: =BA66 -> 0 | BC66: =IF(BD66="","",BD66*BA66) | BE66: =BD66 -> 0 | BF66: =IF(BG66="","",BG66*BD66) | BH66: =BG66 -> 0 | BI66: =IF(BJ66="","",BJ66*BG66) | BK66: =BJ66 -> 0 | BL66: =IF(BM66="","",BM66*BJ66) | BN66: =BM66 -> 0 | BO66: =IF(BP66="","",BP66*BM66) | BQ66: =BP66 -> 0 | BR66: =IF(BS66="","",BS66*BP66) | BT66: =BS66 -> 0 | BU66: =IF(BV66="","",BV66*BS66) | BW66: =BV66 -> 0 | BX66: =IF(BY66="","",BY66*BV66) | BZ66: =BY66 -> 0 | CA66: =IF(CB66="","",CB66*BY66) | CC66: =CB66 -> 0 | CD66: =IF(CE66="","",CE66*CB66) | CF66: =CE66 -> 0 | CG66: =IF(CH66="","",CH66*CE66) | CI66: =CH66 -> 0 | CJ66: =IF(CK66="","",CK66*CH66) | CL66: =CK66 -> 0 | CM66: =IF(CN66="","",CN66*CK66) | CO66: =CN66 -> 0 | CP66: =IF(CQ66="","",CQ66*CN66) | CR66: =CQ66 -> 0 | CS66: =IF(CT66="","",CT66*CQ66) | CU66: =CT66 -> 0 | CV66: =IF(CW66="","",CW66*CT66) | CX66: =CW66 -> 0 | CY66: =IF(CZ66="","",CZ66*CW66) | DA66: =CZ66 -> 0 | DB66: =IF(DC66="","",DC66*CZ66) | DD66: =DC66 -> 0 | DE66: =IF(DF66="","",DF66*DC66) | DG66: =DF66 -> 0 | DH66: =IF(DI66="","",DI66*DF66) | DJ66: =DI66 -> 0
A67: 3 | B67: 3.2.2.1 | C67: PILARES | E67: =VLOOKUP(B67,'[49]PLANILHA ORCAMENTARIA'!A:G,7,0) -> 14883.24 | G67: =IF(H67="","",H67*$E67) | I67: =H67 -> 0 | J67: =IF(K67="","",K67*$E67) | L67: =K67+I67 -> 0 | M67: =IF(N67="","",N67*$E67) | O67: =N67+L67 -> 0 | P67: =IF(Q67="","",Q67*$E67) -> 14883.24 | Q67: 1 | R67: =Q67+O67 -> 1 | S67: =IF(T67="","",T67*$E67) | U67: =T67+R67 -> 1 | V67: =IF(W67="","",W67*$E67) | X67: =W67+U67 -> 1 | Y67: =IF(Z67="","",Z67*$E67) | AA67: =Z67+X67 -> 1 | AB67: =IF(AC67="","",AC67*$E67) | AD67: =AC67+AA67 -> 1 | AE67: =IF(AF67="","",AF67*$E67) | AG67: =AF67+AD67 -> 1 | AH67: =IF(AI67="","",AI67*$E67) | AJ67: =AI67+AG67 -> 1 | AK67: =IF(AL67="","",AL67*$E67) | AM67: =AL67+AJ67 -> 1 | AN67: =IF(AO67="","",AO67*$E67) | AP67: =AO67+AM67 -> 1 | AQ67: =IF(AR67="","",AR67*$E67) | AS67: =AR67+AP67 -> 1 | AT67: =IF(AU67="","",AU67*$E67) | AV67: =AU67+AS67 -> 1 | AW67: =IF(AX67="","",AX67*$E67) | AY67: =AX67+AV67 -> 1 | AZ67: =IF(BA67="","",BA67*$E67) | BB67: =BA67+AY67 -> 1 | BC67: =IF(BD67="","",BD67*$E67) | BE67: =BD67+BB67 -> 1 | BF67: =IF(BG67="","",BG67*$E67) | BH67: =BG67+BE67 -> 1 | BI67: =IF(BJ67="","",BJ67*$E67) | BK67: =BJ67+BH67 -> 1 | BL67: =IF(BM67="","",BM67*$E67) | BN67: =BM67+BK67 -> 1 | BO67: =IF(BP67="","",BP67*$E67) | BQ67: =BP67+BN67 -> 1 | BR67: =IF(BS67="","",BS67*$E67) | BT67: =BS67+BQ67 -> 1 | BU67: =IF(BV67="","",BV67*$E67) | BW67: =BV67+BT67 -> 1 | BX67: =IF(BY67="","",BY67*$E67) | BZ67: =BY67+BW67 -> 1 | CA67: =IF(CB67="","",CB67*$E67) | CC67: =CB67+BZ67 -> 1 | CD67: =IF(CE67="","",CE67*$E67) | CF67: =CE67+CC67 -> 1 | CG67: =IF(CH67="","",CH67*$E67) | CI67: =CH67+CF67 -> 1 | CJ67: =IF(CK67="","",CK67*$E67) | CL67: =CK67+CI67 -> 1 | CM67: =IF(CN67="","",CN67*$E67) | CO67: =CN67+CL67 -> 1 | CP67: =IF(CQ67="","",CQ67*$E67) | CR67: =CQ67+CO67 -> 1 | CS67: =IF(CT67="","",CT67*$E67) | CU67: =CT67+CR67 -> 1 | CV67: =IF(CW67="","",CW67*$E67) | CX67: =CW67+CU67 -> 1 | CY67: =IF(CZ67="","",CZ67*$E67) | DA67: =CZ67+CX67 -> 1 | DB67: =IF(DC67="","",DC67*$E67) | DD67: =DC67+DA67 -> 1 | DE67: =IF(DF67="","",DF67*$E67) | DG67: =DF67+DD67 -> 1 | DH67: =IF(DI67="","",DI67*$E67) | DJ67: =DI67+DG67 -> 1
A68: 3 | B68: 3.2.2.2 | C68: LAJE COM ESCORAMENTO E CIMBRAMENTO - INCLUSO VIGAS | E68: =VLOOKUP(B68,'[49]PLANILHA ORCAMENTARIA'!A:G,7,0) -> 122827.78 | G68: =IF(H68="","",H68*$E68) | I68: =H68 -> 0 | J68: =IF(K68="","",K68*$E68) | L68: =K68+I68 -> 0 | M68: =IF(N68="","",N68*$E68) | O68: =N68+L68 -> 0 | P68: =IF(Q68="","",Q68*$E68) | R68: =Q68+O68 -> 0 | S68: =IF(T68="","",T68*$E68) -> 122827.78 | T68: 1 | U68: =T68+R68 -> 1 | V68: =IF(W68="","",W68*$E68) | X68: =W68+U68 -> 1 | Y68: =IF(Z68="","",Z68*$E68) | AA68: =Z68+X68 -> 1 | AB68: =IF(AC68="","",AC68*$E68) | AD68: =AC68+AA68 -> 1 | AE68: =IF(AF68="","",AF68*$E68) | AG68: =AF68+AD68 -> 1 | AH68: =IF(AI68="","",AI68*$E68) | AJ68: =AI68+AG68 -> 1 | AK68: =IF(AL68="","",AL68*$E68) | AM68: =AL68+AJ68 -> 1 | AN68: =IF(AO68="","",AO68*$E68) | AP68: =AO68+AM68 -> 1 | AQ68: =IF(AR68="","",AR68*$E68) | AS68: =AR68+AP68 -> 1 | AT68: =IF(AU68="","",AU68*$E68) | AV68: =AU68+AS68 -> 1 | AW68: =IF(AX68="","",AX68*$E68) | AY68: =AX68+AV68 -> 1 | AZ68: =IF(BA68="","",BA68*$E68) | BB68: =BA68+AY68 -> 1 | BC68: =IF(BD68="","",BD68*$E68) | BE68: =BD68+BB68 -> 1 | BF68: =IF(BG68="","",BG68*$E68) | BH68: =BG68+BE68 -> 1 | BI68: =IF(BJ68="","",BJ68*$E68) | BK68: =BJ68+BH68 -> 1 | BL68: =IF(BM68="","",BM68*$E68) | BN68: =BM68+BK68 -> 1 | BO68: =IF(BP68="","",BP68*$E68) | BQ68: =BP68+BN68 -> 1 | BR68: =IF(BS68="","",BS68*$E68) | BT68: =BS68+BQ68 -> 1 | BU68: =IF(BV68="","",BV68*$E68) | BW68: =BV68+BT68 -> 1 | BX68: =IF(BY68="","",BY68*$E68) | BZ68: =BY68+BW68 -> 1 | CA68: =IF(CB68="","",CB68*$E68) | CC68: =CB68+BZ68 -> 1 | CD68: =IF(CE68="","",CE68*$E68) | CF68: =CE68+CC68 -> 1 | CG68: =IF(CH68="","",CH68*$E68) | CI68: =CH68+CF68 -> 1 | CJ68: =IF(CK68="","",CK68*$E68) | CL68: =CK68+CI68 -> 1 | CM68: =IF(CN68="","",CN68*$E68) | CO68: =CN68+CL68 -> 1 | CP68: =IF(CQ68="","",CQ68*$E68) | CR68: =CQ68+CO68 -> 1 | CS68: =IF(CT68="","",CT68*$E68) | CU68: =CT68+CR68 -> 1 | CV68: =IF(CW68="","",CW68*$E68) | CX68: =CW68+CU68 -> 1 | CY68: =IF(CZ68="","",CZ68*$E68) | DA68: =CZ68+CX68 -> 1 | DB68: =IF(DC68="","",DC68*$E68) | DD68: =DC68+DA68 -> 1 | DE68: =IF(DF68="","",DF68*$E68) | DG68: =DF68+DD68 -> 1 | DH68: =IF(DI68="","",DI68*$E68) | DJ68: =DI68+DG68 -> 1
A69: 3 | B69: 3.2.3 | C69: BLOCOS AUXILIARES ( CISTERNA / SUBESTAÇÃO / LIXEIRA / GERADOR ) | E69: =VLOOKUP(B69,'[49]PLANILHA ORCAMENTARIA'!A:G,7,0) -> 48910.395 | G69: =IF(H69="","",H69*E69) | I69: =H69 -> 0 | J69: =IF(K69="","",K69*H69) | L69: =K69 -> 0 | M69: =IF(N69="","",N69*K69) | O69: =N69 -> 0 | P69: =IF(Q69="","",Q69*N69) | R69: =Q69 -> 0 | S69: =IF(T69="","",T69*Q69) | U69: =T69 -> 0 | V69: =IF(W69="","",W69*T69) | X69: =W69 -> 0 | Y69: =IF(Z69="","",Z69*W69) | AA69: =Z69 -> 0 | AB69: =IF(AC69="","",AC69*Z69) | AD69: =AC69 -> 0 | AE69: =IF(AF69="","",AF69*AC69) | AG69: =AF69 -> 0 | AH69: =IF(AI69="","",AI69*AF69) | AJ69: =AI69 -> 0 | AK69: =IF(AL69="","",AL69*AI69) | AM69: =AL69 -> 0 | AN69: =IF(AO69="","",AO69*AL69) | AP69: =AO69 -> 0 | AQ69: =IF(AR69="","",AR69*AO69) | AS69: =AR69 -> 0 | AT69: =IF(AU69="","",AU69*AR69) | AV69: =AU69 -> 0 | AW69: =IF(AX69="","",AX69*AU69) | AY69: =AX69 -> 0 | AZ69: =IF(BA69="","",BA69*AX69) | BB69: =BA69 -> 0 | BC69: =IF(BD69="","",BD69*BA69) | BE69: =BD69 -> 0 | BF69: =IF(BG69="","",BG69*BD69) | BH69: =BG69 -> 0 | BI69: =IF(BJ69="","",BJ69*BG69) | BK69: =BJ69 -> 0 | BL69: =IF(BM69="","",BM69*BJ69) | BN69: =BM69 -> 0 | BO69: =IF(BP69="","",BP69*BM69) | BQ69: =BP69 -> 0 | BR69: =IF(BS69="","",BS69*BP69) | BT69: =BS69 -> 0 | BU69: =IF(BV69="","",BV69*BS69) | BW69: =BV69 -> 0 | BX69: =IF(BY69="","",BY69*BV69) | BZ69: =BY69 -> 0 | CA69: =IF(CB69="","",CB69*BY69) | CC69: =CB69 -> 0 | CD69: =IF(CE69="","",CE69*CB69) | CF69: =CE69 -> 0 | CG69: =IF(CH69="","",CH69*CE69) | CI69: =CH69 -> 0 | CJ69: =IF(CK69="","",CK69*CH69) | CL69: =CK69 -> 0 | CM69: =IF(CN69="","",CN69*CK69) | CO69: =CN69 -> 0 | CP69: =IF(CQ69="","",CQ69*CN69) | CR69: =CQ69 -> 0 | CS69: =IF(CT69="","",CT69*CQ69) | CU69: =CT69 -> 0 | CV69: =IF(CW69="","",CW69*CT69) | CX69: =CW69 -> 0 | CY69: =IF(CZ69="","",CZ69*CW69) | DA69: =CZ69 -> 0 | DB69: =IF(DC69="","",DC69*CZ69) | DD69: =DC69 -> 0 | DE69: =IF(DF69="","",DF69*DC69) | DG69: =DF69 -> 0 | DH69: =IF(DI69="","",DI69*DF69) | DJ69: =DI69 -> 0
A70: 3 | B70: 3.2.3.1 | C70: PILARES | E70: =VLOOKUP(B70,'[49]PLANILHA ORCAMENTARIA'!A:G,7,0) -> 13882.705 | G70: =IF(H70="","",H70*$E70) | I70: =H70 -> 0 | J70: =IF(K70="","",K70*$E70) | L70: =K70+I70 -> 0 | M70: =IF(N70="","",N70*$E70) | O70: =N70+L70 -> 0 | P70: =IF(Q70="","",Q70*$E70) | R70: =Q70+O70 -> 0 | S70: =IF(T70="","",T70*$E70) | U70: =T70+R70 -> 0 | V70: =IF(W70="","",W70*$E70) | X70: =W70+U70 -> 0 | Y70: =IF(Z70="","",Z70*$E70) | AA70: =Z70+X70 -> 0 | AB70: =IF(AC70="","",AC70*$E70) | AD70: =AC70+AA70 -> 0 | AE70: =IF(AF70="","",AF70*$E70) | AG70: =AF70+AD70 -> 0 | AH70: =IF(AI70="","",AI70*$E70) | AJ70: =AI70+AG70 -> 0 | AK70: =IF(AL70="","",AL70*$E70) | AM70: =AL70+AJ70 -> 0 | AN70: =IF(AO70="","",AO70*$E70) | AP70: =AO70+AM70 -> 0 | AQ70: =IF(AR70="","",AR70*$E70) | AS70: =AR70+AP70 -> 0 | AT70: =IF(AU70="","",AU70*$E70) | AV70: =AU70+AS70 -> 0 | AW70: =IF(AX70="","",AX70*$E70) | AY70: =AX70+AV70 -> 0 | AZ70: =IF(BA70="","",BA70*$E70) | BB70: =BA70+AY70 -> 0 | BC70: =IF(BD70="","",BD70*$E70) | BE70: =BD70+BB70 -> 0 | BF70: =IF(BG70="","",BG70*$E70) | BH70: =BG70+BE70 -> 0 | BI70: =IF(BJ70="","",BJ70*$E70) | BK70: =BJ70+BH70 -> 0 | BL70: =IF(BM70="","",BM70*$E70) | BN70: =BM70+BK70 -> 0 | BO70: =IF(BP70="","",BP70*$E70) | BQ70: =BP70+BN70 -> 0 | BR70: =IF(BS70="","",BS70*$E70) | BT70: =BS70+BQ70 -> 0 | BU70: =IF(BV70="","",BV70*$E70) | BW70: =BV70+BT70 -> 0 | BX70: =IF(BY70="","",BY70*$E70) | BZ70: =BY70+BW70 -> 0 | CA70: =IF(CB70="","",CB70*$E70) | CC70: =CB70+BZ70 -> 0 | CD70: =IF(CE70="","",CE70*$E70) | CF70: =CE70+CC70 -> 0 | CG70: =IF(CH70="","",CH70*$E70) | CI70: =CH70+CF70 -> 0 | CJ70: =IF(CK70="","",CK70*$E70) | CL70: =CK70+CI70 -> 0 | CM70: =IF(CN70="","",CN70*$E70) | CO70: =CN70+CL70 -> 0 | CP70: =IF(CQ70="","",CQ70*$E70) | CR70: =CQ70+CO70 -> 0 | CS70: =IF(CT70="","",CT70*$E70) | CU70: =CT70+CR70 -> 0 | CV70: =IF(CW70="","",CW70*$E70) | CX70: =CW70+CU70 -> 0 | CY70: =IF(CZ70="","",CZ70*$E70) | DA70: =CZ70+CX70 -> 0 | DB70: =IF(DC70="","",DC70*$E70) | DD70: =DC70+DA70 -> 0 | DE70: =IF(DF70="","",DF70*$E70) | DG70: =DF70+DD70 -> 0 | DH70: =IF(DI70="","",DI70*$E70) | DJ70: =DI70+DG70 -> 0
A71: 3 | B71: 3.2.3.2 | C71: LAJE COM ESCORAMENTO E CIMBRAMENTO - INCLUSO VIGAS | E71: =VLOOKUP(B71,'[49]PLANILHA ORCAMENTARIA'!A:G,7,0) -> 35027.689 | G71: =IF(H71="","",H71*$E71) | I71: =H71 -> 0 | J71: =IF(K71="","",K71*$E71) | L71: =K71+I71 -> 0 | M71: =IF(N71="","",N71*$E71) | O71: =N71+L71 -> 0 | P71: =IF(Q71="","",Q71*$E71) | R71: =Q71+O71 -> 0 | S71: =IF(T71="","",T71*$E71) | U71: =T71+R71 -> 0 | V71: =IF(W71="","",W71*$E71) | X71: =W71+U71 -> 0 | Y71: =IF(Z71="","",Z71*$E71) | AA71: =Z71+X71 -> 0 | AB71: =IF(AC71="","",AC71*$E71) | AD71: =AC71+AA71 -> 0 | AE71: =IF(AF71="","",AF71*$E71) | AG71: =AF71+AD71 -> 0 | AH71: =IF(AI71="","",AI71*$E71) | AJ71: =AI71+AG71 -> 0 | AK71: =IF(AL71="","",AL71*$E71) | AM71: =AL71+AJ71 -> 0 | AN71: =IF(AO71="","",AO71*$E71) | AP71: =AO71+AM71 -> 0 | AQ71: =IF(AR71="","",AR71*$E71) | AS71: =AR71+AP71 -> 0 | AT71: =IF(AU71="","",AU71*$E71) | AV71: =AU71+AS71 -> 0 | AW71: =IF(AX71="","",AX71*$E71) | AY71: =AX71+AV71 -> 0 | AZ71: =IF(BA71="","",BA71*$E71) | BB71: =BA71+AY71 -> 0 | BC71: =IF(BD71="","",BD71*$E71) | BE71: =BD71+BB71 -> 0 | BF71: =IF(BG71="","",BG71*$E71) | BH71: =BG71+BE71 -> 0 | BI71: =IF(BJ71="","",BJ71*$E71) | BK71: =BJ71+BH71 -> 0 | BL71: =IF(BM71="","",BM71*$E71) | BN71: =BM71+BK71 -> 0 | BO71: =IF(BP71="","",BP71*$E71) | BQ71: =BP71+BN71 -> 0 | BR71: =IF(BS71="","",BS71*$E71) | BT71: =BS71+BQ71 -> 0 | BU71: =IF(BV71="","",BV71*$E71) | BW71: =BV71+BT71 -> 0 | BX71: =IF(BY71="","",BY71*$E71) | BZ71: =BY71+BW71 -> 0 | CA71: =IF(CB71="","",CB71*$E71) | CC71: =CB71+BZ71 -> 0 | CD71: =IF(CE71="","",CE71*$E71) | CF71: =CE71+CC71 -> 0 | CG71: =IF(CH71="","",CH71*$E71) | CI71: =CH71+CF71 -> 0 | CJ71: =IF(CK71="","",CK71*$E71) | CL71: =CK71+CI71 -> 0 | CM71: =IF(CN71="","",CN71*$E71) | CO71: =CN71+CL71 -> 0 | CP71: =IF(CQ71="","",CQ71*$E71) | CR71: =CQ71+CO71 -> 0 | CS71: =IF(CT71="","",CT71*$E71) | CU71: =CT71+CR71 -> 0 | CV71: =IF(CW71="","",CW71*$E71) | CX71: =CW71+CU71 -> 0 | CY71: =IF(CZ71="","",CZ71*$E71) | DA71: =CZ71+CX71 -> 0 | DB71: =IF(DC71="","",DC71*$E71) | DD71: =DC71+DA71 -> 0 | DE71: =IF(DF71="","",DF71*$E71) | DG71: =DF71+DD71 -> 0 | DH71: =IF(DI71="","",DI71*$E71) | DJ71: =DI71+DG71 -> 0
A72: =LEFT(B72,1) -> 4 | B72: 4 | C72: ARQUITETURA E ELEMENTOS URBANISMO | E72: =VLOOKUP(B72,'[49]PLANILHA ORCAMENTARIA'!A:G,7,0) -> 9606333.9 | G72: =SUMIF($A$73:$A$269,$B$72,G73:G269) -> 0 | H72: =IF(G72="","",G72/$E72) -> 0 | I72: =H72 -> 0 | J72: =SUMIF($A$73:$A$269,$B$72,J73:J269) -> 0 | K72: =IF(J72="","",J72/$E72) -> 0 | L72: =K72+I72 -> 0 | M72: =SUMIF($A$73:$A$269,$B$72,M73:M269) -> 0 | N72: =IF(M72="","",M72/$E72) -> 0 | O72: =N72+L72 -> 0 | P72: =SUMIF($A$73:$A$269,$B$72,P73:P269) -> 0 | Q72: =IF(P72="","",P72/$E72) -> 0 | R72: =Q72+O72 -> 0 | S72: =SUMIF($A$73:$A$269,$B$72,S73:S269) -> 0 | T72: =IF(S72="","",S72/$E72) -> 0 | U72: =T72+R72 -> 0 | V72: =SUMIF($A$73:$A$269,$B$72,V73:V269) -> 0 | W72: =IF(V72="","",V72/$E72) -> 0 | X72: =W72+U72 -> 0 | Y72: =SUMIF($A$73:$A$269,$B$72,Y73:Y269) -> 0 | Z72: =IF(Y72="","",Y72/$E72) -> 0 | AA72: =Z72+X72 -> 0 | AB72: =SUMIF($A$73:$A$269,$B$72,AB73:AB269) -> 0 | AC72: =IF(AB72="","",AB72/$E72) -> 0 | AD72: =AC72+AA72 -> 0 | AE72: =SUMIF($A$73:$A$269,$B$72,AE73:AE269) -> 0 | AF72: =IF(AE72="","",AE72/$E72) -> 0 | AG72: =AF72+AD72 -> 0 | AH72: =SUMIF($A$73:$A$269,$B$72,AH73:AH269) -> 0 | AI72: =IF(AH72="","",AH72/$E72) -> 0 | AJ72: =AI72+AG72 -> 0 | AK72: =SUMIF($A$73:$A$269,$B$72,AK73:AK269) -> 0 | AL72: =IF(AK72="","",AK72/$E72) -> 0 | AM72: =AL72+AJ72 -> 0 | AN72: =SUMIF($A$73:$A$269,$B$72,AN73:AN269) -> 0 | AO72: =IF(AN72="","",AN72/$E72) -> 0 | AP72: =AO72+AM72 -> 0 | AQ72: =SUMIF($A$73:$A$269,$B$72,AQ73:AQ269) -> 0 | AR72: =IF(AQ72="","",AQ72/$E72) -> 0 | AS72: =AR72+AP72 -> 0 | AT72: =SUMIF($A$73:$A$269,$B$72,AT73:AT269) -> 0 | AU72: =IF(AT72="","",AT72/$E72) -> 0 | AV72: =AU72+AS72 -> 0 | AW72: =SUMIF($A$73:$A$269,$B$72,AW73:AW269) -> 0 | AX72: =IF(AW72="","",AW72/$E72) -> 0 | AY72: =AX72+AV72 -> 0 | AZ72: =SUMIF($A$73:$A$269,$B$72,AZ73:AZ269) -> 0 | BA72: =IF(AZ72="","",AZ72/$E72) -> 0 | BB72: =BA72+AY72 -> 0 | BC72: =SUMIF($A$73:$A$269,$B$72,BC73:BC269) -> 0 | BD72: =IF(BC72="","",BC72/$E72) -> 0 | BE72: =BD72+BB72 -> 0 | BF72: =SUMIF($A$73:$A$269,$B$72,BF73:BF269) -> 0 | BG72: =IF(BF72="","",BF72/$E72) -> 0 | BH72: =BG72+BE72 -> 0 | BI72: =SUMIF($A$73:$A$269,$B$72,BI73:BI269) -> 0 | BJ72: =IF(BI72="","",BI72/$E72) -> 0 | BK72: =BJ72+BH72 -> 0 | BL72: =SUMIF($A$73:$A$269,$B$72,BL73:BL269) -> 0 | BM72: =IF(BL72="","",BL72/$E72) -> 0 | BN72: =BM72+BK72 -> 0 | BO72: =SUMIF($A$73:$A$269,$B$72,BO73:BO269) -> 0 | BP72: =IF(BO72="","",BO72/$E72) -> 0 | BQ72: =BP72+BN72 -> 0 | BR72: =SUMIF($A$73:$A$269,$B$72,BR73:BR269) -> 0 | BS72: =IF(BR72="","",BR72/$E72) -> 0 | BT72: =BS72+BQ72 -> 0 | BU72: =SUMIF($A$73:$A$269,$B$72,BU73:BU269) -> 0 | BV72: =IF(BU72="","",BU72/$E72) -> 0 | BW72: =BV72+BT72 -> 0 | BX72: =SUMIF($A$73:$A$269,$B$72,BX73:BX269) -> 0 | BY72: =IF(BX72="","",BX72/$E72) -> 0 | BZ72: =BY72+BW72 -> 0 | CA72: =SUMIF($A$73:$A$269,$B$72,CA73:CA269) -> 0 | CB72: =IF(CA72="","",CA72/$E72) -> 0 | CC72: =CB72+BZ72 -> 0 | CD72: =SUMIF($A$73:$A$269,$B$72,CD73:CD269) -> 0 | CE72: =IF(CD72="","",CD72/$E72) -> 0 | CF72: =CE72+CC72 -> 0 | CG72: =SUMIF($A$73:$A$269,$B$72,CG73:CG269) -> 0 | CH72: =IF(CG72="","",CG72/$E72) -> 0 | CI72: =CH72+CF72 -> 0 | CJ72: =SUMIF($A$73:$A$269,$B$72,CJ73:CJ269) -> 0 | CK72: =IF(CJ72="","",CJ72/$E72) -> 0 | CL72: =CK72+CI72 -> 0 | CM72: =SUMIF($A$73:$A$269,$B$72,CM73:CM269) -> 0 | CN72: =IF(CM72="","",CM72/$E72) -> 0 | CO72: =CN72+CL72 -> 0 | CP72: =SUMIF($A$73:$A$269,$B$72,CP73:CP269) -> 0 | CQ72: =IF(CP72="","",CP72/$E72) -> 0 | CR72: =CQ72+CO72 -> 0 | CS72: =SUMIF($A$73:$A$269,$B$72,CS73:CS269) -> 0 | CT72: =IF(CS72="","",CS72/$E72) -> 0 | CU72: =CT72+CR72 -> 0 | CV72: =SUMIF($A$73:$A$269,$B$72,CV73:CV269) -> 0 | CW72: =IF(CV72="","",CV72/$E72) -> 0 | CX72: =CW72+CU72 -> 0 | CY72: =SUMIF($A$73:$A$269,$B$72,CY73:CY269) -> 0 | CZ72: =IF(CY72="","",CY72/$E72) -> 0 | DA72: =CZ72+CX72 -> 0 | DB72: =SUMIF($A$73:$A$269,$B$72,DB73:DB269) -> 0 | DC72: =IF(DB72="","",DB72/$E72) -> 0 | DD72: =DC72+DA72 -> 0 | DE72: =SUMIF($A$73:$A$269,$B$72,DE73:DE269) -> 0 | DF72: =IF(DE72="","",DE72/$E72) -> 0 | DG72: =DF72+DD72 -> 0 | DH72: =SUMIF($A$73:$A$269,$B$72,DH73:DH269) -> 0 | DI72: =IF(DH72="","",DH72/$E72) -> 0 | DJ72: =DI72+DG72 -> 0 | DK72: =G72+J72+M72+P72+S72+V72+Y72+AB72+AE72+AH72+AK72+AN72+AQ72+AT72+AW72+AZ72+BC72+BF72+BI72+BL72+BO72+BR72+BU72+BX72+CA72+CD72+CG72+CJ72+CM72+CP72+CS72+CV72+CY72+DB72+DE72+DH72 -> 0 | DL72: =E72-DK72 -> 9606333.9 | DM72: =DK72/E72 -> 0
A73: =LEFT(B73,1) -> 4 | B73: 4.1 | C73: BLOCO PRINCIPAL | E73: =VLOOKUP(B73,'[49]PLANILHA ORCAMENTARIA'!A:G,7,0) -> 8034578.2 | G73: =IF(H73="","",H73*E73) | I73: =H73 -> 0 | J73: =IF(K73="","",K73*H73) | L73: =K73 -> 0 | M73: =IF(N73="","",N73*K73) | O73: =N73 -> 0 | P73: =IF(Q73="","",Q73*N73) | R73: =Q73 -> 0 | S73: =IF(T73="","",T73*Q73) | U73: =T73 -> 0 | V73: =IF(W73="","",W73*T73) | X73: =W73 -> 0 | Y73: =IF(Z73="","",Z73*W73) | AA73: =Z73 -> 0 | AB73: =IF(AC73="","",AC73*Z73) | AD73: =AC73 -> 0 | AE73: =IF(AF73="","",AF73*AC73) | AG73: =AF73 -> 0 | AH73: =IF(AI73="","",AI73*AF73) | AJ73: =AI73 -> 0 | AK73: =IF(AL73="","",AL73*AI73) | AM73: =AL73 -> 0 | AN73: =IF(AO73="","",AO73*AL73) | AP73: =AO73 -> 0 | AQ73: =IF(AR73="","",AR73*AO73) | AS73: =AR73 -> 0 | AT73: =IF(AU73="","",AU73*AR73) | AV73: =AU73 -> 0 | AW73: =IF(AX73="","",AX73*AU73) | AY73: =AX73 -> 0 | AZ73: =IF(BA73="","",BA73*AX73) | BB73: =BA73 -> 0 | BC73: =IF(BD73="","",BD73*BA73) | BE73: =BD73 -> 0 | BF73: =IF(BG73="","",BG73*BD73) | BH73: =BG73 -> 0 | BI73: =IF(BJ73="","",BJ73*BG73) | BK73: =BJ73 -> 0 | BL73: =IF(BM73="","",BM73*BJ73) | BN73: =BM73 -> 0 | BO73: =IF(BP73="","",BP73*BM73) | BQ73: =BP73 -> 0 | BR73: =IF(BS73="","",BS73*BP73) | BT73: =BS73 -> 0 | BU73: =IF(BV73="","",BV73*BS73) | BW73: =BV73 -> 0 | BX73: =IF(BY73="","",BY73*BV73) | BZ73: =BY73 -> 0 | CA73: =IF(CB73="","",CB73*BY73) | CC73: =CB73 -> 0 | CD73: =IF(CE73="","",CE73*CB73) | CF73: =CE73 -> 0 | CG73: =IF(CH73="","",CH73*CE73) | CI73: =CH73 -> 0 | CJ73: =IF(CK73="","",CK73*CH73) | CL73: =CK73 -> 0 | CM73: =IF(CN73="","",CN73*CK73) | CO73: =CN73 -> 0 | CP73: =IF(CQ73="","",CQ73*CN73) | CR73: =CQ73 -> 0 | CS73: =IF(CT73="","",CT73*CQ73) | CU73: =CT73 -> 0 | CV73: =IF(CW73="","",CW73*CT73) | CX73: =CW73 -> 0 | CY73: =IF(CZ73="","",CZ73*CW73) | DA73: =CZ73 -> 0 | DB73: =IF(DC73="","",DC73*CZ73) | DD73: =DC73 -> 0 | DE73: =IF(DF73="","",DF73*DC73) | DG73: =DF73 -> 0 | DH73: =IF(DI73="","",DI73*DF73) | DJ73: =DI73 -> 0
A74: =LEFT(B74,1) -> 4 | B74: 4.1.1 | C74: PISOS - TÉRREO | E74: =VLOOKUP(B74,'[49]PLANILHA ORCAMENTARIA'!A:G,7,0) -> 1321041.4
A75: =LEFT(B75,1) -> 4 | B75: 4.1.1.1 | C75: =VLOOKUP(B75,'[49]PLANILHA ORCAMENTARIA'!A:B,2,0) -> RADIER - SETOR 1 | E75: =VLOOKUP(B75,'[49]PLANILHA ORCAMENTARIA'!A:G,7,0) -> 279155.87 | G75: =IF(H75="","",H75*$E75) | I75: =H75 -> 0 | J75: =IF(K75="","",K75*$E75) | L75: =K75+I75 -> 0 | M75: =IF(N75="","",N75*$E75) | O75: =N75+L75 -> 0 | P75: =IF(Q75="","",Q75*$E75) | R75: =Q75+O75 -> 0 | S75: =IF(T75="","",T75*$E75) | U75: =T75+R75 -> 0 | V75: =IF(W75="","",W75*$E75) | X75: =W75+U75 -> 0 | Y75: =IF(Z75="","",Z75*$E75) | AA75: =Z75+X75 -> 0 | AB75: =IF(AC75="","",AC75*$E75) | AD75: =AC75+AA75 -> 0 | AE75: =IF(AF75="","",AF75*$E75) | AG75: =AF75+AD75 -> 0 | AH75: =IF(AI75="","",AI75*$E75) | AJ75: =AI75+AG75 -> 0 | AK75: =IF(AL75="","",AL75*$E75) | AM75: =AL75+AJ75 -> 0 | AN75: =IF(AO75="","",AO75*$E75) | AP75: =AO75+AM75 -> 0 | AQ75: =IF(AR75="","",AR75*$E75) | AS75: =AR75+AP75 -> 0 | AT75: =IF(AU75="","",AU75*$E75) | AV75: =AU75+AS75 -> 0 | AW75: =IF(AX75="","",AX75*$E75) | AY75: =AX75+AV75 -> 0 | AZ75: =IF(BA75="","",BA75*$E75) | BB75: =BA75+AY75 -> 0 | BC75: =IF(BD75="","",BD75*$E75) | BE75: =BD75+BB75 -> 0 | BF75: =IF(BG75="","",BG75*$E75) | BH75: =BG75+BE75 -> 0 | BI75: =IF(BJ75="","",BJ75*$E75) | BK75: =BJ75+BH75 -> 0 | BL75: =IF(BM75="","",BM75*$E75) | BN75: =BM75+BK75 -> 0 | BO75: =IF(BP75="","",BP75*$E75) | BQ75: =BP75+BN75 -> 0 | BR75: =IF(BS75="","",BS75*$E75) | BT75: =BS75+BQ75 -> 0 | BU75: =IF(BV75="","",BV75*$E75) | BW75: =BV75+BT75 -> 0 | BX75: =IF(BY75="","",BY75*$E75) | BZ75: =BY75+BW75 -> 0 | CA75: =IF(CB75="","",CB75*$E75) | CC75: =CB75+BZ75 -> 0 | CD75: =IF(CE75="","",CE75*$E75) | CF75: =CE75+CC75 -> 0 | CG75: =IF(CH75="","",CH75*$E75) | CI75: =CH75+CF75 -> 0 | CJ75: =IF(CK75="","",CK75*$E75) | CL75: =CK75+CI75 -> 0 | CM75: =IF(CN75="","",CN75*$E75) | CO75: =CN75+CL75 -> 0 | CP75: =IF(CQ75="","",CQ75*$E75) | CR75: =CQ75+CO75 -> 0 | CS75: =IF(CT75="","",CT75*$E75) | CU75: =CT75+CR75 -> 0 | CV75: =IF(CW75="","",CW75*$E75) | CX75: =CW75+CU75 -> 0 | CY75: =IF(CZ75="","",CZ75*$E75) | DA75: =CZ75+CX75 -> 0 | DB75: =IF(DC75="","",DC75*$E75) | DD75: =DC75+DA75 -> 0 | DE75: =IF(DF75="","",DF75*$E75) | DG75: =DF75+DD75 -> 0 | DH75: =IF(DI75="","",DI75*$E75) | DJ75: =DI75+DG75 -> 0
A76: =LEFT(B76,1) -> 4 | B76: 4.1.1.2 | C76: =VLOOKUP(B76,'[49]PLANILHA ORCAMENTARIA'!A:B,2,0) -> RADIER - SETOR 3 | E76: =VLOOKUP(B76,'[49]PLANILHA ORCAMENTARIA'!A:G,7,0) -> 422377.71 | G76: =IF(H76="","",H76*$E76) | I76: =H76 -> 0 | J76: =IF(K76="","",K76*$E76) | L76: =K76+I76 -> 0 | M76: =IF(N76="","",N76*$E76) | O76: =N76+L76 -> 0 | P76: =IF(Q76="","",Q76*$E76) | R76: =Q76+O76 -> 0 | S76: =IF(T76="","",T76*$E76) | U76: =T76+R76 -> 0 | V76: =IF(W76="","",W76*$E76) | X76: =W76+U76 -> 0 | Y76: =IF(Z76="","",Z76*$E76) | AA76: =Z76+X76 -> 0 | AB76: =IF(AC76="","",AC76*$E76) | AD76: =AC76+AA76 -> 0 | AE76: =IF(AF76="","",AF76*$E76) | AG76: =AF76+AD76 -> 0 | AH76: =IF(AI76="","",AI76*$E76) | AJ76: =AI76+AG76 -> 0 | AK76: =IF(AL76="","",AL76*$E76) | AM76: =AL76+AJ76 -> 0 | AN76: =IF(AO76="","",AO76*$E76) | AP76: =AO76+AM76 -> 0 | AQ76: =IF(AR76="","",AR76*$E76) | AS76: =AR76+AP76 -> 0 | AT76: =IF(AU76="","",AU76*$E76) | AV76: =AU76+AS76 -> 0 | AW76: =IF(AX76="","",AX76*$E76) | AY76: =AX76+AV76 -> 0 | AZ76: =IF(BA76="","",BA76*$E76) | BB76: =BA76+AY76 -> 0 | BC76: =IF(BD76="","",BD76*$E76) | BE76: =BD76+BB76 -> 0 | BF76: =IF(BG76="","",BG76*$E76) | BH76: =BG76+BE76 -> 0 | BI76: =IF(BJ76="","",BJ76*$E76) | BK76: =BJ76+BH76 -> 0 | BL76: =IF(BM76="","",BM76*$E76) | BN76: =BM76+BK76 -> 0 | BO76: =IF(BP76="","",BP76*$E76) | BQ76: =BP76+BN76 -> 0 | BR76: =IF(BS76="","",BS76*$E76) | BT76: =BS76+BQ76 -> 0 | BU76: =IF(BV76="","",BV76*$E76) | BW76: =BV76+BT76 -> 0 | BX76: =IF(BY76="","",BY76*$E76) | BZ76: =BY76+BW76 -> 0 | CA76: =IF(CB76="","",CB76*$E76) | CC76: =CB76+BZ76 -> 0 | CD76: =IF(CE76="","",CE76*$E76) | CF76: =CE76+CC76 -> 0 | CG76: =IF(CH76="","",CH76*$E76) | CI76: =CH76+CF76 -> 0 | CJ76: =IF(CK76="","",CK76*$E76) | CL76: =CK76+CI76 -> 0 | CM76: =IF(CN76="","",CN76*$E76) | CO76: =CN76+CL76 -> 0 | CP76: =IF(CQ76="","",CQ76*$E76) | CR76: =CQ76+CO76 -> 0 | CS76: =IF(CT76="","",CT76*$E76) | CU76: =CT76+CR76 -> 0 | CV76: =IF(CW76="","",CW76*$E76) | CX76: =CW76+CU76 -> 0 | CY76: =IF(CZ76="","",CZ76*$E76) | DA76: =CZ76+CX76 -> 0 | DB76: =IF(DC76="","",DC76*$E76) | DD76: =DC76+DA76 -> 0 | DE76: =IF(DF76="","",DF76*$E76) | DG76: =DF76+DD76 -> 0 | DH76: =IF(DI76="","",DI76*$E76) | DJ76: =DI76+DG76 -> 0
A77: =LEFT(B77,1) -> 4 | B77: 4.1.1.3 | C77: =VLOOKUP(B77,'[49]PLANILHA ORCAMENTARIA'!A:B,2,0) -> CONTRAPISO - SETOR 1 | E77: =VLOOKUP(B77,'[49]PLANILHA ORCAMENTARIA'!A:G,7,0) -> 123343.89 | G77: =IF(H77="","",H77*$E77) | I77: =H77 -> 0 | J77: =IF(K77="","",K77*$E77) | L77: =K77+I77 -> 0 | M77: =IF(N77="","",N77*$E77) | O77: =N77+L77 -> 0 | P77: =IF(Q77="","",Q77*$E77) | R77: =Q77+O77 -> 0 | S77: =IF(T77="","",T77*$E77) | U77: =T77+R77 -> 0 | V77: =IF(W77="","",W77*$E77) | X77: =W77+U77 -> 0 | Y77: =IF(Z77="","",Z77*$E77) | AA77: =Z77+X77 -> 0 | AB77: =IF(AC77="","",AC77*$E77) | AD77: =AC77+AA77 -> 0 | AE77: =IF(AF77="","",AF77*$E77) | AG77: =AF77+AD77 -> 0 | AH77: =IF(AI77="","",AI77*$E77) | AJ77: =AI77+AG77 -> 0 | AK77: =IF(AL77="","",AL77*$E77) | AM77: =AL77+AJ77 -> 0 | AN77: =IF(AO77="","",AO77*$E77) | AP77: =AO77+AM77 -> 0 | AQ77: =IF(AR77="","",AR77*$E77) | AS77: =AR77+AP77 -> 0 | AT77: =IF(AU77="","",AU77*$E77) | AV77: =AU77+AS77 -> 0 | AW77: =IF(AX77="","",AX77*$E77) | AY77: =AX77+AV77 -> 0 | AZ77: =IF(BA77="","",BA77*$E77) | BB77: =BA77+AY77 -> 0 | BC77: =IF(BD77="","",BD77*$E77) | BE77: =BD77+BB77 -> 0 | BF77: =IF(BG77="","",BG77*$E77) | BH77: =BG77+BE77 -> 0 | BI77: =IF(BJ77="","",BJ77*$E77) | BK77: =BJ77+BH77 -> 0 | BL77: =IF(BM77="","",BM77*$E77) | BN77: =BM77+BK77 -> 0 | BO77: =IF(BP77="","",BP77*$E77) | BQ77: =BP77+BN77 -> 0 | BR77: =IF(BS77="","",BS77*$E77) | BT77: =BS77+BQ77 -> 0 | BU77: =IF(BV77="","",BV77*$E77) | BW77: =BV77+BT77 -> 0 | BX77: =IF(BY77="","",BY77*$E77) | BZ77: =BY77+BW77 -> 0 | CA77: =IF(CB77="","",CB77*$E77) | CC77: =CB77+BZ77 -> 0 | CD77: =IF(CE77="","",CE77*$E77) | CF77: =CE77+CC77 -> 0 | CG77: =IF(CH77="","",CH77*$E77) | CI77: =CH77+CF77 -> 0 | CJ77: =IF(CK77="","",CK77*$E77) | CL77: =CK77+CI77 -> 0 | CM77: =IF(CN77="","",CN77*$E77) | CO77: =CN77+CL77 -> 0 | CP77: =IF(CQ77="","",CQ77*$E77) | CR77: =CQ77+CO77 -> 0 | CS77: =IF(CT77="","",CT77*$E77) | CU77: =CT77+CR77 -> 0 | CV77: =IF(CW77="","",CW77*$E77) | CX77: =CW77+CU77 -> 0 | CY77: =IF(CZ77="","",CZ77*$E77) | DA77: =CZ77+CX77 -> 0 | DB77: =IF(DC77="","",DC77*$E77) | DD77: =DC77+DA77 -> 0 | DE77: =IF(DF77="","",DF77*$E77) | DG77: =DF77+DD77 -> 0 | DH77: =IF(DI77="","",DI77*$E77) | DJ77: =DI77+DG77 -> 0
A78: =LEFT(B78,1) -> 4 | B78: 4.1.1.4 | C78: =VLOOKUP(B78,'[49]PLANILHA ORCAMENTARIA'!A:B,2,0) -> CONTRAPISO - SETOR 3 | E78: =VLOOKUP(B78,'[49]PLANILHA ORCAMENTARIA'!A:G,7,0) -> 186635.13 | G78: =IF(H78="","",H78*$E78) | I78: =H78 -> 0 | J78: =IF(K78="","",K78*$E78) | L78: =K78+I78 -> 0 | M78: =IF(N78="","",N78*$E78) | O78: =N78+L78 -> 0 | P78: =IF(Q78="","",Q78*$E78) | R78: =Q78+O78 -> 0 | S78: =IF(T78="","",T78*$E78) | U78: =T78+R78 -> 0 | V78: =IF(W78="","",W78*$E78) | X78: =W78+U78 -> 0 | Y78: =IF(Z78="","",Z78*$E78) | AA78: =Z78+X78 -> 0 | AB78: =IF(AC78="","",AC78*$E78) | AD78: =AC78+AA78 -> 0 | AE78: =IF(AF78="","",AF78*$E78) | AG78: =AF78+AD78 -> 0 | AH78: =IF(AI78="","",AI78*$E78) | AJ78: =AI78+AG78 -> 0 | AK78: =IF(AL78="","",AL78*$E78) | AM78: =AL78+AJ78 -> 0 | AN78: =IF(AO78="","",AO78*$E78) | AP78: =AO78+AM78 -> 0 | AQ78: =IF(AR78="","",AR78*$E78) | AS78: =AR78+AP78 -> 0 | AT78: =IF(AU78="","",AU78*$E78) | AV78: =AU78+AS78 -> 0 | AW78: =IF(AX78="","",AX78*$E78) | AY78: =AX78+AV78 -> 0 | AZ78: =IF(BA78="","",BA78*$E78) | BB78: =BA78+AY78 -> 0 | BC78: =IF(BD78="","",BD78*$E78) | BE78: =BD78+BB78 -> 0 | BF78: =IF(BG78="","",BG78*$E78) | BH78: =BG78+BE78 -> 0 | BI78: =IF(BJ78="","",BJ78*$E78) | BK78: =BJ78+BH78 -> 0 | BL78: =IF(BM78="","",BM78*$E78) | BN78: =BM78+BK78 -> 0 | BO78: =IF(BP78="","",BP78*$E78) | BQ78: =BP78+BN78 -> 0 | BR78: =IF(BS78="","",BS78*$E78) | BT78: =BS78+BQ78 -> 0 | BU78: =IF(BV78="","",BV78*$E78) | BW78: =BV78+BT78 -> 0 | BX78: =IF(BY78="","",BY78*$E78) | BZ78: =BY78+BW78 -> 0 | CA78: =IF(CB78="","",CB78*$E78) | CC78: =CB78+BZ78 -> 0 | CD78: =IF(CE78="","",CE78*$E78) | CF78: =CE78+CC78 -> 0 | CG78: =IF(CH78="","",CH78*$E78) | CI78: =CH78+CF78 -> 0 | CJ78: =IF(CK78="","",CK78*$E78) | CL78: =CK78+CI78 -> 0 | CM78: =IF(CN78="","",CN78*$E78) | CO78: =CN78+CL78 -> 0 | CP78: =IF(CQ78="","",CQ78*$E78) | CR78: =CQ78+CO78 -> 0 | CS78: =IF(CT78="","",CT78*$E78) | CU78: =CT78+CR78 -> 0 | CV78: =IF(CW78="","",CW78*$E78) | CX78: =CW78+CU78 -> 0 | CY78: =IF(CZ78="","",CZ78*$E78) | DA78: =CZ78+CX78 -> 0 | DB78: =IF(DC78="","",DC78*$E78) | DD78: =DC78+DA78 -> 0 | DE78: =IF(DF78="","",DF78*$E78) | DG78: =DF78+DD78 -> 0 | DH78: =IF(DI78="","",DI78*$E78) | DJ78: =DI78+DG78 -> 0
A79: =LEFT(B79,1) -> 4 | B79: 4.1.1.5 | C79: =VLOOKUP(B79,'[49]PLANILHA ORCAMENTARIA'!A:B,2,0) -> PORCELANATO / REVESTIMENTO DE PISO - SETOR 1 | E79: =VLOOKUP(B79,'[49]PLANILHA ORCAMENTARIA'!A:G,7,0) -> 116180.63 | G79: =IF(H79="","",H79*$E79) | I79: =H79 -> 0 | J79: =IF(K79="","",K79*$E79) | L79: =K79+I79 -> 0 | M79: =IF(N79="","",N79*$E79) | O79: =N79+L79 -> 0 | P79: =IF(Q79="","",Q79*$E79) | R79: =Q79+O79 -> 0 | S79: =IF(T79="","",T79*$E79) | U79: =T79+R79 -> 0 | V79: =IF(W79="","",W79*$E79) | X79: =W79+U79 -> 0 | Y79: =IF(Z79="","",Z79*$E79) | AA79: =Z79+X79 -> 0 | AB79: =IF(AC79="","",AC79*$E79) | AD79: =AC79+AA79 -> 0 | AE79: =IF(AF79="","",AF79*$E79) | AG79: =AF79+AD79 -> 0 | AH79: =IF(AI79="","",AI79*$E79) | AJ79: =AI79+AG79 -> 0 | AK79: =IF(AL79="","",AL79*$E79) | AM79: =AL79+AJ79 -> 0 | AN79: =IF(AO79="","",AO79*$E79) | AP79: =AO79+AM79 -> 0 | AQ79: =IF(AR79="","",AR79*$E79) | AS79: =AR79+AP79 -> 0 | AT79: =IF(AU79="","",AU79*$E79) | AV79: =AU79+AS79 -> 0 | AW79: =IF(AX79="","",AX79*$E79) | AY79: =AX79+AV79 -> 0 | AZ79: =IF(BA79="","",BA79*$E79) | BB79: =BA79+AY79 -> 0 | BC79: =IF(BD79="","",BD79*$E79) | BE79: =BD79+BB79 -> 0 | BF79: =IF(BG79="","",BG79*$E79) | BH79: =BG79+BE79 -> 0 | BI79: =IF(BJ79="","",BJ79*$E79) | BK79: =BJ79+BH79 -> 0 | BL79: =IF(BM79="","",BM79*$E79) | BN79: =BM79+BK79 -> 0 | BO79: =IF(BP79="","",BP79*$E79) | BQ79: =BP79+BN79 -> 0 | BR79: =IF(BS79="","",BS79*$E79) | BT79: =BS79+BQ79 -> 0 | BU79: =IF(BV79="","",BV79*$E79) | BW79: =BV79+BT79 -> 0 | BX79: =IF(BY79="","",BY79*$E79) | BZ79: =BY79+BW79 -> 0 | CA79: =IF(CB79="","",CB79*$E79) | CC79: =CB79+BZ79 -> 0 | CD79: =IF(CE79="","",CE79*$E79) | CF79: =CE79+CC79 -> 0 | CG79: =IF(CH79="","",CH79*$E79) | CI79: =CH79+CF79 -> 0 | CJ79: =IF(CK79="","",CK79*$E79) | CL79: =CK79+CI79 -> 0 | CM79: =IF(CN79="","",CN79*$E79) | CO79: =CN79+CL79 -> 0 | CP79: =IF(CQ79="","",CQ79*$E79) | CR79: =CQ79+CO79 -> 0 | CS79: =IF(CT79="","",CT79*$E79) | CU79: =CT79+CR79 -> 0 | CV79: =IF(CW79="","",CW79*$E79) | CX79: =CW79+CU79 -> 0 | CY79: =IF(CZ79="","",CZ79*$E79) | DA79: =CZ79+CX79 -> 0 | DB79: =IF(DC79="","",DC79*$E79) | DD79: =DC79+DA79 -> 0 | DE79: =IF(DF79="","",DF79*$E79) | DG79: =DF79+DD79 -> 0 | DH79: =IF(DI79="","",DI79*$E79) | DJ79: =DI79+DG79 -> 0
A80: =LEFT(B80,1) -> 4 | B80: 4.1.1.6 | C80: =VLOOKUP(B80,'[49]PLANILHA ORCAMENTARIA'!A:B,2,0) -> PORCELANATO / REVESTIMENTO DE PISO - SETOR 3 | E80: =VLOOKUP(B80,'[49]PLANILHA ORCAMENTARIA'!A:G,7,0) -> 175796.2 | G80: =IF(H80="","",H80*$E80) | I80: =H80 -> 0 | J80: =IF(K80="","",K80*$E80) | L80: =K80+I80 -> 0 | M80: =IF(N80="","",N80*$E80) | O80: =N80+L80 -> 0 | P80: =IF(Q80="","",Q80*$E80) | R80: =Q80+O80 -> 0 | S80: =IF(T80="","",T80*$E80) | U80: =T80+R80 -> 0 | V80: =IF(W80="","",W80*$E80) | X80: =W80+U80 -> 0 | Y80: =IF(Z80="","",Z80*$E80) | AA80: =Z80+X80 -> 0 | AB80: =IF(AC80="","",AC80*$E80) | AD80: =AC80+AA80 -> 0 | AE80: =IF(AF80="","",AF80*$E80) | AG80: =AF80+AD80 -> 0 | AH80: =IF(AI80="","",AI80*$E80) | AJ80: =AI80+AG80 -> 0 | AK80: =IF(AL80="","",AL80*$E80) | AM80: =AL80+AJ80 -> 0 | AN80: =IF(AO80="","",AO80*$E80) | AP80: =AO80+AM80 -> 0 | AQ80: =IF(AR80="","",AR80*$E80) | AS80: =AR80+AP80 -> 0 | AT80: =IF(AU80="","",AU80*$E80) | AV80: =AU80+AS80 -> 0 | AW80: =IF(AX80="","",AX80*$E80) | AY80: =AX80+AV80 -> 0 | AZ80: =IF(BA80="","",BA80*$E80) | BB80: =BA80+AY80 -> 0 | BC80: =IF(BD80="","",BD80*$E80) | BE80: =BD80+BB80 -> 0 | BF80: =IF(BG80="","",BG80*$E80) | BH80: =BG80+BE80 -> 0 | BI80: =IF(BJ80="","",BJ80*$E80) | BK80: =BJ80+BH80 -> 0 | BL80: =IF(BM80="","",BM80*$E80) | BN80: =BM80+BK80 -> 0 | BO80: =IF(BP80="","",BP80*$E80) | BQ80: =BP80+BN80 -> 0 | BR80: =IF(BS80="","",BS80*$E80) | BT80: =BS80+BQ80 -> 0 | BU80: =IF(BV80="","",BV80*$E80) | BW80: =BV80+BT80 -> 0 | BX80: =IF(BY80="","",BY80*$E80) | BZ80: =BY80+BW80 -> 0 | CA80: =IF(CB80="","",CB80*$E80) | CC80: =CB80+BZ80 -> 0 | CD80: =IF(CE80="","",CE80*$E80) | CF80: =CE80+CC80 -> 0 | CG80: =IF(CH80="","",CH80*$E80) | CI80: =CH80+CF80 -> 0 | CJ80: =IF(CK80="","",CK80*$E80) | CL80: =CK80+CI80 -> 0 | CM80: =IF(CN80="","",CN80*$E80) | CO80: =CN80+CL80 -> 0 | CP80: =IF(CQ80="","",CQ80*$E80) | CR80: =CQ80+CO80 -> 0 | CS80: =IF(CT80="","",CT80*$E80) | CU80: =CT80+CR80 -> 0 | CV80: =IF(CW80="","",CW80*$E80) | CX80: =CW80+CU80 -> 0 | CY80: =IF(CZ80="","",CZ80*$E80) | DA80: =CZ80+CX80 -> 0 | DB80: =IF(DC80="","",DC80*$E80) | DD80: =DC80+DA80 -> 0 | DE80: =IF(DF80="","",DF80*$E80) | DG80: =DF80+DD80 -> 0 | DH80: =IF(DI80="","",DI80*$E80) | DJ80: =DI80+DG80 -> 0
A81: =LEFT(B81,1) -> 4 | B81: 4.1.1.7 | C81: =VLOOKUP(B81,'[49]PLANILHA ORCAMENTARIA'!A:B,2,0) -> REJUNTE / RODAPÉ / SOLEIRA | E81: =VLOOKUP(B81,'[49]PLANILHA ORCAMENTARIA'!A:G,7,0) -> 17551.99 | G81: =IF(H81="","",H81*$E81) | I81: =H81 -> 0 | J81: =IF(K81="","",K81*$E81) | L81: =K81+I81 -> 0 | M81: =IF(N81="","",N81*$E81) | O81: =N81+L81 -> 0 | P81: =IF(Q81="","",Q81*$E81) | R81: =Q81+O81 -> 0 | S81: =IF(T81="","",T81*$E81) | U81: =T81+R81 -> 0 | V81: =IF(W81="","",W81*$E81) | X81: =W81+U81 -> 0 | Y81: =IF(Z81="","",Z81*$E81) | AA81: =Z81+X81 -> 0 | AB81: =IF(AC81="","",AC81*$E81) | AD81: =AC81+AA81 -> 0 | AE81: =IF(AF81="","",AF81*$E81) | AG81: =AF81+AD81 -> 0 | AH81: =IF(AI81="","",AI81*$E81) | AJ81: =AI81+AG81 -> 0 | AK81: =IF(AL81="","",AL81*$E81) | AM81: =AL81+AJ81 -> 0 | AN81: =IF(AO81="","",AO81*$E81) | AP81: =AO81+AM81 -> 0 | AQ81: =IF(AR81="","",AR81*$E81) | AS81: =AR81+AP81 -> 0 | AT81: =IF(AU81="","",AU81*$E81) | AV81: =AU81+AS81 -> 0 | AW81: =IF(AX81="","",AX81*$E81) | AY81: =AX81+AV81 -> 0 | AZ81: =IF(BA81="","",BA81*$E81) | BB81: =BA81+AY81 -> 0 | BC81: =IF(BD81="","",BD81*$E81) | BE81: =BD81+BB81 -> 0 | BF81: =IF(BG81="","",BG81*$E81) | BH81: =BG81+BE81 -> 0 | BI81: =IF(BJ81="","",BJ81*$E81) | BK81: =BJ81+BH81 -> 0 | BL81: =IF(BM81="","",BM81*$E81) | BN81: =BM81+BK81 -> 0 | BO81: =IF(BP81="","",BP81*$E81) | BQ81: =BP81+BN81 -> 0 | BR81: =IF(BS81="","",BS81*$E81) | BT81: =BS81+BQ81 -> 0 | BU81: =IF(BV81="","",BV81*$E81) | BW81: =BV81+BT81 -> 0 | BX81: =IF(BY81="","",BY81*$E81) | BZ81: =BY81+BW81 -> 0 | CA81: =IF(CB81="","",CB81*$E81) | CC81: =CB81+BZ81 -> 0 | CD81: =IF(CE81="","",CE81*$E81) | CF81: =CE81+CC81 -> 0 | CG81: =IF(CH81="","",CH81*$E81) | CI81: =CH81+CF81 -> 0 | CJ81: =IF(CK81="","",CK81*$E81) | CL81: =CK81+CI81 -> 0 | CM81: =IF(CN81="","",CN81*$E81) | CO81: =CN81+CL81 -> 0 | CP81: =IF(CQ81="","",CQ81*$E81) | CR81: =CQ81+CO81 -> 0 | CS81: =IF(CT81="","",CT81*$E81) | CU81: =CT81+CR81 -> 0 | CV81: =IF(CW81="","",CW81*$E81) | CX81: =CW81+CU81 -> 0 | CY81: =IF(CZ81="","",CZ81*$E81) | DA81: =CZ81+CX81 -> 0 | DB81: =IF(DC81="","",DC81*$E81) | DD81: =DC81+DA81 -> 0 | DE81: =IF(DF81="","",DF81*$E81) | DG81: =DF81+DD81 -> 0 | DH81: =IF(DI81="","",DI81*$E81) | DJ81: =DI81+DG81 -> 0
A82: =LEFT(B82,1) -> 4 | B82: 4.1.2 | C82: PISOS - 1 ANDAR | E82: =VLOOKUP(B82,'[49]PLANILHA ORCAMENTARIA'!A:G,7,0) -> 786472.8
A83: =LEFT(B83,1) -> 4 | B83: 4.1.2.1 | C83: =VLOOKUP(B83,'[49]PLANILHA ORCAMENTARIA'!A:B,2,0) -> CONTRAPISO - SETOR 1 | E83: =VLOOKUP(B83,'[49]PLANILHA ORCAMENTARIA'!A:G,7,0) -> 204890.23 | G83: =IF(H83="","",H83*$E83) | I83: =H83 -> 0 | J83: =IF(K83="","",K83*$E83) | L83: =K83+I83 -> 0 | M83: =IF(N83="","",N83*$E83) | O83: =N83+L83 -> 0 | P83: =IF(Q83="","",Q83*$E83) | R83: =Q83+O83 -> 0 | S83: =IF(T83="","",T83*$E83) | U83: =T83+R83 -> 0 | V83: =IF(W83="","",W83*$E83) | X83: =W83+U83 -> 0 | Y83: =IF(Z83="","",Z83*$E83) | AA83: =Z83+X83 -> 0 | AB83: =IF(AC83="","",AC83*$E83) | AD83: =AC83+AA83 -> 0 | AE83: =IF(AF83="","",AF83*$E83) | AG83: =AF83+AD83 -> 0 | AH83: =IF(AI83="","",AI83*$E83) | AJ83: =AI83+AG83 -> 0 | AK83: =IF(AL83="","",AL83*$E83) | AM83: =AL83+AJ83 -> 0 | AN83: =IF(AO83="","",AO83*$E83) | AP83: =AO83+AM83 -> 0 | AQ83: =IF(AR83="","",AR83*$E83) | AS83: =AR83+AP83 -> 0 | AT83: =IF(AU83="","",AU83*$E83) | AV83: =AU83+AS83 -> 0 | AW83: =IF(AX83="","",AX83*$E83) | AY83: =AX83+AV83 -> 0 | AZ83: =IF(BA83="","",BA83*$E83) | BB83: =BA83+AY83 -> 0 | BC83: =IF(BD83="","",BD83*$E83) | BE83: =BD83+BB83 -> 0 | BF83: =IF(BG83="","",BG83*$E83) | BH83: =BG83+BE83 -> 0 | BI83: =IF(BJ83="","",BJ83*$E83) | BK83: =BJ83+BH83 -> 0 | BL83: =IF(BM83="","",BM83*$E83) | BN83: =BM83+BK83 -> 0 | BO83: =IF(BP83="","",BP83*$E83) | BQ83: =BP83+BN83 -> 0 | BR83: =IF(BS83="","",BS83*$E83) | BT83: =BS83+BQ83 -> 0 | BU83: =IF(BV83="","",BV83*$E83) | BW83: =BV83+BT83 -> 0 | BX83: =IF(BY83="","",BY83*$E83) | BZ83: =BY83+BW83 -> 0 | CA83: =IF(CB83="","",CB83*$E83) | CC83: =CB83+BZ83 -> 0 | CD83: =IF(CE83="","",CE83*$E83) | CF83: =CE83+CC83 -> 0 | CG83: =IF(CH83="","",CH83*$E83) | CI83: =CH83+CF83 -> 0 | CJ83: =IF(CK83="","",CK83*$E83) | CL83: =CK83+CI83 -> 0 | CM83: =IF(CN83="","",CN83*$E83) | CO83: =CN83+CL83 -> 0 | CP83: =IF(CQ83="","",CQ83*$E83) | CR83: =CQ83+CO83 -> 0 | CS83: =IF(CT83="","",CT83*$E83) | CU83: =CT83+CR83 -> 0 | CV83: =IF(CW83="","",CW83*$E83) | CX83: =CW83+CU83 -> 0 | CY83: =IF(CZ83="","",CZ83*$E83) | DA83: =CZ83+CX83 -> 0 | DB83: =IF(DC83="","",DC83*$E83) | DD83: =DC83+DA83 -> 0 | DE83: =IF(DF83="","",DF83*$E83) | DG83: =DF83+DD83 -> 0 | DH83: =IF(DI83="","",DI83*$E83) | DJ83: =DI83+DG83 -> 0
A84: =LEFT(B84,1) -> 4 | B84: 4.1.2.2 | C84: =VLOOKUP(B84,'[49]PLANILHA ORCAMENTARIA'!A:B,2,0) -> CONTRAPISO - SETOR 2 | E84: =VLOOKUP(B84,'[49]PLANILHA ORCAMENTARIA'!A:G,7,0) -> 102585.49 | G84: =IF(H84="","",H84*$E84) | I84: =H84 -> 0 | J84: =IF(K84="","",K84*$E84) | L84: =K84+I84 -> 0 | M84: =IF(N84="","",N84*$E84) | O84: =N84+L84 -> 0 | P84: =IF(Q84="","",Q84*$E84) | R84: =Q84+O84 -> 0 | S84: =IF(T84="","",T84*$E84) | U84: =T84+R84 -> 0 | V84: =IF(W84="","",W84*$E84) | X84: =W84+U84 -> 0 | Y84: =IF(Z84="","",Z84*$E84) | AA84: =Z84+X84 -> 0 | AB84: =IF(AC84="","",AC84*$E84) | AD84: =AC84+AA84 -> 0 | AE84: =IF(AF84="","",AF84*$E84) | AG84: =AF84+AD84 -> 0 | AH84: =IF(AI84="","",AI84*$E84) | AJ84: =AI84+AG84 -> 0 | AK84: =IF(AL84="","",AL84*$E84) | AM84: =AL84+AJ84 -> 0 | AN84: =IF(AO84="","",AO84*$E84) | AP84: =AO84+AM84 -> 0 | AQ84: =IF(AR84="","",AR84*$E84) | AS84: =AR84+AP84 -> 0 | AT84: =IF(AU84="","",AU84*$E84) | AV84: =AU84+AS84 -> 0 | AW84: =IF(AX84="","",AX84*$E84) | AY84: =AX84+AV84 -> 0 | AZ84: =IF(BA84="","",BA84*$E84) | BB84: =BA84+AY84 -> 0 | BC84: =IF(BD84="","",BD84*$E84) | BE84: =BD84+BB84 -> 0 | BF84: =IF(BG84="","",BG84*$E84) | BH84: =BG84+BE84 -> 0 | BI84: =IF(BJ84="","",BJ84*$E84) | BK84: =BJ84+BH84 -> 0 | BL84: =IF(BM84="","",BM84*$E84) | BN84: =BM84+BK84 -> 0 | BO84: =IF(BP84="","",BP84*$E84) | BQ84: =BP84+BN84 -> 0 | BR84: =IF(BS84="","",BS84*$E84) | BT84: =BS84+BQ84 -> 0 | BU84: =IF(BV84="","",BV84*$E84) | BW84: =BV84+BT84 -> 0 | BX84: =IF(BY84="","",BY84*$E84) | BZ84: =BY84+BW84 -> 0 | CA84: =IF(CB84="","",CB84*$E84) | CC84: =CB84+BZ84 -> 0 | CD84: =IF(CE84="","",CE84*$E84) | CF84: =CE84+CC84 -> 0 | CG84: =IF(CH84="","",CH84*$E84) | CI84: =CH84+CF84 -> 0 | CJ84: =IF(CK84="","",CK84*$E84) | CL84: =CK84+CI84 -> 0 | CM84: =IF(CN84="","",CN84*$E84) | CO84: =CN84+CL84 -> 0 | CP84: =IF(CQ84="","",CQ84*$E84) | CR84: =CQ84+CO84 -> 0 | CS84: =IF(CT84="","",CT84*$E84) | CU84: =CT84+CR84 -> 0 | CV84: =IF(CW84="","",CW84*$E84) | CX84: =CW84+CU84 -> 0 | CY84: =IF(CZ84="","",CZ84*$E84) | DA84: =CZ84+CX84 -> 0 | DB84: =IF(DC84="","",DC84*$E84) | DD84: =DC84+DA84 -> 0 | DE84: =IF(DF84="","",DF84*$E84) | DG84: =DF84+DD84 -> 0 | DH84: =IF(DI84="","",DI84*$E84) | DJ84: =DI84+DG84 -> 0
A85: =LEFT(B85,1) -> 4 | B85: 4.1.2.3 | C85: =VLOOKUP(B85,'[49]PLANILHA ORCAMENTARIA'!A:B,2,0) -> CONTRAPISO - SETOR 3 | E85: =VLOOKUP(B85,'[49]PLANILHA ORCAMENTARIA'!A:G,7,0) -> 126010.97 | G85: =IF(H85="","",H85*$E85) | I85: =H85 -> 0 | J85: =IF(K85="","",K85*$E85) | L85: =K85+I85 -> 0 | M85: =IF(N85="","",N85*$E85) | O85: =N85+L85 -> 0 | P85: =IF(Q85="","",Q85*$E85) | R85: =Q85+O85 -> 0 | S85: =IF(T85="","",T85*$E85) | U85: =T85+R85 -> 0 | V85: =IF(W85="","",W85*$E85) | X85: =W85+U85 -> 0 | Y85: =IF(Z85="","",Z85*$E85) | AA85: =Z85+X85 -> 0 | AB85: =IF(AC85="","",AC85*$E85) | AD85: =AC85+AA85 -> 0 | AE85: =IF(AF85="","",AF85*$E85) | AG85: =AF85+AD85 -> 0 | AH85: =IF(AI85="","",AI85*$E85) | AJ85: =AI85+AG85 -> 0 | AK85: =IF(AL85="","",AL85*$E85) | AM85: =AL85+AJ85 -> 0 | AN85: =IF(AO85="","",AO85*$E85) | AP85: =AO85+AM85 -> 0 | AQ85: =IF(AR85="","",AR85*$E85) | AS85: =AR85+AP85 -> 0 | AT85: =IF(AU85="","",AU85*$E85) | AV85: =AU85+AS85 -> 0 | AW85: =IF(AX85="","",AX85*$E85) | AY85: =AX85+AV85 -> 0 | AZ85: =IF(BA85="","",BA85*$E85) | BB85: =BA85+AY85 -> 0 | BC85: =IF(BD85="","",BD85*$E85) | BE85: =BD85+BB85 -> 0 | BF85: =IF(BG85="","",BG85*$E85) | BH85: =BG85+BE85 -> 0 | BI85: =IF(BJ85="","",BJ85*$E85) | BK85: =BJ85+BH85 -> 0 | BL85: =IF(BM85="","",BM85*$E85) | BN85: =BM85+BK85 -> 0 | BO85: =IF(BP85="","",BP85*$E85) | BQ85: =BP85+BN85 -> 0 | BR85: =IF(BS85="","",BS85*$E85) | BT85: =BS85+BQ85 -> 0 | BU85: =IF(BV85="","",BV85*$E85) | BW85: =BV85+BT85 -> 0 | BX85: =IF(BY85="","",BY85*$E85) | BZ85: =BY85+BW85 -> 0 | CA85: =IF(CB85="","",CB85*$E85) | CC85: =CB85+BZ85 -> 0 | CD85: =IF(CE85="","",CE85*$E85) | CF85: =CE85+CC85 -> 0 | CG85: =IF(CH85="","",CH85*$E85) | CI85: =CH85+CF85 -> 0 | CJ85: =IF(CK85="","",CK85*$E85) | CL85: =CK85+CI85 -> 0 | CM85: =IF(CN85="","",CN85*$E85) | CO85: =CN85+CL85 -> 0 | CP85: =IF(CQ85="","",CQ85*$E85) | CR85: =CQ85+CO85 -> 0 | CS85: =IF(CT85="","",CT85*$E85) | CU85: =CT85+CR85 -> 0 | CV85: =IF(CW85="","",CW85*$E85) | CX85: =CW85+CU85 -> 0 | CY85: =IF(CZ85="","",CZ85*$E85) | DA85: =CZ85+CX85 -> 0 | DB85: =IF(DC85="","",DC85*$E85) | DD85: =DC85+DA85 -> 0 | DE85: =IF(DF85="","",DF85*$E85) | DG85: =DF85+DD85 -> 0 | DH85: =IF(DI85="","",DI85*$E85) | DJ85: =DI85+DG85 -> 0
A86: =LEFT(B86,1) -> 4 | B86: 4.1.2.4 | C86: =VLOOKUP(B86,'[49]PLANILHA ORCAMENTARIA'!A:B,2,0) -> PORCELANATO / REVESTIMENTO DE PISO - SETOR 1 | E86: =VLOOKUP(B86,'[49]PLANILHA ORCAMENTARIA'!A:G,7,0) -> 130350.7 | G86: =IF(H86="","",H86*$E86) | I86: =H86 -> 0 | J86: =IF(K86="","",K86*$E86) | L86: =K86+I86 -> 0 | M86: =IF(N86="","",N86*$E86) | O86: =N86+L86 -> 0 | P86: =IF(Q86="","",Q86*$E86) | R86: =Q86+O86 -> 0 | S86: =IF(T86="","",T86*$E86) | U86: =T86+R86 -> 0 | V86: =IF(W86="","",W86*$E86) | X86: =W86+U86 -> 0 | Y86: =IF(Z86="","",Z86*$E86) | AA86: =Z86+X86 -> 0 | AB86: =IF(AC86="","",AC86*$E86) | AD86: =AC86+AA86 -> 0 | AE86: =IF(AF86="","",AF86*$E86) | AG86: =AF86+AD86 -> 0 | AH86: =IF(AI86="","",AI86*$E86) | AJ86: =AI86+AG86 -> 0 | AK86: =IF(AL86="","",AL86*$E86) | AM86: =AL86+AJ86 -> 0 | AN86: =IF(AO86="","",AO86*$E86) | AP86: =AO86+AM86 -> 0 | AQ86: =IF(AR86="","",AR86*$E86) | AS86: =AR86+AP86 -> 0 | AT86: =IF(AU86="","",AU86*$E86) | AV86: =AU86+AS86 -> 0 | AW86: =IF(AX86="","",AX86*$E86) | AY86: =AX86+AV86 -> 0 | AZ86: =IF(BA86="","",BA86*$E86) | BB86: =BA86+AY86 -> 0 | BC86: =IF(BD86="","",BD86*$E86) | BE86: =BD86+BB86 -> 0 | BF86: =IF(BG86="","",BG86*$E86) | BH86: =BG86+BE86 -> 0 | BI86: =IF(BJ86="","",BJ86*$E86) | BK86: =BJ86+BH86 -> 0 | BL86: =IF(BM86="","",BM86*$E86) | BN86: =BM86+BK86 -> 0 | BO86: =IF(BP86="","",BP86*$E86) | BQ86: =BP86+BN86 -> 0 | BR86: =IF(BS86="","",BS86*$E86) | BT86: =BS86+BQ86 -> 0 | BU86: =IF(BV86="","",BV86*$E86) | BW86: =BV86+BT86 -> 0 | BX86: =IF(BY86="","",BY86*$E86) | BZ86: =BY86+BW86 -> 0 | CA86: =IF(CB86="","",CB86*$E86) | CC86: =CB86+BZ86 -> 0 | CD86: =IF(CE86="","",CE86*$E86) | CF86: =CE86+CC86 -> 0 | CG86: =IF(CH86="","",CH86*$E86) | CI86: =CH86+CF86 -> 0 | CJ86: =IF(CK86="","",CK86*$E86) | CL86: =CK86+CI86 -> 0 | CM86: =IF(CN86="","",CN86*$E86) | CO86: =CN86+CL86 -> 0 | CP86: =IF(CQ86="","",CQ86*$E86) | CR86: =CQ86+CO86 -> 0 | CS86: =IF(CT86="","",CT86*$E86) | CU86: =CT86+CR86 -> 0 | CV86: =IF(CW86="","",CW86*$E86) | CX86: =CW86+CU86 -> 0 | CY86: =IF(CZ86="","",CZ86*$E86) | DA86: =CZ86+CX86 -> 0 | DB86: =IF(DC86="","",DC86*$E86) | DD86: =DC86+DA86 -> 0 | DE86: =IF(DF86="","",DF86*$E86) | DG86: =DF86+DD86 -> 0 | DH86: =IF(DI86="","",DI86*$E86) | DJ86: =DI86+DG86 -> 0
A87: =LEFT(B87,1) -> 4 | B87: 4.1.2.5 | C87: =VLOOKUP(B87,'[49]PLANILHA ORCAMENTARIA'!A:B,2,0) -> PORCELANATO / REVESTIMENTO DE PISO - SETOR 2 | E87: =VLOOKUP(B87,'[49]PLANILHA ORCAMENTARIA'!A:G,7,0) -> 92749.93 | G87: =IF(H87="","",H87*$E87) | I87: =H87 -> 0 | J87: =IF(K87="","",K87*$E87) | L87: =K87+I87 -> 0 | M87: =IF(N87="","",N87*$E87) | O87: =N87+L87 -> 0 | P87: =IF(Q87="","",Q87*$E87) | R87: =Q87+O87 -> 0 | S87: =IF(T87="","",T87*$E87) | U87: =T87+R87 -> 0 | V87: =IF(W87="","",W87*$E87) | X87: =W87+U87 -> 0 | Y87: =IF(Z87="","",Z87*$E87) | AA87: =Z87+X87 -> 0 | AB87: =IF(AC87="","",AC87*$E87) | AD87: =AC87+AA87 -> 0 | AE87: =IF(AF87="","",AF87*$E87) | AG87: =AF87+AD87 -> 0 | AH87: =IF(AI87="","",AI87*$E87) | AJ87: =AI87+AG87 -> 0 | AK87: =IF(AL87="","",AL87*$E87) | AM87: =AL87+AJ87 -> 0 | AN87: =IF(AO87="","",AO87*$E87) | AP87: =AO87+AM87 -> 0 | AQ87: =IF(AR87="","",AR87*$E87) | AS87: =AR87+AP87 -> 0 | AT87: =IF(AU87="","",AU87*$E87) | AV87: =AU87+AS87 -> 0 | AW87: =IF(AX87="","",AX87*$E87) | AY87: =AX87+AV87 -> 0 | AZ87: =IF(BA87="","",BA87*$E87) | BB87: =BA87+AY87 -> 0 | BC87: =IF(BD87="","",BD87*$E87) | BE87: =BD87+BB87 -> 0 | BF87: =IF(BG87="","",BG87*$E87) | BH87: =BG87+BE87 -> 0 | BI87: =IF(BJ87="","",BJ87*$E87) | BK87: =BJ87+BH87 -> 0 | BL87: =IF(BM87="","",BM87*$E87) | BN87: =BM87+BK87 -> 0 | BO87: =IF(BP87="","",BP87*$E87) | BQ87: =BP87+BN87 -> 0 | BR87: =IF(BS87="","",BS87*$E87) | BT87: =BS87+BQ87 -> 0 | BU87: =IF(BV87="","",BV87*$E87) | BW87: =BV87+BT87 -> 0 | BX87: =IF(BY87="","",BY87*$E87) | BZ87: =BY87+BW87 -> 0 | CA87: =IF(CB87="","",CB87*$E87) | CC87: =CB87+BZ87 -> 0 | CD87: =IF(CE87="","",CE87*$E87) | CF87: =CE87+CC87 -> 0 | CG87: =IF(CH87="","",CH87*$E87) | CI87: =CH87+CF87 -> 0 | CJ87: =IF(CK87="","",CK87*$E87) | CL87: =CK87+CI87 -> 0 | CM87: =IF(CN87="","",CN87*$E87) | CO87: =CN87+CL87 -> 0 | CP87: =IF(CQ87="","",CQ87*$E87) | CR87: =CQ87+CO87 -> 0 | CS87: =IF(CT87="","",CT87*$E87) | CU87: =CT87+CR87 -> 0 | CV87: =IF(CW87="","",CW87*$E87) | CX87: =CW87+CU87 -> 0 | CY87: =IF(CZ87="","",CZ87*$E87) | DA87: =CZ87+CX87 -> 0 | DB87: =IF(DC87="","",DC87*$E87) | DD87: =DC87+DA87 -> 0 | DE87: =IF(DF87="","",DF87*$E87) | DG87: =DF87+DD87 -> 0 | DH87: =IF(DI87="","",DI87*$E87) | DJ87: =DI87+DG87 -> 0
A88: =LEFT(B88,1) -> 4 | B88: 4.1.2.6 | C88: =VLOOKUP(B88,'[49]PLANILHA ORCAMENTARIA'!A:B,2,0) -> PORCELANATO / REVESTIMENTO DE PISO - SETOR 3 | E88: =VLOOKUP(B88,'[49]PLANILHA ORCAMENTARIA'!A:G,7,0) -> 118692.81 | G88: =IF(H88="","",H88*$E88) | I88: =H88 -> 0 | J88: =IF(K88="","",K88*$E88) | L88: =K88+I88 -> 0 | M88: =IF(N88="","",N88*$E88) | O88: =N88+L88 -> 0 | P88: =IF(Q88="","",Q88*$E88) | R88: =Q88+O88 -> 0 | S88: =IF(T88="","",T88*$E88) | U88: =T88+R88 -> 0 | V88: =IF(W88="","",W88*$E88) | X88: =W88+U88 -> 0 | Y88: =IF(Z88="","",Z88*$E88) | AA88: =Z88+X88 -> 0 | AB88: =IF(AC88="","",AC88*$E88) | AD88: =AC88+AA88 -> 0 | AE88: =IF(AF88="","",AF88*$E88) | AG88: =AF88+AD88 -> 0 | AH88: =IF(AI88="","",AI88*$E88) | AJ88: =AI88+AG88 -> 0 | AK88: =IF(AL88="","",AL88*$E88) | AM88: =AL88+AJ88 -> 0 | AN88: =IF(AO88="","",AO88*$E88) | AP88: =AO88+AM88 -> 0 | AQ88: =IF(AR88="","",AR88*$E88) | AS88: =AR88+AP88 -> 0 | AT88: =IF(AU88="","",AU88*$E88) | AV88: =AU88+AS88 -> 0 | AW88: =IF(AX88="","",AX88*$E88) | AY88: =AX88+AV88 -> 0 | AZ88: =IF(BA88="","",BA88*$E88) | BB88: =BA88+AY88 -> 0 | BC88: =IF(BD88="","",BD88*$E88) | BE88: =BD88+BB88 -> 0 | BF88: =IF(BG88="","",BG88*$E88) | BH88: =BG88+BE88 -> 0 | BI88: =IF(BJ88="","",BJ88*$E88) | BK88: =BJ88+BH88 -> 0 | BL88: =IF(BM88="","",BM88*$E88) | BN88: =BM88+BK88 -> 0 | BO88: =IF(BP88="","",BP88*$E88) | BQ88: =BP88+BN88 -> 0 | BR88: =IF(BS88="","",BS88*$E88) | BT88: =BS88+BQ88 -> 0 | BU88: =IF(BV88="","",BV88*$E88) | BW88: =BV88+BT88 -> 0 | BX88: =IF(BY88="","",BY88*$E88) | BZ88: =BY88+BW88 -> 0 | CA88: =IF(CB88="","",CB88*$E88) | CC88: =CB88+BZ88 -> 0 | CD88: =IF(CE88="","",CE88*$E88) | CF88: =CE88+CC88 -> 0 | CG88: =IF(CH88="","",CH88*$E88) | CI88: =CH88+CF88 -> 0 | CJ88: =IF(CK88="","",CK88*$E88) | CL88: =CK88+CI88 -> 0 | CM88: =IF(CN88="","",CN88*$E88) | CO88: =CN88+CL88 -> 0 | CP88: =IF(CQ88="","",CQ88*$E88) | CR88: =CQ88+CO88 -> 0 | CS88: =IF(CT88="","",CT88*$E88) | CU88: =CT88+CR88 -> 0 | CV88: =IF(CW88="","",CW88*$E88) | CX88: =CW88+CU88 -> 0 | CY88: =IF(CZ88="","",CZ88*$E88) | DA88: =CZ88+CX88 -> 0 | DB88: =IF(DC88="","",DC88*$E88) | DD88: =DC88+DA88 -> 0 | DE88: =IF(DF88="","",DF88*$E88) | DG88: =DF88+DD88 -> 0 | DH88: =IF(DI88="","",DI88*$E88) | DJ88: =DI88+DG88 -> 0
A89: =LEFT(B89,1) -> 4 | B89: 4.1.2.7 | C89: =VLOOKUP(B89,'[49]PLANILHA ORCAMENTARIA'!A:B,2,0) -> REJUNTE / RODAPÉ / SOLEIRA | E89: =VLOOKUP(B89,'[49]PLANILHA ORCAMENTARIA'!A:G,7,0) -> 11192.67 | G89: =IF(H89="","",H89*$E89) | I89: =H89 -> 0 | J89: =IF(K89="","",K89*$E89) | L89: =K89+I89 -> 0 | M89: =IF(N89="","",N89*$E89) | O89: =N89+L89 -> 0 | P89: =IF(Q89="","",Q89*$E89) | R89: =Q89+O89 -> 0 | S89: =IF(T89="","",T89*$E89) | U89: =T89+R89 -> 0 | V89: =IF(W89="","",W89*$E89) | X89: =W89+U89 -> 0 | Y89: =IF(Z89="","",Z89*$E89) | AA89: =Z89+X89 -> 0 | AB89: =IF(AC89="","",AC89*$E89) | AD89: =AC89+AA89 -> 0 | AE89: =IF(AF89="","",AF89*$E89) | AG89: =AF89+AD89 -> 0 | AH89: =IF(AI89="","",AI89*$E89) | AJ89: =AI89+AG89 -> 0 | AK89: =IF(AL89="","",AL89*$E89) | AM89: =AL89+AJ89 -> 0 | AN89: =IF(AO89="","",AO89*$E89) | AP89: =AO89+AM89 -> 0 | AQ89: =IF(AR89="","",AR89*$E89) | AS89: =AR89+AP89 -> 0 | AT89: =IF(AU89="","",AU89*$E89) | AV89: =AU89+AS89 -> 0 | AW89: =IF(AX89="","",AX89*$E89) | AY89: =AX89+AV89 -> 0 | AZ89: =IF(BA89="","",BA89*$E89) | BB89: =BA89+AY89 -> 0 | BC89: =IF(BD89="","",BD89*$E89) | BE89: =BD89+BB89 -> 0 | BF89: =IF(BG89="","",BG89*$E89) | BH89: =BG89+BE89 -> 0 | BI89: =IF(BJ89="","",BJ89*$E89) | BK89: =BJ89+BH89 -> 0 | BL89: =IF(BM89="","",BM89*$E89) | BN89: =BM89+BK89 -> 0 | BO89: =IF(BP89="","",BP89*$E89) | BQ89: =BP89+BN89 -> 0 | BR89: =IF(BS89="","",BS89*$E89) | BT89: =BS89+BQ89 -> 0 | BU89: =IF(BV89="","",BV89*$E89) | BW89: =BV89+BT89 -> 0 | BX89: =IF(BY89="","",BY89*$E89) | BZ89: =BY89+BW89 -> 0 | CA89: =IF(CB89="","",CB89*$E89) | CC89: =CB89+BZ89 -> 0 | CD89: =IF(CE89="","",CE89*$E89) | CF89: =CE89+CC89 -> 0 | CG89: =IF(CH89="","",CH89*$E89) | CI89: =CH89+CF89 -> 0 | CJ89: =IF(CK89="","",CK89*$E89) | CL89: =CK89+CI89 -> 0 | CM89: =IF(CN89="","",CN89*$E89) | CO89: =CN89+CL89 -> 0 | CP89: =IF(CQ89="","",CQ89*$E89) | CR89: =CQ89+CO89 -> 0 | CS89: =IF(CT89="","",CT89*$E89) | CU89: =CT89+CR89 -> 0 | CV89: =IF(CW89="","",CW89*$E89) | CX89: =CW89+CU89 -> 0 | CY89: =IF(CZ89="","",CZ89*$E89) | DA89: =CZ89+CX89 -> 0 | DB89: =IF(DC89="","",DC89*$E89) | DD89: =DC89+DA89 -> 0 | DE89: =IF(DF89="","",DF89*$E89) | DG89: =DF89+DD89 -> 0 | DH89: =IF(DI89="","",DI89*$E89) | DJ89: =DI89+DG89 -> 0
A90: =LEFT(B90,1) -> 4 | B90: 4.1.3 | C90: PISOS - 2 ANDAR | E90: =VLOOKUP(B90,'[49]PLANILHA ORCAMENTARIA'!A:G,7,0) -> 911670.73
A91: =LEFT(B91,1) -> 4 | B91: 4.1.3.1 | C91: =VLOOKUP(B91,'[49]PLANILHA ORCAMENTARIA'!A:B,2,0) -> CONTRAPISO - SETOR 1 | E91: =VLOOKUP(B91,'[49]PLANILHA ORCAMENTARIA'!A:G,7,0) -> 123761.67 | G91: =IF(H91="","",H91*$E91) | I91: =H91 -> 0 | J91: =IF(K91="","",K91*$E91) | L91: =K91+I91 -> 0 | M91: =IF(N91="","",N91*$E91) | O91: =N91+L91 -> 0 | P91: =IF(Q91="","",Q91*$E91) | R91: =Q91+O91 -> 0 | S91: =IF(T91="","",T91*$E91) | U91: =T91+R91 -> 0 | V91: =IF(W91="","",W91*$E91) | X91: =W91+U91 -> 0 | Y91: =IF(Z91="","",Z91*$E91) | AA91: =Z91+X91 -> 0 | AB91: =IF(AC91="","",AC91*$E91) | AD91: =AC91+AA91 -> 0 | AE91: =IF(AF91="","",AF91*$E91) | AG91: =AF91+AD91 -> 0 | AH91: =IF(AI91="","",AI91*$E91) | AJ91: =AI91+AG91 -> 0 | AK91: =IF(AL91="","",AL91*$E91) | AM91: =AL91+AJ91 -> 0 | AN91: =IF(AO91="","",AO91*$E91) | AP91: =AO91+AM91 -> 0 | AQ91: =IF(AR91="","",AR91*$E91) | AS91: =AR91+AP91 -> 0 | AT91: =IF(AU91="","",AU91*$E91) | AV91: =AU91+AS91 -> 0 | AW91: =IF(AX91="","",AX91*$E91) | AY91: =AX91+AV91 -> 0 | AZ91: =IF(BA91="","",BA91*$E91) | BB91: =BA91+AY91 -> 0 | BC91: =IF(BD91="","",BD91*$E91) | BE91: =BD91+BB91 -> 0 | BF91: =IF(BG91="","",BG91*$E91) | BH91: =BG91+BE91 -> 0 | BI91: =IF(BJ91="","",BJ91*$E91) | BK91: =BJ91+BH91 -> 0 | BL91: =IF(BM91="","",BM91*$E91) | BN91: =BM91+BK91 -> 0 | BO91: =IF(BP91="","",BP91*$E91) | BQ91: =BP91+BN91 -> 0 | BR91: =IF(BS91="","",BS91*$E91) | BT91: =BS91+BQ91 -> 0 | BU91: =IF(BV91="","",BV91*$E91) | BW91: =BV91+BT91 -> 0 | BX91: =IF(BY91="","",BY91*$E91) | BZ91: =BY91+BW91 -> 0 | CA91: =IF(CB91="","",CB91*$E91) | CC91: =CB91+BZ91 -> 0 | CD91: =IF(CE91="","",CE91*$E91) | CF91: =CE91+CC91 -> 0 | CG91: =IF(CH91="","",CH91*$E91) | CI91: =CH91+CF91 -> 0 | CJ91: =IF(CK91="","",CK91*$E91) | CL91: =CK91+CI91 -> 0 | CM91: =IF(CN91="","",CN91*$E91) | CO91: =CN91+CL91 -> 0 | CP91: =IF(CQ91="","",CQ91*$E91) | CR91: =CQ91+CO91 -> 0 | CS91: =IF(CT91="","",CT91*$E91) | CU91: =CT91+CR91 -> 0 | CV91: =IF(CW91="","",CW91*$E91) | CX91: =CW91+CU91 -> 0 | CY91: =IF(CZ91="","",CZ91*$E91) | DA91: =CZ91+CX91 -> 0 | DB91: =IF(DC91="","",DC91*$E91) | DD91: =DC91+DA91 -> 0 | DE91: =IF(DF91="","",DF91*$E91) | DG91: =DF91+DD91 -> 0 | DH91: =IF(DI91="","",DI91*$E91) | DJ91: =DI91+DG91 -> 0
A92: =LEFT(B92,1) -> 4 | B92: 4.1.3.2 | C92: =VLOOKUP(B92,'[49]PLANILHA ORCAMENTARIA'!A:B,2,0) -> CONTRAPISO - SETOR 2 | E92: =VLOOKUP(B92,'[49]PLANILHA ORCAMENTARIA'!A:G,7,0) -> 123651.37 | G92: =IF(H92="","",H92*$E92) | I92: =H92 -> 0 | J92: =IF(K92="","",K92*$E92) | L92: =K92+I92 -> 0 | M92: =IF(N92="","",N92*$E92) | O92: =N92+L92 -> 0 | P92: =IF(Q92="","",Q92*$E92) | R92: =Q92+O92 -> 0 | S92: =IF(T92="","",T92*$E92) | U92: =T92+R92 -> 0 | V92: =IF(W92="","",W92*$E92) | X92: =W92+U92 -> 0 | Y92: =IF(Z92="","",Z92*$E92) | AA92: =Z92+X92 -> 0 | AB92: =IF(AC92="","",AC92*$E92) | AD92: =AC92+AA92 -> 0 | AE92: =IF(AF92="","",AF92*$E92) | AG92: =AF92+AD92 -> 0 | AH92: =IF(AI92="","",AI92*$E92) | AJ92: =AI92+AG92 -> 0 | AK92: =IF(AL92="","",AL92*$E92) | AM92: =AL92+AJ92 -> 0 | AN92: =IF(AO92="","",AO92*$E92) | AP92: =AO92+AM92 -> 0 | AQ92: =IF(AR92="","",AR92*$E92) | AS92: =AR92+AP92 -> 0 | AT92: =IF(AU92="","",AU92*$E92) | AV92: =AU92+AS92 -> 0 | AW92: =IF(AX92="","",AX92*$E92) | AY92: =AX92+AV92 -> 0 | AZ92: =IF(BA92="","",BA92*$E92) | BB92: =BA92+AY92 -> 0 | BC92: =IF(BD92="","",BD92*$E92) | BE92: =BD92+BB92 -> 0 | BF92: =IF(BG92="","",BG92*$E92) | BH92: =BG92+BE92 -> 0 | BI92: =IF(BJ92="","",BJ92*$E92) | BK92: =BJ92+BH92 -> 0 | BL92: =IF(BM92="","",BM92*$E92) | BN92: =BM92+BK92 -> 0 | BO92: =IF(BP92="","",BP92*$E92) | BQ92: =BP92+BN92 -> 0 | BR92: =IF(BS92="","",BS92*$E92) | BT92: =BS92+BQ92 -> 0 | BU92: =IF(BV92="","",BV92*$E92) | BW92: =BV92+BT92 -> 0 | BX92: =IF(BY92="","",BY92*$E92) | BZ92: =BY92+BW92 -> 0 | CA92: =IF(CB92="","",CB92*$E92) | CC92: =CB92+BZ92 -> 0 | CD92: =IF(CE92="","",CE92*$E92) | CF92: =CE92+CC92 -> 0 | CG92: =IF(CH92="","",CH92*$E92) | CI92: =CH92+CF92 -> 0 | CJ92: =IF(CK92="","",CK92*$E92) | CL92: =CK92+CI92 -> 0 | CM92: =IF(CN92="","",CN92*$E92) | CO92: =CN92+CL92 -> 0 | CP92: =IF(CQ92="","",CQ92*$E92) | CR92: =CQ92+CO92 -> 0 | CS92: =IF(CT92="","",CT92*$E92) | CU92: =CT92+CR92 -> 0 | CV92: =IF(CW92="","",CW92*$E92) | CX92: =CW92+CU92 -> 0 | CY92: =IF(CZ92="","",CZ92*$E92) | DA92: =CZ92+CX92 -> 0 | DB92: =IF(DC92="","",DC92*$E92) | DD92: =DC92+DA92 -> 0 | DE92: =IF(DF92="","",DF92*$E92) | DG92: =DF92+DD92 -> 0 | DH92: =IF(DI92="","",DI92*$E92) | DJ92: =DI92+DG92 -> 0
A93: =LEFT(B93,1) -> 4 | B93: 4.1.3.3 | C93: =VLOOKUP(B93,'[49]PLANILHA ORCAMENTARIA'!A:B,2,0) -> CONTRAPISO - SETOR 3 | E93: =VLOOKUP(B93,'[49]PLANILHA ORCAMENTARIA'!A:G,7,0) -> 210822.63 | G93: =IF(H93="","",H93*$E93) | I93: =H93 -> 0 | J93: =IF(K93="","",K93*$E93) | L93: =K93+I93 -> 0 | M93: =IF(N93="","",N93*$E93) | O93: =N93+L93 -> 0 | P93: =IF(Q93="","",Q93*$E93) | R93: =Q93+O93 -> 0 | S93: =IF(T93="","",T93*$E93) | U93: =T93+R93 -> 0 | V93: =IF(W93="","",W93*$E93) | X93: =W93+U93 -> 0 | Y93: =IF(Z93="","",Z93*$E93) | AA93: =Z93+X93 -> 0 | AB93: =IF(AC93="","",AC93*$E93) | AD93: =AC93+AA93 -> 0 | AE93: =IF(AF93="","",AF93*$E93) | AG93: =AF93+AD93 -> 0 | AH93: =IF(AI93="","",AI93*$E93) | AJ93: =AI93+AG93 -> 0 | AK93: =IF(AL93="","",AL93*$E93) | AM93: =AL93+AJ93 -> 0 | AN93: =IF(AO93="","",AO93*$E93) | AP93: =AO93+AM93 -> 0 | AQ93: =IF(AR93="","",AR93*$E93) | AS93: =AR93+AP93 -> 0 | AT93: =IF(AU93="","",AU93*$E93) | AV93: =AU93+AS93 -> 0 | AW93: =IF(AX93="","",AX93*$E93) | AY93: =AX93+AV93 -> 0 | AZ93: =IF(BA93="","",BA93*$E93) | BB93: =BA93+AY93 -> 0 | BC93: =IF(BD93="","",BD93*$E93) | BE93: =BD93+BB93 -> 0 | BF93: =IF(BG93="","",BG93*$E93) | BH93: =BG93+BE93 -> 0 | BI93: =IF(BJ93="","",BJ93*$E93) | BK93: =BJ93+BH93 -> 0 | BL93: =IF(BM93="","",BM93*$E93) | BN93: =BM93+BK93 -> 0 | BO93: =IF(BP93="","",BP93*$E93) | BQ93: =BP93+BN93 -> 0 | BR93: =IF(BS93="","",BS93*$E93) | BT93: =BS93+BQ93 -> 0 | BU93: =IF(BV93="","",BV93*$E93) | BW93: =BV93+BT93 -> 0 | BX93: =IF(BY93="","",BY93*$E93) | BZ93: =BY93+BW93 -> 0 | CA93: =IF(CB93="","",CB93*$E93) | CC93: =CB93+BZ93 -> 0 | CD93: =IF(CE93="","",CE93*$E93) | CF93: =CE93+CC93 -> 0 | CG93: =IF(CH93="","",CH93*$E93) | CI93: =CH93+CF93 -> 0 | CJ93: =IF(CK93="","",CK93*$E93) | CL93: =CK93+CI93 -> 0 | CM93: =IF(CN93="","",CN93*$E93) | CO93: =CN93+CL93 -> 0 | CP93: =IF(CQ93="","",CQ93*$E93) | CR93: =CQ93+CO93 -> 0 | CS93: =IF(CT93="","",CT93*$E93) | CU93: =CT93+CR93 -> 0 | CV93: =IF(CW93="","",CW93*$E93) | CX93: =CW93+CU93 -> 0 | CY93: =IF(CZ93="","",CZ93*$E93) | DA93: =CZ93+CX93 -> 0 | DB93: =IF(DC93="","",DC93*$E93) | DD93: =DC93+DA93 -> 0 | DE93: =IF(DF93="","",DF93*$E93) | DG93: =DF93+DD93 -> 0 | DH93: =IF(DI93="","",DI93*$E93) | DJ93: =DI93+DG93 -> 0
A94: =LEFT(B94,1) -> 4 | B94: 4.1.3.4 | C94: =VLOOKUP(B94,'[49]PLANILHA ORCAMENTARIA'!A:B,2,0) -> PORCELANATO / REVESTIMENTO DE PISO - SETOR 1 | E94: =VLOOKUP(B94,'[49]PLANILHA ORCAMENTARIA'!A:G,7,0) -> 116574.14 | G94: =IF(H94="","",H94*$E94) | I94: =H94 -> 0 | J94: =IF(K94="","",K94*$E94) | L94: =K94+I94 -> 0 | M94: =IF(N94="","",N94*$E94) | O94: =N94+L94 -> 0 | P94: =IF(Q94="","",Q94*$E94) | R94: =Q94+O94 -> 0 | S94: =IF(T94="","",T94*$E94) | U94: =T94+R94 -> 0 | V94: =IF(W94="","",W94*$E94) | X94: =W94+U94 -> 0 | Y94: =IF(Z94="","",Z94*$E94) | AA94: =Z94+X94 -> 0 | AB94: =IF(AC94="","",AC94*$E94) | AD94: =AC94+AA94 -> 0 | AE94: =IF(AF94="","",AF94*$E94) | AG94: =AF94+AD94 -> 0 | AH94: =IF(AI94="","",AI94*$E94) | AJ94: =AI94+AG94 -> 0 | AK94: =IF(AL94="","",AL94*$E94) | AM94: =AL94+AJ94 -> 0 | AN94: =IF(AO94="","",AO94*$E94) | AP94: =AO94+AM94 -> 0 | AQ94: =IF(AR94="","",AR94*$E94) | AS94: =AR94+AP94 -> 0 | AT94: =IF(AU94="","",AU94*$E94) | AV94: =AU94+AS94 -> 0 | AW94: =IF(AX94="","",AX94*$E94) | AY94: =AX94+AV94 -> 0 | AZ94: =IF(BA94="","",BA94*$E94) | BB94: =BA94+AY94 -> 0 | BC94: =IF(BD94="","",BD94*$E94) | BE94: =BD94+BB94 -> 0 | BF94: =IF(BG94="","",BG94*$E94) | BH94: =BG94+BE94 -> 0 | BI94: =IF(BJ94="","",BJ94*$E94) | BK94: =BJ94+BH94 -> 0 | BL94: =IF(BM94="","",BM94*$E94) | BN94: =BM94+BK94 -> 0 | BO94: =IF(BP94="","",BP94*$E94) | BQ94: =BP94+BN94 -> 0 | BR94: =IF(BS94="","",BS94*$E94) | BT94: =BS94+BQ94 -> 0 | BU94: =IF(BV94="","",BV94*$E94) | BW94: =BV94+BT94 -> 0 | BX94: =IF(BY94="","",BY94*$E94) | BZ94: =BY94+BW94 -> 0 | CA94: =IF(CB94="","",CB94*$E94) | CC94: =CB94+BZ94 -> 0 | CD94: =IF(CE94="","",CE94*$E94) | CF94: =CE94+CC94 -> 0 | CG94: =IF(CH94="","",CH94*$E94) | CI94: =CH94+CF94 -> 0 | CJ94: =IF(CK94="","",CK94*$E94) | CL94: =CK94+CI94 -> 0 | CM94: =IF(CN94="","",CN94*$E94) | CO94: =CN94+CL94 -> 0 | CP94: =IF(CQ94="","",CQ94*$E94) | CR94: =CQ94+CO94 -> 0 | CS94: =IF(CT94="","",CT94*$E94) | CU94: =CT94+CR94 -> 0 | CV94: =IF(CW94="","",CW94*$E94) | CX94: =CW94+CU94 -> 0 | CY94: =IF(CZ94="","",CZ94*$E94) | DA94: =CZ94+CX94 -> 0 | DB94: =IF(DC94="","",DC94*$E94) | DD94: =DC94+DA94 -> 0 | DE94: =IF(DF94="","",DF94*$E94) | DG94: =DF94+DD94 -> 0 | DH94: =IF(DI94="","",DI94*$E94) | DJ94: =DI94+DG94 -> 0
A95: =LEFT(B95,1) -> 4 | B95: 4.1.3.5 | C95: =VLOOKUP(B95,'[49]PLANILHA ORCAMENTARIA'!A:B,2,0) -> PORCELANATO / REVESTIMENTO DE PISO - SETOR 2 | E95: =VLOOKUP(B95,'[49]PLANILHA ORCAMENTARIA'!A:G,7,0) -> 116470.26 | G95: =IF(H95="","",H95*$E95) | I95: =H95 -> 0 | J95: =IF(K95="","",K95*$E95) | L95: =K95+I95 -> 0 | M95: =IF(N95="","",N95*$E95) | O95: =N95+L95 -> 0 | P95: =IF(Q95="","",Q95*$E95) | R95: =Q95+O95 -> 0 | S95: =IF(T95="","",T95*$E95) | U95: =T95+R95 -> 0 | V95: =IF(W95="","",W95*$E95) | X95: =W95+U95 -> 0 | Y95: =IF(Z95="","",Z95*$E95) | AA95: =Z95+X95 -> 0 | AB95: =IF(AC95="","",AC95*$E95) | AD95: =AC95+AA95 -> 0 | AE95: =IF(AF95="","",AF95*$E95) | AG95: =AF95+AD95 -> 0 | AH95: =IF(AI95="","",AI95*$E95) | AJ95: =AI95+AG95 -> 0 | AK95: =IF(AL95="","",AL95*$E95) | AM95: =AL95+AJ95 -> 0 | AN95: =IF(AO95="","",AO95*$E95) | AP95: =AO95+AM95 -> 0 | AQ95: =IF(AR95="","",AR95*$E95) | AS95: =AR95+AP95 -> 0 | AT95: =IF(AU95="","",AU95*$E95) | AV95: =AU95+AS95 -> 0 | AW95: =IF(AX95="","",AX95*$E95) | AY95: =AX95+AV95 -> 0 | AZ95: =IF(BA95="","",BA95*$E95) | BB95: =BA95+AY95 -> 0 | BC95: =IF(BD95="","",BD95*$E95) | BE95: =BD95+BB95 -> 0 | BF95: =IF(BG95="","",BG95*$E95) | BH95: =BG95+BE95 -> 0 | BI95: =IF(BJ95="","",BJ95*$E95) | BK95: =BJ95+BH95 -> 0 | BL95: =IF(BM95="","",BM95*$E95) | BN95: =BM95+BK95 -> 0 | BO95: =IF(BP95="","",BP95*$E95) | BQ95: =BP95+BN95 -> 0 | BR95: =IF(BS95="","",BS95*$E95) | BT95: =BS95+BQ95 -> 0 | BU95: =IF(BV95="","",BV95*$E95) | BW95: =BV95+BT95 -> 0 | BX95: =IF(BY95="","",BY95*$E95) | BZ95: =BY95+BW95 -> 0 | CA95: =IF(CB95="","",CB95*$E95) | CC95: =CB95+BZ95 -> 0 | CD95: =IF(CE95="","",CE95*$E95) | CF95: =CE95+CC95 -> 0 | CG95: =IF(CH95="","",CH95*$E95) | CI95: =CH95+CF95 -> 0 | CJ95: =IF(CK95="","",CK95*$E95) | CL95: =CK95+CI95 -> 0 | CM95: =IF(CN95="","",CN95*$E95) | CO95: =CN95+CL95 -> 0 | CP95: =IF(CQ95="","",CQ95*$E95) | CR95: =CQ95+CO95 -> 0 | CS95: =IF(CT95="","",CT95*$E95) | CU95: =CT95+CR95 -> 0 | CV95: =IF(CW95="","",CW95*$E95) | CX95: =CW95+CU95 -> 0 | CY95: =IF(CZ95="","",CZ95*$E95) | DA95: =CZ95+CX95 -> 0 | DB95: =IF(DC95="","",DC95*$E95) | DD95: =DC95+DA95 -> 0 | DE95: =IF(DF95="","",DF95*$E95) | DG95: =DF95+DD95 -> 0 | DH95: =IF(DI95="","",DI95*$E95) | DJ95: =DI95+DG95 -> 0
A96: =LEFT(B96,1) -> 4 | B96: 4.1.3.6 | C96: =VLOOKUP(B96,'[49]PLANILHA ORCAMENTARIA'!A:B,2,0) -> PORCELANATO / REVESTIMENTO DE PISO - SETOR 3 | E96: =VLOOKUP(B96,'[49]PLANILHA ORCAMENTARIA'!A:G,7,0) -> 198579 | G96: =IF(H96="","",H96*$E96) | I96: =H96 -> 0 | J96: =IF(K96="","",K96*$E96) | L96: =K96+I96 -> 0 | M96: =IF(N96="","",N96*$E96) | O96: =N96+L96 -> 0 | P96: =IF(Q96="","",Q96*$E96) | R96: =Q96+O96 -> 0 | S96: =IF(T96="","",T96*$E96) | U96: =T96+R96 -> 0 | V96: =IF(W96="","",W96*$E96) | X96: =W96+U96 -> 0 | Y96: =IF(Z96="","",Z96*$E96) | AA96: =Z96+X96 -> 0 | AB96: =IF(AC96="","",AC96*$E96) | AD96: =AC96+AA96 -> 0 | AE96: =IF(AF96="","",AF96*$E96) | AG96: =AF96+AD96 -> 0 | AH96: =IF(AI96="","",AI96*$E96) | AJ96: =AI96+AG96 -> 0 | AK96: =IF(AL96="","",AL96*$E96) | AM96: =AL96+AJ96 -> 0 | AN96: =IF(AO96="","",AO96*$E96) | AP96: =AO96+AM96 -> 0 | AQ96: =IF(AR96="","",AR96*$E96) | AS96: =AR96+AP96 -> 0 | AT96: =IF(AU96="","",AU96*$E96) | AV96: =AU96+AS96 -> 0 | AW96: =IF(AX96="","",AX96*$E96) | AY96: =AX96+AV96 -> 0 | AZ96: =IF(BA96="","",BA96*$E96) | BB96: =BA96+AY96 -> 0 | BC96: =IF(BD96="","",BD96*$E96) | BE96: =BD96+BB96 -> 0 | BF96: =IF(BG96="","",BG96*$E96) | BH96: =BG96+BE96 -> 0 | BI96: =IF(BJ96="","",BJ96*$E96) | BK96: =BJ96+BH96 -> 0 | BL96: =IF(BM96="","",BM96*$E96) | BN96: =BM96+BK96 -> 0 | BO96: =IF(BP96="","",BP96*$E96) | BQ96: =BP96+BN96 -> 0 | BR96: =IF(BS96="","",BS96*$E96) | BT96: =BS96+BQ96 -> 0 | BU96: =IF(BV96="","",BV96*$E96) | BW96: =BV96+BT96 -> 0 | BX96: =IF(BY96="","",BY96*$E96) | BZ96: =BY96+BW96 -> 0 | CA96: =IF(CB96="","",CB96*$E96) | CC96: =CB96+BZ96 -> 0 | CD96: =IF(CE96="","",CE96*$E96) | CF96: =CE96+CC96 -> 0 | CG96: =IF(CH96="","",CH96*$E96) | CI96: =CH96+CF96 -> 0 | CJ96: =IF(CK96="","",CK96*$E96) | CL96: =CK96+CI96 -> 0 | CM96: =IF(CN96="","",CN96*$E96) | CO96: =CN96+CL96 -> 0 | CP96: =IF(CQ96="","",CQ96*$E96) | CR96: =CQ96+CO96 -> 0 | CS96: =IF(CT96="","",CT96*$E96) | CU96: =CT96+CR96 -> 0 | CV96: =IF(CW96="","",CW96*$E96) | CX96: =CW96+CU96 -> 0 | CY96: =IF(CZ96="","",CZ96*$E96) | DA96: =CZ96+CX96 -> 0 | DB96: =IF(DC96="","",DC96*$E96) | DD96: =DC96+DA96 -> 0 | DE96: =IF(DF96="","",DF96*$E96) | DG96: =DF96+DD96 -> 0 | DH96: =IF(DI96="","",DI96*$E96) | DJ96: =DI96+DG96 -> 0
